Workbook
Name _SCM01: #REF!
Name _SCM01: #REF!
Name _SCM02: #REF!
Name _SCM02: #REF!
Name ACCR1: #REF!
Name ACCR1: #REF!
Name accruals: #REF!
Name accruals: #REF!
Name adi_ars: #REF!
Name adi_ars: #REF!
Name ADI_less1m: #REF!
Name ADI_less1m: #REF!
Name adi_total_type: #REF!
Name adi_total_type: #REF!
Name adi_type_less1m: #REF!
Name adi_type_less1m: #REF!
Name adj: #REF!
Name adj: #REF!
Name AK: #REF!
Name AK: #REF!
Name AMMORT: #REF!:#REF!
Name AMMORT: #REF!:#REF!
Name Ammortamenti: #REF!:#REF!
Name Ammortamenti: #REF!:#REF!
Name Anag: #REF!
Name Anag: #REF!
Name anagr: #REF!
Name anagr: #REF!
Name ANAGRAFICA: #REF!
Name ANAGRAFICA: #REF!
Name answer: FALSE
Name ARS: #REF!
Name ARS: #REF!
Name ars_change: #REF!
Name ars_change: #REF!
Name AT: #REF!
Name AT: #REF!
Name AT15JAN: #REF!
Name AT15JAN: #REF!
Name ATAPR15: #REF!
Name ATAPR15: #REF!
Name ATAUG14: #REF!
Name ATAUG14: #REF!
Name ATAUG15: #REF!
Name ATAUG15: #REF!
Name ATDEC: #REF!
Name ATDEC: #REF!
Name ATDEC15: #REF!
Name ATDEC15: #REF!
Name ATDEC2: #REF!
Name ATDEC2: #REF!
Name ATDEC3: #REF!
Name ATDEC3: #REF!
Name ATDEC4: #REF!
Name ATDEC4: #REF!
Name ATFEB: #REF!
Name ATFEB: #REF!
Name ATFEB16: #REF!
Name ATFEB16: #REF!
Name ATfeb16corr: #REF!

Sheet Note
A1: Terms & Acronym:
A2: YTD | B2: Year to date refers to the period of time beginning the first day of the current calendar year up to the current date
A3: LY or PYTD | B3: Last year refers to the sameperiod of last year
A4: PY or FY'23 | B4: Sum of 12 month for the previous/past year or Full Year 2023
A5: Rolling L12M | B5: Previous year means Last 12 months of the reporting period
A6: YoY % Growth | B6: Rate of change used to compare the performance of a business over tow consecutive years

Sheet Delivery
A1: Customer Experience & Responsiveness
A2: On Time In Full (OTIF) (in %)
A3: (Orders delivered on time and in full​ / Total orders delivered) × 100
A4: BU | C4: 45688 | D4: 45716 | E4: 45747 | F4: 45777 | G4: 45808 | H4: 45838 | I4: 45869 | J4: 45900 | K4: 45930 | L4: 45961 | M4: 45991 | N4: 46022 | O4: 46053 | P4: 46081 | Q4: 46112 | R4: 46142 | S4: 46173 | T4: 46203 | U4: YTD | V4: TARGET | W4: +/- Vs trgt | X4: MoM% | Y4: FY'25 | Z4: % Var. Vs FY'25
A5: Safety | B5: OTIF 1st conf | C5: 0.5 | D5: 0.4 | E5: 0.7 | F5: 0 | G5: 0.33 | H5: 0.375 | I5: 1 | J5: 1 | K5: 0.57 | L5: 1 | M5: 1 | N5: 1 | O5: 0.5 | P5: 0.63 | Q5: 0.86 | R5: 0.36 | S5: 0.89 | T5: 0.2 | U5: 0.58333333 | V5: 0.83 | W5: =+U5-V5 -> -0.24666667 | X5: =IFERROR(T5/S5-1,100%) -> -0.7752809 | Y5: 0.73 | Z5: =+U5/Y5-1 -> -0.20091324
B6: MO count | C6: 6 | D6: 5 | E6: 10 | F6: 1 | G6: 9 | H6: 8 | I6: 19 | J6: 3 | K6: 7 | L6: 9 | M6: 14 | N6: 3 | O6: 8 | P6: 8 | Q6: 7 | R6: 11 | S6: 9 | T6: 5 | U6: =SUM(O6:T6) -> 48 | Y6: 94
A7: Leather | B7: OTIF 1st conf | C7: 0.11 | D7: 0.43 | E7: 0.92 | F7: 0 | G7: 0.46 | H7: 0.2 | I7: 0.78 | K7: 0.5 | L7: 1 | M7: 1 | N7: 1 | O7: 0.88 | P7: 0.38 | Q7: 1 | R7: 0 | S7: 0.25 | T7: 0.42857143 | U7: 0.55102041 | V7: 0.69 | W7: =+U7-V7 -> -0.13897959 | X7: =IFERROR(T7/S7-1,100%) -> 0.71428571 | Y7: 0.59 | Z7: =+U7/Y7-1 -> -0.066067105
B8: MO count | C8: 18 | D8: 7 | E8: 13 | F8: 4 | G8: 13 | H8: 5 | I8: 9 | J8: 0 | K8: 6 | L8: 9 | M8: 22 | N8: 3 | O8: 8 | P8: 8 | Q8: 10 | R8: 5 | S8: 4 | T8: 14 | U8: =SUM(O8:T8) -> 49 | Y8: 109
A9: D|air | B9: OTIF 1st conf | C9: 0.5 | D9: 0.78 | E9: 1 | F9: 0 | G9: 1 | H9: 1 | I9: 0.75 | J9: 1 | K9: 0.6 | L9: 1 | M9: 1 | N9: 1 | O9: 1 | P9: 1 | Q9: 1 | R9: 0.5 | S9: 1 | T9: 0.85714286 | U9: 0.89473684 | V9: 0.92 | W9: =+U9-V9 -> -0.025263158 | X9: =IFERROR(T9/S9-1,100%) -> -0.14285714 | Y9: 0.82 | Z9: =+U9/Y9-1 -> 0.09114249
B10: MO count | C10: 4 | D10: 9 | E10: 9 | F10: 0 | G10: 4 | H10: 5 | I10: 4 | J10: 5 | K10: 5 | L10: 2 | M10: 12 | N10: 1 | O10: 4 | P10: 3 | Q10: 2 | R10: 2 | S10: 1 | T10: 7 | U10: =SUM(O10:T10) -> 19 | Y10: 60
A11: OTIF 1st conf total | C11: 0.25 | D11: 0.57 | E11: 0.88 | F11: 0 | G11: 0.5 | H11: 0.5 | I11: 0.91 | J11: 1 | K11: 0.56 | L11: 1 | M11: 1 | N11: 1 | O11: 0.75 | P11: 0.58 | Q11: 0.95 | R11: 0.28 | S11: 0.71 | T11: 0.5 | U11: 0.62068966 | V11: 0.79 | W11: =+U11-V11 -> -0.16931034 | X11: =IFERROR(T11/S11-1,100%) -> -0.29577465 | Y11: 0.69 | Z11: =+U11/Y11-1 -> -0.10044978
A12: MO count total | C12: =SUM(C10,C8,C6) -> 28 | D12: =SUM(D10,D8,D6) -> 21 | E12: =SUM(E10,E8,E6) -> 32 | F12: =SUM(F10,F8,F6) -> 5 | G12: =SUM(G10,G8,G6) -> 26 | H12: =SUM(H10,H8,H6) -> 18 | I12: =SUM(I10,I8,I6) -> 32 | J12: =SUM(J10,J8,J6) -> 8 | ... U12: =SUM(U10,U8,U6) -> 116 | Y12: 263
A13: * It's agreed that all shipments in advance of the requested delivery date are accepted and don't create any negative signal to OTIF
A14: ** For OTIF only MOs not sent in time for MEL-T reasons are considered
A15: *** Shipment date + Transportation Lead Time ≤ Requested delivery date + 5 working days (agreed tolerance)
A16: Source: "OTIF_LT KPIs.xlsx"
A18: Lead Time (LT)
A19: LT Anticipo = Avvio - Partenza materiale // LT Produzione = Spedizione - Avvio // LT Totale End-to-End = Consegna - Partenza materiale
A20: BU | C20: 45688 | D20: 45716 | E20: 45747 | F20: 45777 | G20: 45777 | H20: 45838 | I20: 45869 | J20: 45900 | K20: 45930 | L20: 45961 | M20: 45991 | N20: 46022 | O20: 46053 | P20: 46081 | Q20: 46112 | R20: 46142 | S20: 46173 | T20: 46203 | U20: YTD | V20: TARGET | W20: +/- Vs trgt | X20: %Var. | Y20: MoM% | Z20: FY'25 | AA20: % Var. Vs FY'25
A21: Safety | B21: LT Anticipo | O21: 30 | P21: 28 | Q21: 82 | R21: 31 | S21: 54 | T21: 64.2 | U21: 45.520833 | V21: 90 | W21: =+U21-V21 -> -44.479167 | X21: =+U21/V21-1 -> -0.49421296 | Y21: =IFERROR(T21/S21-1,100%) -> 0.18888889
B22: LT Produzione | O22: 45 | P22: 55 | Q22: 30 | R22: 47 | S22: 27 | T22: 46.2 | U22: 41.5625 | V22: 30 | W22: =+U22-V22 -> 11.5625 | X22: =+U22/V22-1 -> 0.38541667 | Y22: =IFERROR(T22/S22-1,100%) -> 0.71111111
B23: LT End-to-End | O23: 78 | P23: 86 | Q23: 115 | R23: 81 | S23: 84 | T23: 114.4 | U23: 91.083333 | V23: 120 | W23: =+U23-V23 -> -28.916667 | X23: =+U23/V23-1 -> -0.24097222 | Y23: =IFERROR(T23/S23-1,100%) -> 0.36190476
A24: Leather | B24: LT Anticipo | O24: 16 | P24: 12 | Q24: 27 | R24: 51 | S24: 86 | T24: 43.714286 | U24: 34.714286 | V24: 90 | W24: =+U24-V24 -> -55.285714 | X24: =+U24/V24-1 -> -0.61428571 | Y24: =IFERROR(T24/S24-1,100%) -> -0.49169435
B25: LT Produzione | O25: 57 | P25: 76 | Q25: 67 | R25: 71 | S25: 66 | T25: 31.785714 | U25: 57.081633 | V25: 35 | W25: =+U25-V25 -> 22.081633 | X25: =+U25/V25-1 -> 0.63090379 | Y25: =IFERROR(T25/S25-1,100%) -> -0.51839827
B26: LT End-to-End | O26: 75 | P26: 91 | Q26: 97 | R26: 126 | S26: 155 | T26: 79.5 | U26: 95.795918 | V26: 125 | W26: =+U26-V26 -> -29.204082 | X26: =+U26/V26-1 -> -0.23363265 | Y26: =IFERROR(T26/S26-1,100%) -> -0.48709677
A27: D|air | B27: LT Anticipo | O27: 34 | P27: 47 | Q27: 81 | R27: 79 | S27: 69 | T27: 35.428571 | U27: 48.052632 | V27: 90 | W27: =+U27-V27 -> -41.947368 | X27: =+U27/V27-1 -> -0.46608187 | Y27: =IFERROR(T27/S27-1,100%) -> -0.48654244
B28: LT Produzione | O28: 31 | P28: 8 | Q28: 47 | R28: 35 | S28: 30 | T28: 17.571429 | U28: 24.315789 | V28: 15 | W28: =+U28-V28 -> 9.3157895 | X28: =+U28/V28-1 -> 0.62105263 | Y28: =IFERROR(T28/S28-1,100%) -> -0.41428571
B29: LT End-to-End | O29: 68 | P29: 58 | Q29: 130 | R29: 117 | S29: 102 | T29: 57 | U29: 76.368421 | V29: 105 | W29: =+U29-V29 -> -28.631579 | X29: =+U29/V29-1 -> -0.2726817 | Y29: =IFERROR(T29/S29-1,100%) -> -0.44117647
A30: LT Anticipo | O30: 25 | P30: 24 | Q30: 53 | R30: 42 | S30: 64 | T30: 45.423077 | U30: 41.37069 | V30: 90 | W30: =+U30-V30 -> -48.62931 | X30: =+U30/V30-1 -> -0.54032567 | Y30: =IFERROR(T30/S30-1,100%) -> -0.29026442
A31: LT Produzione | O31: 47 | P31: 56 | Q31: 51 | R31: 52 | S31: 38 | T31: 30.730769 | U31: 45.293103 | V31: 27 | W31: =+U31-V31 -> 18.293103 | X31: =+U31/V31-1 -> 0.67752235 | Y31: =IFERROR(T31/S31-1,100%) -> -0.19129555
A32: LT End-to-End | O32: 75 | P32: 84 | Q32: 107 | R32: 97 | S32: 106 | T32: 80.153846 | U32: 90.663793 | V32: 117 | W32: =+U32-V32 -> -26.336207 | X32: =+U32/V32-1 -> -0.22509579 | Y32: =IFERROR(T32/S32-1,100%) -> -0.24383164
A33: * LT Anticipo Pianificazione (gg): misura quanto stai anticipando quanto margine hai per ottimizzare trasporti
A34: ** LT Produzione: misura solo la parte interna efficienza fabbrica attese interne organizzazione
A35: *** LT End-to-End: è quello che il cliente “vive davvero”
A37: Service Level (SL) (in %)
A38: (Units sold of finished goods ÷ Budgeted units) × 100
A39: BU | C39: 45688 | D39: 45716 | E39: 45747 | F39: 45777 | G39: 45808 | H39: 45838 | I39: 45869 | J39: 45900 | K39: 45930 | L39: 45961 | M39: 45991 | N39: 46022 | O39: 46053 | P39: 46081 | Q39: 46112 | R39: 46142 | S39: 46173 | T39: 46203 | U39: YTD | V39: BDG | W39: +/- Vs bdg | X39: SL % | Y39: TARGET | Z39: %Var. Vs trgt | AA39: MoM% | AB39: PYTD | AC39: SL % FY'25 | AD39: YoY % | AE39: +/- SL Vs FY'25 | AF39: coda 2025 su 2026 | AG39: PLAN | AH39: +/- Vs pln | AI39: SL% Vs plan | AJ39: +/- Vs trgt | AL39: LM +/- Vs bdg | AM39: JUN Effect
A40: Safety | C40: 5638 | D40: 3715 | E40: 3194 | F40: 3425 | G40: 3102 | H40: 3170 | I40: 3939 | J40: 280 | K40: 3415 | L40: 3986 | M40: 5639 | N40: 2160 | O40: 4264 | P40: 2767 | Q40: 2252 | R40: 3232 | S40: 2300 | T40: 2003 | U40: =SUM(O40:T40) -> 16818 | V40: 25967 | W40: =+U40-V40 -> -9149 | X40: =IF(U40=0,"",(U40/V40)) -> 0.64766819 | Y40: 0.95 | Z40: =+X40/Y40-1 -> -0.31824401 | AA40: =IFERROR(T40/S40-1,100%) -> -0.12913043 | AB40: =SUM(C40:H40) -> 22244 | AC40: 0.81086394 | AD40: =IF(AB40=0,100%,U40/AB40-1) -> -0.24393095 | AE40: =+X40-AC40 -> -0.16319574 | AF40: -1537 | AH40: =+U40-AG40 -> 16818 | AI40: =IF(AG40=0,0,U40/AG40) -> 0 | AJ40: =IF(AG40=0,0,+AI40-Y40) -> 0 | AL40: -4222 | AM40: =+W40-AL40 -> -4927
A41: Leather | C41: 3500 | D41: 1499 | E41: 1449 | F41: 1381 | G41: 1487 | H41: 1697 | I41: 1481 | J41: 0 | K41: 1459 | L41: 2643 | M41: 1798 | N41: 573 | O41: 1812 | P41: 1149 | Q41: 1162 | R41: 961 | S41: 1536 | T41: 1706 | U41: =SUM(O41:T41) -> 8326 | V41: 9878 | W41: =+U41-V41 -> -1552 | X41: =IF(U41=0,"",(U41/V41)) -> 0.84288317 | Y41: 0.95 | Z41: =+X41/Y41-1 -> -0.11275455 | AA41: =IFERROR(T41/S41-1,100%) -> 0.11067708 | AB41: =SUM(C41:H41) -> 11013 | AC41: 0.97727741 | AD41: =IF(AB41=0,100%,U41/AB41-1) -> -0.24398438 | AE41: =+X41-AC41 -> -0.13439424 | AF41: -605 | AH41: =+U41-AG41 -> 8326 | AI41: =IF(AG41=0,0,U41/AG41) -> 0 | AJ41: =IF(AG41=0,0,+AI41-Y41) -> 0 | AL41: -1321 | AM41: =+W41-AL41 -> -231
A42: D|air | C42: 4358 | D42: 1723 | E42: 1283 | F42: 664 | G42: 1971 | H42: 904 | I42: 966 | J42: 620 | K42: 1420 | L42: 2182 | M42: 1950 | N42: 768 | O42: 1390 | P42: 816 | Q42: 877 | R42: 1076 | S42: 868 | T42: 1388 | U42: =SUM(O42:T42) -> 6415 | V42: 11271 | W42: =+U42-V42 -> -4856 | X42: =IF(U42=0,"",(U42/V42)) -> 0.56915979 | Y42: 0.95 | Z42: =+X42/Y42-1 -> -0.40088443 | AA42: =IFERROR(T42/S42-1,100%) -> 0.59907834 | AB42: =SUM(C42:H42) -> 10903 | AC42: 0.44674837 | AD42: =IF(AB42=0,100%,U42/AB42-1) -> -0.41162983 | AE42: =+X42-AC42 -> 0.12241142 | AF42: -325 | AH42: =+U42-AG42 -> 6415 | AI42: =IF(AG42=0,0,U42/AG42) -> 0 | AJ42: =IF(AG42=0,0,+AI42-Y42) -> 0 | AL42: -4344 | AM42: =+W42-AL42 -> -512
A43: MEL-T | C43: =SUM(C40:C42) -> 13496 | D43: =SUM(D40:D42) -> 6937 | E43: =SUM(E40:E42) -> 5926 | F43: =SUM(F40:F42) -> 5470 | G43: =SUM(G40:G42) -> 6560 | H43: =SUM(H40:H42) -> 5771 | I43: =SUM(I40:I42) -> 6386 | J43: =SUM(J40:J42) -> 900 | ... V43: =SUM(V40:V42) -> 47116 | W43: =+U43-V43 -> -15557 | X43: =IF(U43=0,"",(U43/V43)) -> 0.66981492 | Y43: 0.95 | Z43: =+X43/Y43-1 -> -0.29493166 | AA43: =IFERROR(T43/S43-1,100%) -> 0.083545918 | AB43: =SUM(AB40:AB42) -> 44160 | AC43: 0.70367877 | AD43: =IF(AB43=0,100%,U43/AB43-1) -> -0.28534873 | AE43: =+X43-AC43 -> -0.033863845 | AF43: =SUM(AF40:AF42) -> -2467 | AG43: =SUM(AG40:AG42) -> 0 | AH43: =+U43-AG43 -> 31559 | AI43: =IF(AG43=0,0,U43/AG43) -> 0 | AJ43: =IF(AG43=0,0,+AI43-Y43) -> 0 | AL43: =SUM(AL40:AL42) -> -9887 | AM43: =+W43-AL43 -> -5670
A44: Source: "KPIs.xlsx" | W44: =+W43/V43 -> -0.33018508
A46: Apparel – Customer Quality Rate (CQR) (in %)
A47: 1 - (Customer defective units / Units sold) × 100
A48: Customer Claims
A49: Total number of external customer claims recorded
A50: BU | C50: 45688 | D50: 45716 | E50: 45747 | F50: 45777 | G50: 45808 | H50: 45838 | I50: 45869 | J50: 45900 | K50: 45930 | L50: 45961 | M50: 45991 | N50: 46022 | O50: 46053 | P50: 46081 | Q50: 46112 | R50: 46142 | S50: 46173 | T50: 46203 | U50: YTD | V50: TARGET | W50: +/- Vs trgt | X50: FY'25 | Y50: % Var. Vs FY'25
A51: Safety | B51: # Units sold | C51: =+C40 -> 5638 | D51: =+D40 -> 3715 | E51: =+E40 -> 3194 | F51: =+F40 -> 3425 | G51: =+G40 -> 3102 | H51: =+H40 -> 3170 | I51: =+I40 -> 3939 | J51: =+J40 -> 280 | ... T51: =+T40 -> 2003 | U51: =SUM(O51:T51) -> 16818 | X51: 41663
B52: # Defective units | C52: 0 | D52: 0 | E52: 0 | F52: 0 | G52: 5 | H52: 0 | I52: 0 | J52: 0 | K52: 16 | L52: 0 | M52: 1 | N52: 0 | O52: 0 | P52: 0 | Q52: 0 | R52: 0 | S52: 0 | T52: 0 | U52: =SUM(O52:T52) -> 0 | X52: 22
B53: CRR% | C53: =IF(C51=0,0,C52/C51) -> 0 | D53: =IF(D51=0,0,D52/D51) -> 0 | E53: =IF(E51=0,0,E52/E51) -> 0 | F53: =IF(F51=0,0,F52/F51) -> 0 | G53: =IF(G51=0,0,G52/G51) -> 0.0016118633 | H53: =IF(H51=0,0,H52/H51) -> 0 | I53: =IF(I51=0,0,I52/I51) -> 0 | J53: =IF(J51=0,0,J52/J51) -> 0 | ... T53: =IF(T51=0,0,T52/T51) -> 0 | U53: =+U52/U51 -> 0 | V53: 0.005 | W53: =U53-V53 -> -0.005 | X53: 0.00052804647 | Y53: =IFERROR((U53/X53)-1,0) -> -1
B54: Customer Claims | C54: 0 | D54: 0 | E54: 0 | F54: 0 | G54: 1 | H54: 0 | I54: 0 | J54: 0 | K54: 2 | L54: 0 | M54: 2 | N54: 0 | O54: 0 | P54: 0 | Q54: 0 | R54: 0 | S54: 0 | T54: 0 | U54: =SUM(O54:T54) -> 0 | X54: 5 | Y54: =+U54-X54 -> -5
A55: Leather | B55: # Units sold | C55: =+C41 -> 3500 | D55: =+D41 -> 1499 | E55: =+E41 -> 1449 | F55: =+F41 -> 1381 | G55: =+G41 -> 1487 | H55: =+H41 -> 1697 | I55: =+I41 -> 1481 | J55: =+J41 -> 0 | ... T55: =+T41 -> 1706 | U55: =SUM(O55:T55) -> 8326 | X55: 18967
B56: # Defective units | C56: 0 | D56: 0 | E56: 0 | F56: 0 | G56: 0 | H56: 0 | I56: 0 | J56: 0 | K56: 0 | L56: 0 | M56: 0 | N56: 0 | O56: 0 | P56: 0 | Q56: 0 | R56: 40 | S56: 0 | T56: 0 | U56: =SUM(O56:T56) -> 40 | X56: 0
B57: CRR% | C57: =IF(C55=0,0,C56/C55) -> 0 | D57: =IF(D55=0,0,D56/D55) -> 0 | E57: =IF(E55=0,0,E56/E55) -> 0 | F57: =IF(F55=0,0,F56/F55) -> 0 | G57: =IF(G55=0,0,G56/G55) -> 0 | H57: =IF(H55=0,0,H56/H55) -> 0 | I57: =IF(I55=0,0,I56/I55) -> 0 | J57: =IF(J55=0,0,J56/J55) -> 0 | ... T57: =IF(T55=0,0,T56/T55) -> 0 | U57: =+U56/U55 -> 0.0048042277 | V57: 0.005 | W57: =U57-V57 -> -0.00019577228 | X57: 0 | Y57: =IFERROR((U57/X57)-1,0) -> 0
B58: Customer Claims | C58: 0 | D58: 0 | E58: 0 | F58: 0 | G58: 0 | H58: 0 | I58: 0 | J58: 0 | K58: 0 | L58: 0 | M58: 0 | N58: 0 | O58: 0 | P58: 0 | Q58: 0 | R58: 1 | S58: 0 | T58: 0 | U58: =SUM(O58:T58) -> 1 | X58: 0 | Y58: =+U58-X58 -> 1
A59: D|air | B59: # Units sold | C59: =+C42 -> 4358 | D59: =+D42 -> 1723 | E59: =+E42 -> 1283 | F59: =+F42 -> 664 | G59: =+G42 -> 1971 | H59: =+H42 -> 904 | I59: =+I42 -> 966 | J59: =+J42 -> 620 | ... T59: =+T42 -> 1388 | U59: =SUM(O59:T59) -> 6415 | X59: 18809
B60: # Defective units | C60: 1 | D60: 1 | E60: 0 | F60: 0 | G60: 3 | H60: 0 | I60: 0 | J60: 0 | K60: 0 | L60: 0 | M60: 9 | N60: 0 | O60: 0 | P60: 1 | Q60: 0 | R60: 0 | S60: 0 | T60: 0 | U60: =SUM(O60:T60) -> 1 | X60: 14
B61: CRR% | C61: =IF(C59=0,0,C60/C59) -> 0.00022946306 | D61: =IF(D59=0,0,D60/D59) -> 0.00058038305 | E61: =IF(E59=0,0,E60/E59) -> 0 | F61: =IF(F59=0,0,F60/F59) -> 0 | G61: =IF(G59=0,0,G60/G59) -> 0.00152207 | H61: =IF(H59=0,0,H60/H59) -> 0 | I61: =IF(I59=0,0,I60/I59) -> 0 | J61: =IF(J59=0,0,J60/J59) -> 0 | ... T61: =IF(T59=0,0,T60/T59) -> 0 | U61: =+U60/U59 -> 0.00015588465 | V61: 0.005 | W61: =U61-V61 -> -0.0048441154 | X61: 0.00074432453 | Y61: =IFERROR((U61/X61)-1,0) -> -0.79056898
B62: Customer Claims | C62: 1 | D62: 1 | E62: 0 | F62: 0 | G62: 1 | H62: 0 | I62: 0 | J62: 0 | K62: 0 | L62: 0 | M62: 1 | N62: 0 | O62: 0 | P62: 1 | Q62: 0 | R62: 0 | S62: 0 | T62: 0 | U62: =SUM(O62:T62) -> 1 | X62: 4 | Y62: =+U62-X62 -> -3
A63: # Units sold total | C63: =SUM(C51,C55,C59) -> 13496 | D63: =SUM(D51,D55,D59) -> 6937 | E63: =SUM(E51,E55,E59) -> 5926 | F63: =SUM(F51,F55,F59) -> 5470 | G63: =SUM(G51,G55,G59) -> 6560 | H63: =SUM(H51,H55,H59) -> 5771 | I63: =SUM(I51,I55,I59) -> 6386 | J63: =SUM(J51,J55,J59) -> 900 | ... T63: =SUM(T51,T55,T59) -> 5097 | U63: =SUM(O63:T63) -> 31559 | X63: 79439
A64: # Defective units total | C64: =SUM(C52,C56,C60) -> 1 | D64: =SUM(D52,D56,D60) -> 1 | E64: =SUM(E52,E56,E60) -> 0 | F64: =SUM(F52,F56,F60) -> 0 | G64: =SUM(G52,G56,G60) -> 8 | H64: =SUM(H52,H56,H60) -> 0 | I64: =SUM(I52,I56,I60) -> 0 | J64: =SUM(J52,J56,J60) -> 0 | ... T64: =SUM(T52,T56,T60) -> 0 | U64: =SUM(O64:T64) -> 41 | X64: 36
A65: CRR% Customer reject rate | C65: =IF(C63=0,0,C64/C63) -> 7.4096028e-05 | D65: =IF(D63=0,0,D64/D63) -> 0.00014415453 | E65: =IF(E63=0,0,E64/E63) -> 0 | F65: =IF(F63=0,0,F64/F63) -> 0 | G65: =IF(G63=0,0,G64/G63) -> 0.0012195122 | H65: =IF(H63=0,0,H64/H63) -> 0 | I65: =IF(I63=0,0,I64/I63) -> 0 | J65: =IF(J63=0,0,J64/J63) -> 0 | ... T65: =IF(T63=0,0,T64/T63) -> 0 | U65: =+U64/U63 -> 0.001299154 | V65: 0.005 | W65: =U65-V65 -> -0.003700846 | X65: 0.00045317791 | Y65: =IFERROR((U65/X65)-1,0) -> 1.8667637
A66: CQR% Customer quality rate | C66: =1-C65 -> 0.9999259 | D66: =1-D65 -> 0.99985585 | E66: =1-E65 -> 1 | F66: =1-F65 -> 1 | G66: =1-G65 -> 0.99878049 | H66: =1-H65 -> 1 | I66: =1-I65 -> 1 | J66: =1-J65 -> 1 | ... U66: =1-U65 -> 0.99870085 | V66: 0.995 | W66: =U66-V66 -> 0.003700846 | X66: 0.99954682
A67: DPMU (ppm) | C67: =(C64/C63)*10^6 -> 74.096028 | D67: =(D64/D63)*10^6 -> 144.15453 | E67: =(E64/E63)*10^6 -> 0 | F67: =(F64/F63)*10^6 -> 0 | G67: =(G64/G63)*10^6 -> 1219.5122 | H67: =(H64/H63)*10^6 -> 0 | I67: =(I64/I63)*10^6 -> 0 | J67: =(J64/J63)*10^6 -> 0 | ... U67: =(U64/U63)*10^6 -> 1299.154 | V67: <6.000 | W67: =+U67-5999 -> -4699.846 | X67: 453.17791
A68: Customer Claims total | C68: =SUM(C54,C58,C62) -> 1 | D68: =SUM(D54,D58,D62) -> 1 | E68: =SUM(E54,E58,E62) -> 0 | F68: =SUM(F54,F58,F62) -> 0 | G68: =SUM(G54,G58,G62) -> 2 | H68: =SUM(H54,H58,H62) -> 0 | I68: =SUM(I54,I58,I62) -> 0 | J68: =SUM(J54,J58,J62) -> 0 | ... U68: =SUM(U54,U58,U62) -> 2 | V68: 4 | W68: =U68-V68 -> -2 | X68: 9 | Y68: =+U68-X68 -> -7
A69: Source: "Qualipro"

Sheet People
A1: Employee Retention & Productivity
A2: Overall Turnover rate (in %)
A3: (Terminations during period / Employees at period start) × 100
A4: BU | E4: 45838 | F4: 45869 | G4: 45900 | H4: 45930 | I4: 45961 | J4: 45991 | K4: 46022 | L4: 46053 | M4: 46081 | N4: 46112 | O4: 46142 | P4: 46173 | Q4: 46203 | R4: 46234 | S4: TARGET | T4: YoY%
A5: Safety | B5: Employees at Beginning | E5: 36 | F5: =+E5+E7+E8-E6 -> 36 | G5: =+F5+F7+F8-F6 -> 34 | H5: =+G5+G7+G8-G6 -> 34 | I5: =+H5+H7+H8-H6 -> 34 | J5: =+I5+I7+I8-I6 -> 33 | K5: =+J5+J7+J8-J6 -> 36 | L5: =+K5+K7+K8-K6 -> 34 | M5: =+L5+L7+L8-L6 -> 27 | ... R5: =+Q5+Q7+Q8-Q6 -> 32
A6: Safety | B6: Terminations | E6: 1 | F6: 4 | G6: 0 | H6: 2 | I6: 2 | J6: 2 | K6: 2 | L6: 8 | M6: 2 | N6: 3 | O6: 1 | P6: 1 | Q6: 0
A7: Safety | B7: Hires | E7: 1 | F7: 2 | G7: 0 | H7: 2 | I7: 2 | J7: 2 | K7: 0 | L7: 2 | M7: 4 | N7: 0 | O7: 3 | P7: 0 | Q7: 4
A8: Safety | B8: Spostamenti interni | E8: 0 | F8: 0 | G8: 0 | H8: 0 | I8: -1 | J8: 3 | K8: 0 | L8: -1 | M8: 1 | N8: 0 | O8: 0 | P8: 0 | Q8: 0
A9: Safety | D9: Turnover rate | E9: =+E6/E5 -> 0.027777778 | F9: =+F6/F5 -> 0.11111111 | G9: =+G6/G5 -> 0 | H9: =+H6/H5 -> 0.058823529 | I9: =+I6/I5 -> 0.058823529 | J9: =+J6/J5 -> 0.060606061 | K9: =+K6/K5 -> 0.055555556 | L9: =+L6/L5 -> 0.23529412 | ... R9: =+R6/R5 -> 0
A10: Safety | D10: YTD | E10: 0.27384077 | F10: 0.38495188 | G10: 0.38495188 | H10: 0.44377541 | I10: 0.50259894 | J10: 0.563205 | K10: 0.61876055 | L10: =+L9 -> 0.23529412 | M10: =+M9+L10 -> 0.30936819 | N10: =+N9+M10 -> 0.40936819 | O10: =+O9+N10 -> 0.44640523 | P10: =+P9+O10 -> 0.48088799 | Q10: =+Q9+P10 -> 0.48088799 | R10: =+R9+Q10 -> 0.48088799 | S10: YTD<-10pts vs PY | T10: =IFERROR(Q10/E10-1,100%) -> 0.75608618
A11: Leather | B11: Employees at Beginning | E11: 98 | F11: =+E11+E13+E14-E12 -> 99 | G11: =+F11+F13+F14-F12 -> 97 | H11: =+G11+G13+G14-G12 -> 98 | I11: =+H11+H13+H14-H12 -> 102 | J11: =+I11+I13+I14-I12 -> 103 | K11: =+J11+J13+J14-J12 -> 101 | L11: =+K11+K13+K14-K12 -> 100 | M11: =+L11+L13+L14-L12 -> 94 | ... R11: =+Q11+Q13+Q14-Q12 -> 96
A12: Leather | B12: Terminations | E12: 0 | F12: 2 | G12: 0 | H12: 3 | I12: 1 | J12: 3 | K12: 1 | L12: 4 | M12: 1 | N12: 2 | O12: 2 | P12: 0 | Q12: 1
A13: Leather | B13: Hires | E13: 1 | F13: 0 | G13: 0 | H13: 6 | I13: 2 | J13: 3 | K13: 0 | L13: 1 | M13: 1 | N13: 0 | O13: 2 | P13: 1 | Q13: 3
A14: Leather | B14: Spostamenti interni | E14: 0 | F14: 0 | G14: 1 | H14: 1 | I14: 0 | J14: -2 | K14: 0 | L14: -3 | M14: 0 | N14: 0 | O14: 0 | P14: 1 | Q14: 0
A15: Leather | D15: Turnover rate | E15: =+E12/E11 -> 0 | F15: =+F12/F11 -> 0.02020202 | G15: =+G12/G11 -> 0 | H15: =+H12/H11 -> 0.030612245 | I15: =+I12/I11 -> 0.0098039216 | J15: =+J12/J11 -> 0.029126214 | K15: =+K12/K11 -> 0.0099009901 | L15: =+L12/L11 -> 0.04 | ... R15: =+R12/R11 -> 0
A16: Leather | D16: YTD | E16: 0.10954129 | F16: 0.12974331 | G16: 0.12974331 | H16: 0.16035555 | I16: 0.17015947 | J16: 0.19928569 | K16: 0.20918668 | L16: =+L15 -> 0.04 | M16: =+M15+L16 -> 0.050638298 | N16: =+N15+M16 -> 0.071914894 | O16: =+O15+N16 -> 0.093654024 | P16: =+P15+O16 -> 0.093654024 | Q16: =+Q15+P16 -> 0.10429232 | R16: =+R15+Q16 -> 0.10429232 | S16: YTD<-10pts vs PY | T16: =IFERROR(Q16/E16-1,100%) -> -0.047917669
A17: Dair | B17: Employees at Beginning | E17: 13 | F17: =+E17+E19+E20-E18 -> 14 | G17: =+F17+F19+F20-F18 -> 14 | H17: =+G17+G19+G20-G18 -> 13 | I17: =+H17+H19+H20-H18 -> 11 | J17: =+I17+I19+I20-I18 -> 12 | K17: =+J17+J19+J20-J18 -> 11 | L17: =+K17+K19+K20-K18 -> 11 | M17: =+L17+L19+L20-L18 -> 9 | ... R17: =+Q17+Q19+Q20-Q18 -> 8
A18: Dair | B18: Terminations | E18: 0 | F18: 1 | G18: 0 | H18: 1 | I18: 1 | J18: 0 | K18: 0 | L18: 1 | M18: 0 | N18: 0 | O18: 0 | P18: 0 | Q18: 0
A19: Dair | B19: Hires | E19: 1 | F19: 1 | G19: 0 | H19: 0 | I19: 1 | J19: 0 | K19: 0 | L19: 0 | M19: 0 | N19: 0 | O19: 0 | P19: 0 | Q19: 0
A20: Dair | B20: Spostamenti interni | E20: 0 | F20: 0 | G20: -1 | H20: -1 | I20: 1 | J20: -1 | K20: 0 | L20: -1 | M20: 0 | N20: 0 | O20: 0 | P20: -1 | Q20: 0
A21: Dair | D21: Turnover rate | E21: =+E18/E17 -> 0 | F21: =+F18/F17 -> 0.071428571 | G21: =+G18/G17 -> 0 | H21: =+H18/H17 -> 0.076923077 | I21: =+I18/I17 -> 0.090909091 | J21: =+J18/J17 -> 0 | K21: =+K18/K17 -> 0 | L21: =+L18/L17 -> 0.090909091 | ... R21: =+R18/R17 -> 0
A22: Dair | D22: YTD | E22: 0.33501401 | F22: 0.40644258 | G22: 0.40644258 | H22: 0.48336565 | I22: 0.57427474 | J22: 0.57427474 | K22: 0.57427474 | L22: =+L21 -> 0.090909091 | M22: =+M21+L22 -> 0.090909091 | N22: =+N21+M22 -> 0.090909091 | O22: =+O21+N22 -> 0.090909091 | P22: =+P21+O22 -> 0.090909091 | Q22: =+Q21+P22 -> 0.090909091 | R22: =+R21+Q22 -> 0.090909091 | S22: YTD<-10pts vs PY | T22: =IFERROR(Q22/E22-1,100%) -> -0.72864092
A23: Commun | B23: Employees at Beginning | E23: 16 | F23: =+E23+E25+E26-E24 -> 16 | G23: =+F23+F25+F26-F24 -> 17 | H23: =+G23+G25+G26-G24 -> 17 | I23: =+H23+H25+H26-H24 -> 17 | J23: =+I23+I25+I26-I24 -> 16 | K23: =+J23+J25+J26-J24 -> 14 | L23: =+K23+K25+K26-K24 -> 14 | M23: =+L23+L25+L26-L24 -> 20 | ... R23: =+Q23+Q25+Q26-Q24 -> 19
A24: Commun | B24: Terminations | E24: 0 | F24: 0 | G24: 0 | H24: 0 | I24: 2 | J24: 2 | K24: 0 | L24: 0 | M24: 1 | N24: 0 | O24: 1 | P24: 0 | Q24: 1
A25: Commun | B25: Hires | E25: 0 | F25: 1 | G25: 0 | H25: 0 | I25: 1 | J25: 0 | K25: 0 | L25: 1 | M25: 1 | N25: 0 | O25: 0 | P25: 0 | Q25: 2
A26: Commun | B26: Spostamenti interni | E26: 0 | F26: 0 | G26: 0 | H26: 0 | I26: 0 | J26: 0 | K26: 0 | L26: 5 | M26: -1 | N26: 0 | O26: 0 | P26: 0 | Q26: 0
A27: Commun | D27: Turnover rate | E27: =+E24/E23 -> 0 | F27: =+F24/F23 -> 0 | G27: =+G24/G23 -> 0 | H27: =+H24/H23 -> 0 | I27: =+I24/I23 -> 0.11764706 | J27: =+J24/J23 -> 0.125 | K27: =+K24/K23 -> 0 | L27: =+L24/L23 -> 0 | ... R27: =+R24/R23 -> 0
A28: Commun | D28: YTD | E28: 0.058823529 | F28: 0.058823529 | G28: 0.058823529 | H28: 0.058823529 | I28: 0.17647059 | J28: 0.30147059 | K28: 0.30147059 | L28: =+L27 -> 0 | M28: =+M27+L28 -> 0.05 | N28: =+N27+M28 -> 0.05 | O28: =+O27+N28 -> 0.10263158 | P28: =+P27+O28 -> 0.10263158 | Q28: =+Q27+P28 -> 0.15818713 | R28: =+R27+Q28 -> 0.15818713 | S28: YTD<-10pts vs PY | T28: =IFERROR(Q28/E28-1,100%) -> 1.6891813
A29: MEL-T | B29: Employees at Beginning | E29: 163 | F29: =+E29+E31+E32-E30 -> 165 | G29: =+F29+F31+F32-F30 -> 162 | H29: =+G29+G31+G32-G30 -> 162 | I29: =+H29+H31+H32-H30 -> 164 | J29: =+I29+I31+I32-I30 -> 164 | K29: =+J29+J31+J32-J30 -> 162 | L29: =+K29+K31+K32-K30 -> 159 | M29: =+L29+L31+L32-L30 -> 150 | ... R29: =+Q29+Q31+Q32-Q30 -> 155
A30: MEL-T | B30: Terminations | E30: =SUM(E24,E18,E12,E6) -> 1 | F30: =SUM(F24,F18,F12,F6) -> 7 | G30: =SUM(G24,G18,G12,G6) -> 0 | H30: =SUM(H24,H18,H12,H6) -> 6 | I30: =SUM(I24,I18,I12,I6) -> 6 | J30: =SUM(J24,J18,J12,J6) -> 7 | K30: =SUM(K24,K18,K12,K6) -> 3 | L30: =SUM(L24,L18,L12,L6) -> 13 | ... R30: =SUM(R24,R18,R12,R6) -> 0
A31: MEL-T | B31: Hires | E31: =SUM(E25,E19,E13,E7) -> 3 | F31: =SUM(F25,F19,F13,F7) -> 4 | G31: =SUM(G25,G19,G13,G7) -> 0 | H31: =SUM(H25,H19,H13,H7) -> 8 | I31: =SUM(I25,I19,I13,I7) -> 6 | J31: =SUM(J25,J19,J13,J7) -> 5 | K31: =SUM(K25,K19,K13,K7) -> 0 | L31: =SUM(L25,L19,L13,L7) -> 4 | ... R31: =SUM(R25,R19,R13,R7) -> 0
A32: MEL-T | B32: Spostamenti interni | E32: =SUM(E26,E20,E14,E8) -> 0 | F32: =SUM(F26,F20,F14,F8) -> 0 | G32: =SUM(G26,G20,G14,G8) -> 0 | H32: =SUM(H26,H20,H14,H8) -> 0 | I32: =SUM(I26,I20,I14,I8) -> 0 | J32: =SUM(J26,J20,J14,J8) -> 0 | K32: =SUM(K26,K20,K14,K8) -> 0 | L32: =SUM(L26,L20,L14,L8) -> 0 | ... R32: =SUM(R26,R20,R14,R8) -> 0
A33: MEL-T | D33: Turnover rate | E33: =+E30/E29 -> 0.0061349693 | F33: =+F30/F29 -> 0.042424242 | G33: =+G30/G29 -> 0 | H33: =+H30/H29 -> 0.037037037 | I33: =+I30/I29 -> 0.036585366 | J33: =+J30/J29 -> 0.042682927 | K33: =+K30/K29 -> 0.018518519 | L33: =+L30/L29 -> 0.081761006 | ... R33: =+R30/R29 -> 0
A34: MEL-T | D34: YTD | E34: 0.16418943 | F34: 0.20661368 | G34: 0.20661368 | H34: 0.24365071 | I34: 0.28023608 | J34: 0.32291901 | K34: 0.34143753 | L34: =+L33 -> 0.081761006 | M34: =+M33+L34 -> 0.10842767 | N34: =+N33+M34 -> 0.14132241 | O34: =+O33+N34 -> 0.16853329 | P34: =+P33+O34 -> 0.17529005 | Q34: =+Q33+P34 -> 0.18880356 | R34: =+R33+Q34 -> 0.18880356 | S34: YTD<-10 p.p. vs PY | T34: =IFERROR(Q34/E34-1,100%) -> 0.149913
A35: Source: « Rolling Turnover rate.xlsx"
A38: Absenteeism Rate (in %)
A39: (Unplanned Lost Hours / Available Hours) × 100
D40: MONTH MAG'26 | L40: YTD'26 | V40: MONTH | AB40: YTD | AI40: BDG | AL40: +/- Vs bdg
A41: BU | D41: Available Hrs | E41: Overall absence Hrs | F41: Overal Absene Rate | G41: Absenteeism Hrs | H41: Absenteeism Rate | I41: TARGET | J41: +/- Vs trgt | L41: Available Hrs | M41: Overall absence Hrs | N41: Overal Absene Rate | O41: Absenteeism Hrs | P41: Absenteeism Rate | Q41: TARGET | R41: +/- Vs trgt | S41: FY'25 | T41: % Var. Vs FY'25 | V41: Hrs par 1.0FTE | W41: Average HC | X41: Absence FTE | Y41: 1.0 FTE | Z41: % | AB41: Hrs par 1.0FTE | AC41: Average HC | AD41: Absence FTE | AE41: 1.0 FTE | AF41: % | AH41: ACT HC | AI41: HC | AJ41: 1.0 FTE | AK41: % | AL41: HC | AM41: 1.0 FTE | AN41: % | AP41: Hire budget realisation | AQ41: To Hire | AR41: % | AS41: Ratio Abs vs BDG
A42: Safety | D42: 4922.5 | E42: 1181 | F42: =+E42/D42 -> 0.23991874 | G42: 1085.5 | H42: =+G42/D42 -> 0.22051803 | I42: 0.075 | J42: =H42-I42 -> 0.14551803 | L42: 27484.5 | M42: 7124 | N42: =+M42/L42 -> 0.25920064 | O42: 5418.5 | P42: =+O42/L42 -> 0.19714748 | Q42: 0.075 | R42: =P42-Q42 -> 0.12214748 | S42: 0.10604721 | T42: =P42/S42-1 -> 0.85905395 | V42: 193.5 | W42: =+D42/V42 -> 25.439276 | X42: =+E42/V42 -> 6.1033592 | Y42: =+W42-X42 -> 19.335917 | Z42: =+Y42/W42-1 -> -0.23991874 | AB42: 1105 | AC42: =+L42/AB42 -> 24.872851 | AD42: =+M42/AB42 -> 6.4470588 | AE42: =+AC42-AD42 -> 18.425792 | AF42: =+AE42/AC42-1 -> -0.25920064 | AH42: 26 | AI42: 44 | AJ42: 35.58 | AK42: =+AJ42/AI42-1 -> -0.19136364 | AL42: =+AH42-AI42 -> -18 | AM42: =+AE42-AJ42 -> -17.154208 | AN42: =-AF42+AK42 -> 0.067837004 | AP42: =+AH42/AI42 -> 0.59090909 | AQ42: =+AM42*(1+AN42) -> -18.317898 | AR42: =AQ42/AI42 -> -0.41631587 | AS42: =+AF42/AK42 -> 1.3544927
A43: Leather | D43: 16157 | E43: 2117.5 | F43: =+E43/D43 -> 0.13105775 | G43: 1058 | H43: =+G43/D43 -> 0.065482453 | I43: 0.075 | J43: =H43-I43 -> -0.0095175466 | L43: 90887 | M43: 14524.5 | N43: =+M43/L43 -> 0.15980833 | O43: 7741 | P43: =+O43/L43 -> 0.085171697 | Q43: 0.075 | R43: =P43-Q43 -> 0.010171697 | S43: 0.071747596 | T43: =P43/S43-1 -> 0.18710175 | V43: 193.5 | W43: =+D43/V43 -> 83.498708 | X43: =+E43/V43 -> 10.943152 | Y43: =+W43-X43 -> 72.555556 | Z43: =+Y43/W43-1 -> -0.13105775 | AB43: 1105 | AC43: =+L43/AB43 -> 82.250679 | AD43: =+M43/AB43 -> 13.144344 | AE43: =+AC43-AD43 -> 69.106335 | AF43: =+AE43/AC43-1 -> -0.15980833 | AH43: 84 | AI43: 85 | AJ43: 69.6 | AK43: =+AJ43/AI43-1 -> -0.18117647 | AL43: =+AH43-AI43 -> -1 | AM43: =+AE43-AJ43 -> -0.49366516 | AN43: =-AF43+AK43 -> -0.021368137 | AP43: =+AH43/AI43 -> 0.98823529 | AQ43: =+AM43*(1+AN43) -> -0.48311645 | AR43: =AQ43/AI43 -> -0.005683723 | AS43: =+AF43/AK43 -> 0.88205898
A44: D|air | D44: 967.5 | E44: 112.5 | F44: =+E44/D44 -> 0.11627907 | G44: 25.5 | H44: =+G44/D44 -> 0.026356589 | I44: 0.075 | J44: =H44-I44 -> -0.048643411 | L44: 4697.5 | M44: 441 | N44: =+M44/L44 -> 0.093879723 | O44: 123.5 | P44: =+O44/L44 -> 0.02629058 | Q44: 0.075 | R44: =P44-Q44 -> -0.04870942 | S44: 0.13737624 | T44: =P44/S44-1 -> -0.80862353 | V44: 193.5 | W44: =+D44/V44 -> 5 | X44: =+E44/V44 -> 0.58139535 | Y44: =+W44-X44 -> 4.4186047 | Z44: =+Y44/W44-1 -> -0.11627907 | AB44: 1105 | AC44: =+L44/AB44 -> 4.2511312 | AD44: =+M44/AB44 -> 0.39909502 | AE44: =+AC44-AD44 -> 3.8520362 | AF44: =+AE44/AC44-1 -> -0.093879723 | AH44: 5 | AI44: 6 | AJ44: 4.9 | AK44: =+AJ44/AI44-1 -> -0.18333333 | AL44: =+AH44-AI44 -> -1 | AM44: =+AE44-AJ44 -> -1.0479638 | AN44: =-AF44+AK44 -> -0.08945361 | AP44: =+AH44/AI44 -> 0.83333333 | AQ44: =+AM44*(1+AN44) -> -0.95421966 | AR44: =AQ44/AI44 -> -0.15903661 | AS44: =+AF44/AK44 -> 0.51207122
A45: Direct total | D45: =SUM(D42:D44) -> 22047 | E45: =SUM(E42:E44) -> 3411 | F45: =+E45/D45 -> 0.15471493 | G45: =SUM(G42:G44) -> 2169 | H45: =+G45/D45 -> 0.098380732 | I45: 0.075 | J45: =H45-I45 -> 0.023380732 | L45: =SUM(L42:L44) -> 123069 | M45: =SUM(M42:M44) -> 22089.5 | N45: =+M45/L45 -> 0.17948874 | O45: =SUM(O42:O44) -> 13283 | P45: =+O45/L45 -> 0.10793132 | Q45: 0.075 | R45: =P45-Q45 -> 0.032931323 | S45: 0.083647462 | T45: =P45/S45-1 -> 0.29031198 | V45: 193.5 | W45: =+D45/V45 -> 113.93798 | X45: =+E45/V45 -> 17.627907 | Y45: =+W45-X45 -> 96.310078 | Z45: =+Y45/W45-1 -> -0.15471493 | AB45: 1105 | AC45: =+L45/AB45 -> 111.37466 | AD45: =+M45/AB45 -> 19.990498 | AE45: =+AC45-AD45 -> 91.384163 | AF45: =+AE45/AC45-1 -> -0.17948874 | AH45: =SUBTOTAL(9,AH42:AH44) -> 115 | AI45: =SUM(AI42:AI44) -> 135 | AJ45: =SUM(AJ42:AJ44) -> 110.08 | AK45: =+AJ45/AI45-1 -> -0.18459259 | AL45: =+AH45-AI45 -> -20 | AM45: =+AE45-AJ45 -> -18.695837 | AN45: =-AF45+AK45 -> -0.0051038505 | AP45: =+AH45/AI45 -> 0.85185185 | AQ45: =SUM(AQ42:AQ44) -> -19.755234 | AR45: =AQ45/AI45 -> -0.14633507 | AS45: =+AF45/AK45 -> 0.97235073
A46: Indirect | D46: 8032 | E46: 465 | F46: =+E46/D46 -> 0.057893426 | G46: 359.5 | H46: =+G46/D46 -> 0.044758466 | I46: 0.075 | J46: =H46-I46 -> -0.030241534 | L46: 45554 | M46: 3563.5 | N46: =+M46/L46 -> 0.078225842 | O46: 1909 | P46: =+O46/L46 -> 0.041906309 | Q46: 0.075 | R46: =P46-Q46 -> -0.033093691 | S46: 0.041861001 | T46: =P46/S46-1 -> 0.0010823498 | V46: 193.5 | W46: =+D46/V46 -> 41.509044 | X46: =+E46/V46 -> 2.4031008 | Y46: =+W46-X46 -> 39.105943 | Z46: =+Y46/W46-1 -> -0.057893426 | AB46: 1105 | AC46: =+L46/AB46 -> 41.225339 | AD46: =+M46/AB46 -> 3.2248869 | AE46: =+AC46-AD46 -> 38.000452 | AF46: =+AE46/AC46-1 -> -0.078225842 | AH46: 40 | AI46: 44 | AJ46: 39 | AK46: =+AJ46/AI46-1 -> -0.11363636 | AL46: =+AH46-AI46 -> -4 | AM46: =+AE46-AJ46 -> -0.99954751 | AN46: =-AF46+AK46 -> -0.035410522 | AP46: =+AH46/AI46 -> 0.90909091 | AQ46: =+AM46*(1+AN46) -> -0.96415301 | AR46: =AQ46/AI46 -> -0.021912568 | AS46: =IFERROR(AF46/AK46,0) -> 0.68838741
A47: MEL-T | D47: =SUM(D45:D46) -> 30079 | E47: =SUM(E45:E46) -> 3876 | F47: =+E47/D47 -> 0.12886067 | G47: =SUM(G45:G46) -> 2528.5 | H47: =+G47/D47 -> 0.08406197 | I47: 0.075 | J47: =H47-I47 -> 0.0090619701 | L47: =SUM(L45:L46) -> 168623 | M47: =SUM(M45:M46) -> 25653 | N47: =+M47/L47 -> 0.15213227 | O47: =SUM(O45:O46) -> 15192 | P47: =+O47/L47 -> 0.090094471 | Q47: 0.075 | R47: =P47-Q47 -> 0.015094471 | S47: 0.073588909 | T47: =P47/S47-1 -> 0.22429415 | AP47: =AP45-1 -> -0.14814815
A49: BU | D49: 45838 | E49: 45869 | F49: 45900 | G49: 45930 | H49: 45961 | I49: 45991 | J49: 46022 | K49: 46053 | L49: 46081 | M49: 46112 | N49: 46142 | O49: 46173 | P49: 46203
A50: Safety | B50: Direct | D50: 0.14930966 | E50: 0.12945591 | F50: 0.044049967 | G50: 0.14883675 | H50: 0.091409897 | I50: 0.068038879 | J50: 0.12695995 | K50: 0.27201917 | L50: 0.2708549 | M50: 0.16353887 | N50: 0.075152897 | O50: 0.166 | P50: 0.221
A51: Leather | B51: Direct | D51: 0.06088052 | E51: 0.055743529 | F51: 0.059043128 | G51: 0.08281833 | H51: 0.093952791 | I51: 0.085702253 | J51: 0.095578308 | K51: 0.12512161 | L51: 0.095564871 | M51: 0.08434098 | N51: 0.087731154 | O51: 0.045 | P51: 0.065
A52: D|air | B52: Direct | D52: 0.068786982 | E52: 0.10148515 | F52: 0.14285714 | G52: 0.268 | H52: 0.020190024 | I52: 0.030630631 | J52: 0.10841584 | K52: 0.056306306 | L52: 0.05758427 | M52: 0.010638298 | N52: 0 | O52: 0 | P52: 0.026
A53: MEL-T | B53: Direct | D53: 0.082628574 | E53: 0.075029806 | F53: 0.060683761 | G53: 0.1051292 | H53: 0.08983916 | I53: 0.079008639 | J53: 0.10329756 | K53: 0.15463038 | L53: 0.13588079 | M53: 0.099002689 | N53: 0.081726271 | O53: 0.07 | P53: 0.098
A54: * The lost hours mentioned in the table are the sum of Illegitimate and Unplanned & Legitimate and Unplanned Work Absence
A55: Source: "Absence rate.xlsx"
A58: Hire Budget Realization (%) by DIR/IND and BU
A59: (Actual HC / Budget HC) × 100
A60: BU | D60: 45838 | E60: 45869 | F60: 45900 | G60: 45930 | H60: 45961 | I60: 45991 | J60: 46022 | K60: 46053 | L60: 46081 | M60: 46112 | N60: 46142 | O60: 46173 | P60: 46203 | Q60: TARGET | R60: +/- Vs trgt | S60: +/- MoM | T60: %Var. MoM | U60: BDG 2026 | V60: ratio direct/indirect
A61: Safety - Direct | D61: 30 | E61: 26 | F61: 26 | G61: 27 | H61: 26 | I61: 30 | J61: 28 | K61: 23 | L61: 25 | M61: 22 | N61: 23 | O61: 23 | P61: 26 | Q61: 44 | R61: =+P61-Q61 -> -18 | S61: =+P61-O61 -> 3 | T61: =IFERROR(P61/O61-1,100%) -> 0.13043478 | U61: 33
A62: Safety - Indirect | D62: 6 | E62: 8 | F62: 8 | G62: 7 | H62: 7 | I62: 6 | J62: 6 | K62: 4 | L62: 5 | M62: 5 | N62: 6 | O62: 5 | P62: 6 | Q62: 6 | R62: =+P62-Q62 -> 0 | S62: =+P62-O62 -> 1 | T62: =IFERROR(P62/O62-1,100%) -> 0.2 | U62: 7 | V62: =+P61/P62 -> 4.3333333
A63: Total Safety | D63: =SUM(D61:D62) -> 36 | E63: =SUM(E61:E62) -> 34 | F63: =SUM(F61:F62) -> 34 | G63: =SUM(G61:G62) -> 34 | H63: =SUM(H61:H62) -> 33 | I63: =SUM(I61:I62) -> 36 | J63: =SUM(J61:J62) -> 34 | K63: =SUM(K61:K62) -> 27 | ... Q63: =SUM(Q61:Q62) -> 50 | R63: =+P63-Q63 -> -18 | S63: =+P63-O63 -> 4 | T63: =IFERROR(P63/O63-1,100%) -> 0.14285714 | U63: 40
A64: Leather - Direct | D64: 87 | E64: 87 | F64: 87 | G64: 91 | H64: 92 | I64: 88 | J64: 87 | K64: 85 | L64: 84 | M64: 81 | N64: 81 | O64: 82 | P64: 84 | Q64: 85 | R64: =+P64-Q64 -> -1 | S64: =+P64-O64 -> 2 | T64: =IFERROR(P64/O64-1,100%) -> 0.024390244 | U64: 95
A65: Leather - Indirect | D65: 12 | E65: 11 | F65: 11 | G65: 11 | H65: 11 | I65: 13 | J65: 13 | K65: 10 | L65: 10 | M65: 11 | N65: 11 | O65: 12 | P65: 12 | Q65: 11 | R65: =+P65-Q65 -> 1 | S65: =+P65-O65 -> 0 | T65: =IFERROR(P65/O65-1,100%) -> 0 | U65: 14 | V65: =+P64/P65 -> 7
A66: Total Leather | D66: =SUM(D64:D65) -> 99 | E66: =SUM(E64:E65) -> 98 | F66: =SUM(F64:F65) -> 98 | G66: =SUM(G64:G65) -> 102 | H66: =SUM(H64:H65) -> 103 | I66: =SUM(I64:I65) -> 101 | J66: =SUM(J64:J65) -> 100 | K66: =SUM(K64:K65) -> 95 | ... Q66: =SUM(Q64:Q65) -> 96 | R66: =+P66-Q66 -> 0 | S66: =+P66-O66 -> 2 | T66: =IFERROR(P66/O66-1,100%) -> 0.021276596 | U66: 109
A67: D|air - Direct | D67: 8 | E67: 7 | F67: 7 | G67: 5 | H67: 6 | I67: 5 | J67: 5 | K67: 4 | L67: 4 | M67: 4 | N67: 4 | O67: 4 | P67: 5 | Q67: 6 | R67: =+P67-Q67 -> -1 | S67: =+P67-O67 -> 1 | T67: =IFERROR(P67/O67-1,100%) -> 0.25 | U67: 6
A68: D|air - Indirect | D68: 6 | E68: 6 | F68: 6 | G68: 6 | H68: 6 | I68: 6 | J68: 6 | K68: 5 | L68: 5 | M68: 5 | N68: 5 | O68: 4 | P68: 3 | Q68: 5 | R68: =+P68-Q68 -> -2 | S68: =+P68-O68 -> -1 | T68: =IFERROR(P68/O68-1,100%) -> -0.25 | U68: 6 | V68: =+P67/P68 -> 1.6666667
A69: Total D|air | D69: =SUM(D67:D68) -> 14 | E69: =SUM(E67:E68) -> 13 | F69: =SUM(F67:F68) -> 13 | G69: =SUM(G67:G68) -> 11 | H69: =SUM(H67:H68) -> 12 | I69: =SUM(I67:I68) -> 11 | J69: =SUM(J67:J68) -> 11 | K69: =SUM(K67:K68) -> 9 | ... Q69: =SUM(Q67:Q68) -> 11 | R69: =+P69-Q69 -> -3 | S69: =+P69-O69 -> 0 | T69: =IFERROR(P69/O69-1,100%) -> 0 | U69: 12
A70: Comune - Direct | D70: 0 | E70: 0 | F70: 0 | G70: 0 | H70: 0 | I70: 0 | J70: 0 | K70: 0 | L70: 0 | M70: 0 | N70: 0 | O70: 0 | P70: 0 | Q70: 0 | R70: =+P70-Q70 -> 0 | S70: =+P70-O70 -> 0 | T70: =IFERROR(P70/O70-1,100%) -> 1 | U70: 0
A71: Comune - Indirect | D71: 16 | E71: 17 | F71: 17 | G71: 17 | H71: 16 | I71: 14 | J71: 14 | K71: 19 | L71: 19 | M71: 19 | N71: 18 | O71: 18 | P71: 19 | Q71: 22 | R71: =+P71-Q71 -> -3 | S71: =+P71-O71 -> 1 | T71: =IFERROR(P71/O71-1,100%) -> 0.055555556 | U71: 17 | V71: =IFERROR(P70/P71,0) -> 0
A72: Total Comune | D72: =SUM(D70:D71) -> 16 | E72: =SUM(E70:E71) -> 17 | F72: =SUM(F70:F71) -> 17 | G72: =SUM(G70:G71) -> 17 | H72: =SUM(H70:H71) -> 16 | I72: =SUM(I70:I71) -> 14 | J72: =SUM(J70:J71) -> 14 | K72: =SUM(K70:K71) -> 19 | ... Q72: =SUM(Q70:Q71) -> 22 | R72: =+P72-Q72 -> -3 | S72: =+P72-O72 -> 1 | T72: =IFERROR(P72/O72-1,100%) -> 0.055555556 | U72: 17
A74: Total Direct | D74: =SUM(D61,D64,D67,D70) -> 125 | E74: =SUM(E61,E64,E67,E70) -> 120 | F74: =SUM(F61,F64,F67,F70) -> 120 | G74: =SUM(G61,G64,G67,G70) -> 123 | H74: =SUM(H61,H64,H67,H70) -> 124 | I74: =SUM(I61,I64,I67,I70) -> 123 | J74: =SUM(J61,J64,J67,J70) -> 120 | K74: =SUM(K61,K64,K67,K70) -> 112 | ... Q74: =SUM(Q61,Q64,Q67,Q70) -> 135 | R74: =+P74-Q74 -> -20 | S74: =+P74-O74 -> 6 | T74: =IFERROR(P74/O74-1,100%) -> 0.055045872 | U74: 134
A75: Total Indirect | D75: =SUM(D62,D65,D68,D71) -> 40 | E75: =SUM(E62,E65,E68,E71) -> 42 | F75: =SUM(F62,F65,F68,F71) -> 42 | G75: =SUM(G62,G65,G68,G71) -> 41 | H75: =SUM(H62,H65,H68,H71) -> 40 | I75: =SUM(I62,I65,I68,I71) -> 39 | J75: =SUM(J62,J65,J68,J71) -> 39 | K75: =SUM(K62,K65,K68,K71) -> 38 | ... Q75: =SUM(Q62,Q65,Q68,Q71) -> 44 | R75: =+P75-Q75 -> -4 | S75: =+P75-O75 -> 1 | T75: =IFERROR(P75/O75-1,100%) -> 0.025641026 | U75: 44 | V75: =+P74/P75 -> 2.875
A76: Total Headcount | D76: =SUM(D74:D75) -> 165 | E76: =SUM(E74:E75) -> 162 | F76: =SUM(F74:F75) -> 162 | G76: =SUM(G74:G75) -> 164 | H76: =SUM(H74:H75) -> 164 | I76: =SUM(I74:I75) -> 162 | J76: =SUM(J74:J75) -> 159 | K76: =SUM(K74:K75) -> 150 | ... Q76: =SUM(Q74:Q75) -> 179 | R76: =+P76-Q76 -> -24 | S76: =+P76-O76 -> 7 | T76: =IFERROR(P76/O76-1,100%) -> 0.047297297 | U76: 178
A78: ratio direct/indirect | D78: =+D74/D75 -> 3.125 | E78: =+E74/E75 -> 2.8571429 | F78: =+F74/F75 -> 2.8571429 | G78: =+G74/G75 -> 3 | H78: =+H74/H75 -> 3.1 | I78: =+I74/I75 -> 3.1538462 | J78: =+J74/J75 -> 3.0769231 | K78: =+K74/K75 -> 2.9473684 | ... Q78: =+Q74/Q75 -> 3.0681818 | U78: =+U74/U75 -> 3.0454545
A79: * #HC at end of month vs BDG
A80: Source: "Registre des employés MEL-T.xlsx"
A83: Hire Budget Realization (%) by Funtion-Group and BU
A84: (Actual HC / Budget HC) × 100
A85: Functional-Group | B85: BU | D85: 45777 | E85: 45808 | F85: 45838 | G85: 45869 | H85: 45900 | I85: 45930 | J85: 45961 | K85: 45991 | L85: 46022 | M85: 46053 | N85: 46081 | O85: 46112 | P85: 46142 | Q85: TARGET | R85: +/- Vs trgt | S85: MoM % | T85: BDG
A86: CUTTING | B86: Safety | C86: HC | D86: 1 | E86: 2 | F86: 2 | G86: 2 | H86: 2 | I86: 2 | J86: 3 | K86: 3 | L86: 3 | M86: 3 | N86: 3 | O86: 3 | P86: 3 | Q86: 3 | R86: =+P86-Q86 -> 0 | S86: =IFERROR(P86/O86-1,100%) -> 0 | T86: 3
A87: CUTTING | B87: Safety | C87: 1.0 FTE | D87: 0.67774936 | E87: 1.6040757 | F87: 1.7840237 | G87: 1.8341584 | H87: 1.8290598 | I87: 1.7232376 | J87: 2.2256532 | K87: 2.8405405 | L87: 2.0123762 | M87: 2.3681592 | N87: 2.7303371 | O87: 2.5987842 | P87: 2.720297 | Q87: 2.7 | R87: =+P87-Q87 -> 0.02029703 | S87: =IFERROR(P87/O87-1,100%) -> 0.04675757 | T87: 2.7
A88: CUTTING
A89: CUTTING | B89: Leather | C89: HC | D89: 6 | E89: 5 | F89: 5 | G89: 5 | H89: 5 | I89: 6 | J89: 6 | K89: 7 | L89: 7 | M89: 7 | N89: 6 | O89: 5 | P89: 5 | Q89: 8 | R89: =+P89-Q89 -> -3 | S89: =IFERROR(P89/O89-1,100%) -> 0 | T89: 10
A90: CUTTING | B90: Leather | C90: 1.0 FTE | D90: 3.9207161 | E90: 3.8955224 | F90: 4.5710059 | G90: 4.6509901 | H90: 3.8717949 | I90: 4.5483029 | J90: 4.5402161 | K90: 5.0945946 | L90: 5.4158416 | M90: 4.7189055 | N90: 5.3876404 | O90: 4.2553191 | P90: 4.549505 | Q90: 7.2 | R90: =+P90-Q90 -> -2.650495 | S90: =IFERROR(P90/O90-1,100%) -> 0.069133663 | T90: 9
A91: CUTTING
A92: CUTTING | B92: Dair | C92: HC | D92: 1 | E92: 1 | F92: 1 | G92: 1 | H92: 1 | I92: 0 | J92: 0 | K92: 0 | L92: 0 | M92: 0 | N92: 0 | O92: 0 | P92: 0 | Q92: 1 | R92: =+P92-Q92 -> -1 | S92: =IFERROR(P92/O92-1,100%) -> 1 | T92: 2
A93: CUTTING | B93: Dair | C93: 1.0 FTE | D93: 0.875 | E93: 0.91891892 | F93: 0.85502959 | G93: 0.85643564 | H93: 0.87179487 | I93: 0 | J93: 0 | K93: 0 | L93: 0 | M93: 0 | N93: 0 | O93: 0 | P93: 0 | Q93: 0.9 | R93: =+P93-Q93 -> -0.9 | S93: =IFERROR(P93/O93-1,100%) -> 1 | T93: 1.8
C94: CUTTING HC | D94: =SUBTOTAL(9,D86,D89,D92) -> 8 | E94: =SUBTOTAL(9,E86,E89,E92) -> 8 | F94: =SUBTOTAL(9,F86,F89,F92) -> 8 | G94: =SUBTOTAL(9,G86,G89,G92) -> 8 | H94: =SUBTOTAL(9,H86,H89,H92) -> 8 | I94: =SUBTOTAL(9,I86,I89,I92) -> 8 | J94: =SUBTOTAL(9,J86,J89,J92) -> 9 | K94: =SUBTOTAL(9,K86,K89,K92) -> 10 | ... Q94: =SUBTOTAL(9,Q86,Q89,Q92) -> 12 | R94: =+P94-Q94 -> -4 | S94: =IFERROR(P94/O94-1,100%) -> 0 | T94: =SUBTOTAL(9,T86,T89,T92) -> 15
C95: CUTTING 1.0 FTE | D95: =SUBTOTAL(9,D87,D90,D93) -> 5.4734655 | E95: =SUBTOTAL(9,E87,E90,E93) -> 6.418517 | F95: =SUBTOTAL(9,F87,F90,F93) -> 7.2100592 | G95: =SUBTOTAL(9,G87,G90,G93) -> 7.3415842 | H95: =SUBTOTAL(9,H87,H90,H93) -> 6.5726496 | I95: =SUBTOTAL(9,I87,I90,I93) -> 6.2715405 | J95: =SUBTOTAL(9,J87,J90,J93) -> 6.7658693 | K95: =SUBTOTAL(9,K87,K90,K93) -> 7.9351351 | ... Q95: =SUBTOTAL(9,Q87,Q90,Q93) -> 10.8 | R95: =+P95-Q95 -> -3.530198 | S95: =IFERROR(P95/O95-1,100%) -> 0.060649602 | T95: =SUBTOTAL(9,T87,T90,T93) -> 13.5
A96: STITCHING | B96: Safety | C96: HC | D96: 28 | E96: 26 | F96: 26 | G96: 26 | H96: 22 | I96: 22 | J96: 22 | K96: 23 | L96: 23 | M96: 24 | N96: 22 | O96: 20 | P96: 19 | Q96: 35 | R96: =+P96-Q96 -> -16 | S96: =IFERROR(P96/O96-1,100%) -> -0.05 | T96: 36
A97: STITCHING | B97: Safety | C97: 1.0 FTE | D97: 14.519182 | E97: 17.320896 | F97: 18.39645 | G97: 18.24505 | H97: 10.08547 | I97: 18.138381 | J97: 18.118765 | K97: 17.059459 | L97: 15.039604 | M97: 12.965174 | N97: 14.629213 | O97: 14.048632 | P97: 14.237624 | Q97: 28 | R97: =+P97-Q97 -> -13.762376 | S97: =IFERROR(P97/O97-1,100%) -> 0.013452665 | T97: 29.34
A98: STITCHING
A99: STITCHING | B99: Leather | C99: HC | D99: 71 | E99: 70 | F99: 70 | G99: 70 | H99: 70 | I99: 71 | J99: 72 | K99: 70 | L99: 69 | M99: 67 | N99: 65 | O99: 64 | P99: 65 | Q99: 62 | R99: =+P99-Q99 -> 3 | S99: =IFERROR(P99/O99-1,100%) -> 0.015625 | T99: 74
A100: STITCHING | B100: Leather | C100: 1.0 FTE | D100: 41.44757 | E100: 51.895522 | F100: 59.579882 | G100: 61.116337 | H100: 35.888889 | I100: 59.488251 | J100: 60.551069 | K100: 58.381081 | L100: 52.032178 | M100: 53.38806 | N100: 54.80618 | O100: 53.18845 | P100: 53.893564 | Q100: 49.6 | R100: =+P100-Q100 -> 4.2935644 | S100: =IFERROR(P100/O100-1,100%) -> 0.01325691 | T100: 60.31
A101: STITCHING
A102: STITCHING | B102: Dair | C102: HC | D102: 6 | E102: 6 | F102: 5 | G102: 5 | H102: 5 | I102: 4 | J102: 4 | K102: 4 | L102: 3 | M102: 3 | N102: 2 | O102: 2 | P102: 2 | Q102: 3 | R102: =+P102-Q102 -> -1 | S102: =IFERROR(P102/O102-1,100%) -> 0 | T102: 6
A103: STITCHING | B103: Dair | C103: 1.0 FTE | D103: 2.258312 | E103: 2.2437811 | F103: 2.5798817 | G103: 2.1831683 | H103: 1.6410256 | I103: 1.0287206 | J103: 2.6983373 | K103: 2.7081081 | L103: 2.039604 | M103: 1.6442786 | N103: 1.8061798 | O103: 1.9574468 | P103: 1.9678218 | Q103: 2.4 | R103: =+P103-Q103 -> -0.43217822 | S103: =IFERROR(P103/O103-1,100%) -> 0.0053002583 | T103: 4.89
C104: STITCHING HC | D104: =SUBTOTAL(9,D96,D99,D102) -> 105 | E104: =SUBTOTAL(9,E96,E99,E102) -> 102 | F104: =SUBTOTAL(9,F96,F99,F102) -> 101 | G104: =SUBTOTAL(9,G96,G99,G102) -> 101 | H104: =SUBTOTAL(9,H96,H99,H102) -> 97 | I104: =SUBTOTAL(9,I96,I99,I102) -> 97 | J104: =SUBTOTAL(9,J96,J99,J102) -> 98 | K104: =SUBTOTAL(9,K96,K99,K102) -> 97 | ... Q104: =SUBTOTAL(9,Q96,Q99,Q102) -> 100 | R104: =+P104-Q104 -> -14 | S104: =IFERROR(P104/O104-1,100%) -> 0 | T104: =SUBTOTAL(9,T96,T99,T102) -> 116
C105: STITCHING 1.0 FTE | D105: =SUBTOTAL(9,D97,D100,D103) -> 58.225064 | E105: =SUBTOTAL(9,E97,E100,E103) -> 71.460199 | F105: =SUBTOTAL(9,F97,F100,F103) -> 80.556213 | G105: =SUBTOTAL(9,G97,G100,G103) -> 81.544554 | H105: =SUBTOTAL(9,H97,H100,H103) -> 47.615385 | I105: =SUBTOTAL(9,I97,I100,I103) -> 78.655352 | J105: =SUBTOTAL(9,J97,J100,J103) -> 81.368171 | K105: =SUBTOTAL(9,K97,K100,K103) -> 78.148649 | ... Q105: =SUBTOTAL(9,Q97,Q100,Q103) -> 80 | R105: =+P105-Q105 -> -9.9009901 | S105: =IFERROR(P105/O105-1,100%) -> 0.013071569 | T105: =SUBTOTAL(9,T97,T100,T103) -> 94.54
A106: PREPARATION | B106: Safety | C106: HC
A107: PREPARATION | B107: Safety | C107: 1.0 FTE
A108: PREPARATION
A109: PREPARATION | B109: Leather | C109: HC | D109: 5 | E109: 8 | F109: 7 | G109: 8 | H109: 8 | I109: 12 | J109: 11 | K109: 11 | L109: 9 | M109: 9 | N109: 10 | O109: 10 | P109: 9 | Q109: 11 | R109: =+P109-Q109 -> -2 | S109: =IFERROR(P109/O109-1,100%) -> -0.1 | T109: 10
...

Sheet People_2
A1: Mth | B1: HC (inizio mese) | C1: HIRE | D1: LEFT | E1: DIR → IND | F1: IND →DIR | G1: HC (fine mese) | H1: Bdg / Trgt | I1: % Realization | J1: +/- Vs BDG | K1: Note
A2: gen | B2: 120 | C2: 2 | D2: 10 | G2: =+B2+C2-D2-E2+F2 -> 112 | H2: 120 | I2: =+G2/H2 -> 0.93333333 | J2: =+G2-H2 -> -8
A3: feb | B3: =+G2 -> 112 | C3: 4 | D3: 3 | G3: =+B3+C3-D3-E3+F3 -> 113 | H3: 120 | I3: =+G3/H3 -> 0.94166667 | J3: =+G3-H3 -> -7
A4: mar | B4: =+G3 -> 113 | C4: 0 | D4: 5 | E4: 1 | G4: =+B4+C4-D4-E4+F4 -> 107 | H4: 123 | I4: =+G4/H4 -> 0.8699187 | J4: =+G4-H4 -> -16 | K4: changement Mat 1712 de taglio Pelle Vers Warehouse
A5: apr | B5: =+G4 -> 107 | C5: 4 | D5: 3 | G5: =+B5+C5-D5-E5+F5 -> 108 | H5: 129 | I5: =+G5/H5 -> 0.8372093 | J5: =+G5-H5 -> -21
A6: mag | B6: =+G5 -> 108 | C6: 1 | G6: =+B6+C6-D6-E6+F6 -> 109 | H6: 134 | I6: =+G6/H6 -> 0.81343284 | J6: =+G6-H6 -> -25
A7: giu | B7: =+G6 -> 109 | C7: 7 | D7: 1 | E7: 1 | F7: 1 | G7: =+B7+C7-D7-E7+F7 -> 115 | H7: 135 | I7: =+G7/H7 -> 0.85185185 | J7: =+G7-H7 -> -20 | K7: Changement Mat 719 de Maintenance Vers TGL Laser + Changement Mat 369 vers Line Leader
A8: lug | B8: =+G7 -> 115 | G8: =+B8+C8-D8-E8+F8 -> 115 | H8: 135 | I8: =+G8/H8 -> 0.85185185 | J8: =+G8-H8 -> -20
A9: ago | B9: =+G8 -> 115 | G9: =+B9+C9-D9-E9+F9 -> 115 | H9: 135 | I9: =+G9/H9 -> 0.85185185 | J9: =+G9-H9 -> -20
A10: set | B10: =+G9 -> 115 | G10: =+B10+C10-D10-E10+F10 -> 115 | H10: 135 | I10: =+G10/H10 -> 0.85185185 | J10: =+G10-H10 -> -20
A11: ott | B11: =+G10 -> 115 | G11: =+B11+C11-D11-E11+F11 -> 115 | H11: 135 | I11: =+G11/H11 -> 0.85185185 | J11: =+G11-H11 -> -20
A12: nov | B12: =+G11 -> 115 | G12: =+B12+C12-D12-E12+F12 -> 115 | H12: 135 | I12: =+G12/H12 -> 0.85185185 | J12: =+G12-H12 -> -20
A13: dic | B13: =+G12 -> 115 | G13: =+B13+C13-D13-E13+F13 -> 115 | H13: 135 | I13: =+G13/H13 -> 0.85185185 | J13: =+G13-H13 -> -20

Sheet Worked Hrs
B1: Total worked hours and Overtime by Month
A3: Grand total | B3: Valori | C3: 45688 | D3: 45716 | E3: 45747 | F3: 45777 | G3: 45808 | H3: 45838 | I3: 45869 | J3: 45900 | K3: 45930 | L3: 45961 | M3: 45991 | N3: 46022 | O3: 46053 | P3: 46081 | Q3: 46112 | R3: 46142 | S3: 46173 | T3: 46203
A4: =SUM(O4:Z4) -> 168623 | B4: Available Hours | C4: 35186 | D4: 31851.5 | E4: 28203 | F4: 31774.5 | G4: 32422.5 | H4: 28239 | I4: 33153.5 | J4: 10444.5 | K4: 31287 | L4: 34724.5 | M4: 30948 | N4: 32506.5 | O4: 30654 | P4: 27728 | Q4: 24817.5 | R4: 30334.5 | S4: 25010 | T4: 30079
A5: =SUM(O5:Z5) -> 142970 | B5: Worked Hours (Regular Hrs) | C5: 30578 | D5: 27764 | E5: 19899 | F5: 18771 | G5: 23784 | H5: 23249 | I5: 28405.5 | J5: 6313.5 | K5: 26257.5 | L5: 29561.5 | M5: 25807.5 | N5: 24668 | O5: 23842 | P5: 23490.5 | Q5: 21026 | R5: 26516 | S5: 21892.5 | T5: 26203
A6: =SUM(O6:Z6) -> 923 | B6: HC | C6: 179 | D6: 177 | E6: 174 | F6: 167 | G6: 164 | H6: 165 | I6: 168 | J6: 161 | K6: 169 | L6: 169 | M6: 168 | N6: 161 | O6: 162 | P6: 155 | Q6: 151 | R6: 151 | S6: 148 | T6: 156
A7: =SUM(O7:Z7) -> 1105 | B7: Hrs par 1.0FTE | C7: 202 | D7: 185 | E7: 168 | F7: 195.5 | G7: 201 | H7: 169 | I7: 202 | J7: 58.5 | K7: 191.5 | L7: 210.5 | M7: 185 | N7: 202 | O7: 201 | P7: 178 | Q7: 164.5 | R7: 202 | S7: 166 | T7: 193.5
A8: =SUM(O8:Z8) -> 776.96952 | B8: 1.0 FTE | C8: 151.37624 | D8: 150.07568 | E8: 118.44643 | F8: 96.015345 | G8: 118.32836 | H8: 137.56805 | I8: 140.62129 | J8: 107.92308 | K8: 137.11488 | L8: 140.43468 | M8: 139.5 | N8: 122.11881 | O8: 118.61692 | P8: 131.9691 | Q8: 127.81763 | R8: 131.26733 | S8: 131.88253 | T8: 135.41602
A9: =SUM(O9:Z9) -> 219.5 | B9: 1.00x OT Hrs | C9: 0 | D9: 1.5 | E9: 220.5 | F9: 609.5 | G9: 87.5 | H9: 4.5 | I9: 1 | J9: 218.5 | K9: 24.5 | L9: 46.5 | M9: 24 | N9: 0 | O9: 60.5 | P9: 31 | Q9: 0 | R9: 0 | S9: 3 | T9: 125
A10: =SUM(O10:Z10) -> 1174 | B10: 1.75x OT Hrs | C10: 7.5 | D10: 24 | E10: 0 | F10: 28.5 | G10: 38.5 | H10: 0 | I10: 0 | J10: 206 | K10: 129 | L10: 179 | M10: 75 | N10: 0 | O10: 7 | P10: 40 | Q10: 0 | R10: 30 | S10: 392 | T10: 705
A11: =SUM(O11:Z11) -> 435.5 | B11: 2.00x OT Hrs | C11: 64 | D11: 5 | E11: 5 | F11: 10.5 | H11: 245.5 | I11: 48 | J11: 57.5 | K11: 71.5 | L11: 5.5 | M11: 11.5 | N11: 36 | O11: 44 | Q11: 96 | R11: 20 | S11: 165.5 | T11: 110
A12: =SUM(O12:Z12) -> 144799 | B12: Total Worked Hours | C12: 30649.5 | D12: 27794.5 | E12: 20124.5 | F12: 19419.5 | G12: 23910 | H12: 23499 | I12: 28454.5 | J12: 6795.5 | K12: 26482.5 | L12: 29792.5 | M12: 25918 | N12: 24704 | O12: 23953.5 | P12: 23561.5 | Q12: 21122 | R12: 26566 | S12: 22453 | T12: 27143
A13: =SUM(O13:Z13) -> 1829 | B13: Total Overtime Hrs | C13: 71.5 | D13: 30.5 | E13: 225.5 | F13: 648.5 | G13: 126 | H13: 250 | I13: 49 | J13: 482 | K13: 225 | L13: 231 | M13: 110.5 | N13: 36 | O13: 111.5 | P13: 71 | Q13: =SUM(Q9:Q11) -> 96 | R13: =SUM(R9:R11) -> 50 | S13: 560.5 | T13: 940
A14: =+A13/A12 -> 0.012631303 | B14: OT rate | C14: 0.0023328276 | D14: 0.0010973394 | E14: 0.011205247 | F14: 0.033394269 | G14: 0.0052697616 | H14: 0.010638751 | I14: 0.0017220475 | J14: 0.070929291 | K14: 0.0084961767 | L14: 0.0077536293 | M14: 0.0042634463 | N14: 0.0014572539 | O14: 0.0046548521 | P14: 0.0030133905 | Q14: =+Q13/Q12 -> 0.0045450241 | R14: =+R13/R12 -> 0.0018821049 | S14: 0.024963257 | T14: 0.034631397
B17: Absence hours by Type, Type level, Reasons and Month [ Only DL ]
A19: Grand total | B19: Valori | C19: 45688 | D19: 45716 | E19: 45747 | F19: 45777 | G19: 45808 | H19: 45838 | I19: 45869 | J19: 45900 | K19: 45930 | L19: 45961 | M19: 45991 | N19: 46022 | O19: 46053 | P19: 46081 | Q19: 46112 | R19: 46142 | S19: 46173 | T19: 46203
A20: =SUM(O20:Z20) -> 123069 | B20: Available Hours | C20: 27679 | D20: 25191.5 | E20: 22155 | F20: 24541 | G20: 24985.5 | H20: 21106.5 | I20: 24743.5 | J20: 7020 | K20: 23181 | L20: 25957.5 | M20: 22978.5 | N20: 24366.5 | O20: 22854.5 | P20: 20334 | Q20: 17848 | R20: 21908.5 | S20: 18077 | T20: 22047
A21: =SUM(O21:Z21) -> 100979.5 | B21: Worked Hours | C21: 23742.5 | D21: 21530 | E21: 15443.5 | F21: 14258.5 | G21: 18071.5 | H21: 17104.5 | I21: 20753.5 | J21: 3709 | K21: 18966.5 | L21: 21665 | M21: 18669.5 | N21: 17851.5 | O21: 17164 | P21: 16630.5 | Q21: 14580.5 | R21: 18571 | S21: 15397.5 | T21: 18636
A22: =SUM(O22:Z22) -> 686 | B22: HC | C22: 141 | D22: 141 | E22: 138 | F22: 130 | G22: 127 | H22: 125 | I22: 125 | J22: 120 | K22: 128 | L22: 127 | M22: 127 | N22: 123 | O22: 122 | P22: 116 | Q22: 112 | R22: 111 | S22: 109 | T22: 116
A23: =SUM(O23:Z23) -> -22089.5 | B23: Overall Absence Hours | C23: -3936.5 | D23: -3661.5 | E23: -6711.5 | F23: -10282.5 | G23: -6914 | H23: -4002 | I23: -3990 | J23: -3311 | K23: -4214.5 | L23: -4292.5 | M23: -4309 | N23: -6515 | O23: -5690.5 | P23: -3703.5 | Q23: -3267.5 | R23: -3337.5 | S23: -2679.5 | T23: -3411
A24: =SUM(O24:Z24) -> 1.0694754 | B24: Overall Absence Rate | C24: 0.14221973 | D24: 0.14534664 | E24: 0.30293387 | F24: 0.41899271 | G24: 0.2767205 | H24: 0.18960984 | I24: 0.16125447 | J24: 0.47165242 | K24: 0.18180838 | L24: 0.16536646 | M24: 0.18752312 | N24: 0.26737529 | O24: 0.24898816 | P24: 0.18213337 | Q24: 0.18307373 | R24: 0.15233813 | S24: 0.14822703 | T24: 0.15471493
A25: =SUM(O25:Z25) -> 1105 | B25: Hrs par 1.0FTE | C25: 202 | D25: 185 | E25: 168 | F25: 195.5 | G25: 201 | H25: 169 | I25: 202 | J25: 58.5 | K25: 191.5 | L25: 210.5 | M25: 185 | N25: 202 | O25: 201 | P25: 178 | Q25: 164.5 | R25: 202 | S25: 166 | T25: 193.5
A26: =SUM(O26:Z26) -> 548.45981 | B26: 1.0 FTE | C26: 117.53713 | D26: 116.37838 | E26: 91.925595 | F26: 72.933504 | G26: 89.90796 | H26: 101.21006 | I26: 102.7401 | J26: 63.401709 | K26: 99.041775 | L26: 102.92162 | M26: 100.91622 | N26: 88.373762 | O26: 85.393035 | P26: 93.429775 | Q26: 88.635258 | R26: 91.935644 | S26: 92.756024 | T26: 96.310078
A27: =SUM(O27:Z27) -> 5637.5 | B27: 1000 - Planned and approved | C27: 230.5 | D27: 266.5 | E27: 444.5 | F27: 513.5 | G27: 1045.5 | H27: 755.5 | I27: 737.5 | J27: 322.5 | K27: 509.5 | L27: 843.5 | M27: 895 | N27: 905 | O27: 603 | P27: 847.5 | Q27: 1023 | R27: 1173.5 | S27: 937 | T27: 1053.5
A28: =SUM(O28:Z28) -> 3169 | B28: 2000 - Planned and unapproved | C28: 1735 | D28: 986 | E28: 4868 | F28: 7480 | G28: 4153 | H28: 1502.5 | I28: 1396 | J28: 2562.5 | K28: 1268 | L28: 1117 | M28: 1598.5 | N28: 3093 | O28: 1553.5 | P28: 93 | Q28: 477.5 | R28: 373.5 | S28: 483 | T28: 188.5
A29: =SUM(O29:Z29) -> 2651.5 | B29: 3000 - Unplanned and unapproved | C29: 980 | D29: 837.5 | E29: 370 | F29: 373 | G29: 210 | H29: 454.5 | I29: 455.5 | J29: 56 | K29: 360 | L29: 496 | M29: 507 | N29: 445 | O29: 871 | P29: 339.5 | Q29: 274.5 | R29: 336 | S29: 222.5 | T29: 608
A30: =SUM(O30:Z30) -> 10631.5 | B30: 4000 - Unplanned and approved | C30: 991 | D30: 1571.5 | E30: 1029 | F30: 1916 | G30: 1505.5 | H30: 1289.5 | I30: 1401 | J30: 370 | K30: 2077 | L30: 1836 | M30: 1308.5 | N30: 2072 | O30: 2663 | P30: 2423.5 | Q30: 1492.5 | R30: 1454.5 | S30: 1037 | T30: 1561
A32: =SUM(O32:Z32) -> 13283 | B32: Absenteeism Hrs | C32: 1971 | D32: 2409 | E32: 1399 | F32: 2289 | G32: 1715.5 | H32: 1744 | I32: 1856.5 | J32: 426 | K32: 2437 | L32: 2332 | M32: 1815.5 | N32: 2517 | O32: 3534 | P32: 2763 | Q32: 1767 | R32: 1790.5 | S32: 1259.5 | T32: 2169
A33: =+A32/A20 -> 0.10793132 | B33: Absenteeism Rate | C33: 0.07120922 | D33: 0.095627493 | E33: 0.063146017 | F33: 0.093272483 | G33: 0.068659823 | H33: 0.082628574 | I33: 0.075029806 | J33: 0.060683761 | K33: 0.1051292 | L33: 0.08983916 | M33: 0.079008639 | N33: 0.10329756 | O33: 0.15463038 | P33: 0.13588079 | Q33: 0.099002689 | R33: 0.081726271 | S33: 0.069674172 | T33: 0.098380732
B35: Total worked hours and Overtime by Month
B37: Valori | C37: 45688 | D37: 45716 | E37: 45747 | F37: 45777 | G37: 45808 | H37: 45838 | I37: 45869 | J37: 45900 | K37: 45930 | L37: 45961 | M37: 45991 | N37: 46022 | O37: 46053 | P37: 46081 | Q37: 46112 | R37: 46142 | S37: 46173 | T37: 46203
A38: =SUM(O38:Z38) -> 150652.5 | B38: Payable Hours | C38: 31640 | D38: 27545 | E38: 22460 | F38: 20550 | G38: 24940.5 | H38: 26254 | I38: 29251.5 | J38: 6538.5 | K38: 27199 | L38: 29367.5 | M38: 25509.5 | N38: 28336.5 | O38: 24926 | P38: 23688 | Q38: 22906 | R38: 26452.5 | S38: 25268.5 | T38: 27411.5
A39: =SUM(O39:Z39) -> 142970 | B39: Worked Hours (Regular Hrs) | C39: 30578 | D39: 27764 | E39: 19899 | F39: 18771 | G39: 23784 | H39: 23249 | I39: 28405.5 | J39: 6313.5 | K39: 26257.5 | L39: 29561.5 | M39: 25807.5 | N39: 24668 | O39: 23842 | P39: 23490.5 | Q39: 21026 | R39: 26516 | S39: 21892.5 | T39: 26203
A40: =SUM(O40:Z40) -> 7024 | B40: AL12 - Jours fériés, chômés et payés | C40: 1275 | E40: 2440 | F40: 1160 | G40: 1136 | H40: 3192 | I40: 1048 | K40: 1088 | N40: 1112 | O40: 1104 | Q40: 1968 | S40: 2952 | T40: 1000
A41: =SUM(O41:Z41) -> 119 | B41: AL23 - Congés spéciaux pour raison de famille | C41: 67 | D41: 25.5 | E41: 0 | F41: 76.5 | G41: 8.5 | H41: 59.5 | I41: 51 | J41: 25.5 | K41: 25.5 | L41: 34 | M41: 17 | N41: 42.5 | O41: 42.5 | P41: 25.5 | Q41: 0 | R41: 25.5 | S41: 0 | T41: 25.5
A42: =SUM(O42:Z42) -> 0 | B42: AT39 - Chômage partiel payés | C42: 85 | D42: 0 | E42: 0 | F42: 0 | G42: 0 | H42: 0 | I42: 0 | J42: 0 | K42: 0 | L42: 0 | M42: 0 | N42: 0 | O42: 0 | P42: 0 | Q42: 0 | R42: 0 | S42: 0 | T42: 0
A43: =SUM(O43:Z43) -> 459 | B43: AT39 - Chômage partiel payés (H) | Q43: 72 | S43: 387
A44: =SUM(O44:Z44) -> 68 | B44: AT40 - Participation à la formation | C44: 0 | D44: 0 | E44: 0 | F44: 0 | G44: 0 | H44: 0 | I44: 0 | J44: 0 | K44: 0 | L44: 0 | M44: 0 | N44: 0 | O44: 17 | P44: 0 | Q44: 0 | R44: 34 | S44: 0 | T44: 17
A45: =SUM(O45:Z45) -> 345 | B45: AT40 - Participation à la formation (H) | M45: 36 | N45: 18 | O45: 12 | S45: 134 | T45: 199
A46: =SUM(O46:Z46) -> 219.5 | B46: 1.00x OT Hrs | C46: 0 | D46: 1.5 | E46: 220.5 | F46: 609.5 | G46: 87.5 | H46: 4.5 | I46: 1 | J46: 218.5 | K46: 24.5 | L46: 46.5 | M46: 24 | N46: 0 | O46: 60.5 | P46: 31 | Q46: 0 | R46: 0 | S46: 3 | T46: 125
A47: =SUM(O47:Z47) -> 22 | B47: 1.25x OT Hrs | C47: 54 | D47: 22 | F47: 10 | G47: 13 | H47: 76 | I47: 8 | L47: 28 | M47: 2 | T47: 22
A48: =SUM(O48:Z48) -> 1174 | B48: 1.75x OT Hrs | C48: 7.5 | D48: 24 | E48: 0 | F48: 28.5 | G48: 38.5 | H48: 0 | I48: 0 | J48: 206 | K48: 129 | L48: 179 | M48: 75 | N48: 0 | O48: 7 | P48: 40 | Q48: 0 | R48: 30 | S48: 392 | T48: 705
A49: =SUM(O49:Z49) -> 435.5 | B49: 2.00x OT Hrs | C49: 64 | D49: 5 | E49: 5 | F49: 10.5 | H49: 245.5 | I49: 48 | J49: 57.5 | K49: 71.5 | L49: 5.5 | M49: 11.5 | N49: 36 | O49: 44 | Q49: 96 | R49: 20 | S49: 165.5 | T49: 110
A50: =SUM(O50:Z50) -> 1012 | B50: Heures d'allaitement | C50: 204 | D50: 160 | E50: 145 | F50: 119 | G50: 195 | H50: 214 | I50: 263 | J50: 53 | K50: 220 | L50: 190 | M50: 144 | N50: 182 | O50: 164 | P50: 142 | Q50: 124 | R50: 160 | S50: 162 | T50: 260
A51: =SUM(O51:Z51) -> 0 | B51: Paid Partial or Technical unemployment | N51: 2677.5
A52: =SUM(O52:Z52) -> 368.5 | B52: PTO | C52: -67 | E52: 97 | F52: 96 | G52: 52 | H52: 3 | I52: 15 | J52: 16 | K52: 6.5 | L52: 4 | M52: -134 | N52: 8 | O52: 49 | P52: 234 | Q52: 20 | R52: 12.5 | S52: 21 | T52: 32
A53: =SUM(O53:Z53) -> -277 | B53: Ore Multa NP | C53: -41 | D53: -83 | E53: -42 | F53: -30 | G53: -32 | H53: -41 | I53: -62 | J53: -6 | K53: -78 | L53: -53 | M53: -81 | N53: -43 | O53: -46 | P53: -44 | Q53: -58 | R53: -36 | S53: -37 | T53: -56
A54: =SUM(O54:Z54) -> -296 | B54: Ore Multa di ass | C54: -68 | D54: -60 | E54: -48 | F54: -28 | G54: -44 | H54: -68 | I54: -88 | J54: -20 | K54: -52 | L54: -96 | M54: -80 | N54: -60 | O54: -52 | P54: -16 | Q54: -64 | R54: -48 | S54: -60 | T54: -56
A55: =SUM(O55:Z55) -> -148 | B55: Ore Multa di ritardo | C55: -57 | D55: -39 | E55: -43.5 | F55: -30 | G55: -25.5 | H55: -39 | I55: -50 | J55: -7 | K55: -33 | L55: -18.5 | M55: -29 | N55: -41.5 | O55: -21.5 | P55: -24 | Q55: -25 | R55: -35.5 | S55: -16 | T55: -26
A56: =SUM(O56:Z56) -> -177.5 | B56: Ore Multa diverse | C56: -78 | D56: -42 | E56: -63 | F56: -65 | G56: -13 | H56: -30 | I56: -61 | J56: -2 | K56: -40 | L56: -83 | M56: -49 | N56: -45 | O56: -81.5 | P56: -9 | Q56: -33 | R56: -16 | S56: -8 | T56: -30
A57: =SUM(O57:Z57) -> 153296 | B57: Grand Total Pay | C57: 31969.5 | D57: 27756 | E57: 22610 | F57: 20718 | G57: 25187 | H57: 26789.5 | I57: 29570.5 | J57: 6855 | K57: 27619.5 | L57: 29770 | M57: 25742 | N57: 28554.5 | O57: 25141 | P57: 23870 | Q57: 23126 | R57: 26662.5 | S57: 25988 | T57: 28508.5
A58: =SUM(O58:Z58) -> 8497 | B58: Pay vs Worked | C58: 1320 | D58: -38.5 | E58: 2485.5 | F58: 1298.5 | G58: 1277 | H58: 3290.5 | I58: 1116 | J58: 59.5 | K58: 1137 | L58: -22.5 | M58: -176 | N58: 3850.5 | O58: 1187.5 | P58: 308.5 | Q58: 2004 | R58: 96.5 | S58: 3535 | T58: 1365.5
A59: =+A58/A39 -> 0.059432049 | B59: % Pay vs Worked | C59: 1.0455066 | D59: 0.99971186 | E59: 1.136238 | F59: 1.1037238 | G59: 1.0589892 | H59: 1.1522861 | I59: 1.0410132 | J59: 1.0857686 | K59: 1.0518709 | L59: 1.0070531 | M59: 0.99746198 | N59: 1.1575523 | O59: 1.0544837 | P59: 1.0161555 | Q59: 1.0998763 | R59: 1.005525 | S59: 1.1870732 | T59: 1.0879861
A61: =SUM(A39:A56,-A47)-A57 -> 0 | B61: Ckeck | C61: 0 | D61: 0 | E61: 0 | F61: 0 | G61: 0 | H61: 0 | I61: 0 | J61: 0 | K61: 0 | L61: 0 | M61: 0 | N61: 0 | O61: 0 | P61: =SUM(P39:P56,-P47)-P57 -> 0 | Q61: =SUM(Q39:Q56,-Q47)-Q57 -> 0 | R61: =SUM(R39:R56,-R47)-R57 -> 0 | S61: 0 | T61: 0

Sheet Quality
A1: Apparel Quality Rate
A2: Apparel - FQC Defective Rate Finished Goods
A3: (Defective Units / Units Inspected) × 100
B5: MONTH JUN'26 | J5: YTD'26
A6: BU | B6: Qty prod | C6: Sample size | D6: Check Rate | E6: Defective units | F6: FQC Rej % | G6: TARGET | H6: +/- Vs trgt | J6: Qty prod | K6: Sample size | L6: Check Rate | M6: Defective units | N6: FQC Rej % | O6: % Yiled FQR | P6: % FPY | Q6: TARGET | R6: % Var. Vs trgt | T6: FY'25 | U6: % Var. Vs PY | W6: # Opportunities | X6: # Defects | Y6: DPU | Z6: DPR | AA6: Throughput Yield TPY | AB6: DPO | AC6: DPMO | AD6: Process Sigma level | AE6: DPMU (ppm) | AG6: Class | AI6: Rolled-throughput Yield RTY
A7: Safety | B7: 1500 | C7: 1677 | D7: =IFERROR(C7/B7,"") -> 1.118 | E7: 192 | F7: =IFERROR(E7/C7,"") -> 0.11449016 | G7: 0.035 | H7: =IFERROR(F7-G7,"") -> 0.079490161 | J7: 15299 | K7: 15783 | L7: =+K7/J7 -> 1.0316361 | M7: 1253 | N7: =+M7/K7 -> 0.079389216 | O7: =1-N7 -> 0.92061078 | P7: =(1-N7)/L7 -> 0.89237942 | Q7: 0.035 | R7: =IFERROR((N7/Q7)-1,0) -> 1.2682633 | T7: 0.054050203 | U7: =IFERROR((N7/T7)-1,0) -> 0.46880514 | W7: 6 | X7: 1379 | Y7: =+X7/K7 -> 0.087372489 | Z7: =+X7/M7 -> 1.1005587 | AA7: =1-Y7 -> 0.91262751 | AB7: =+X7/(K7*W7) -> 0.014562082 | AC7: =+(X7/(K7*W7))*10^6 -> 14562.082 | AD7: =IF(K7=0,"",(IF((AC7/1000000)>0.933199,0,IF((AC7/1000000)>0.5,1.5-ABS(NORMSINV(AC7/1000000)),ABS(NORMSINV(AC7/1000000))+1.5)))) -> 3.6818018 | AE7: =+(M7/K7)*10^6 -> 79389.216 | AG7: =IF(AC7="","",IF(AC7>20000,"BRONZE",IF(AC7<=6000,"PLATINUM",IF(AC7>15000,"SILVER","GOLD")))) -> GOLD
A8: Leather | B8: 1510 | C8: 1480 | D8: =IFERROR(C8/B8,"") -> 0.98013245 | E8: 151 | F8: =IFERROR(E8/C8,"") -> 0.10202703 | G8: 0.075 | H8: =IFERROR(F8-G8,"") -> 0.027027027 | J8: 7929 | K8: 7919 | L8: =+K8/J8 -> 0.99873881 | M8: 811 | N8: =+M8/K8 -> 0.10241192 | O8: =1-N8 -> 0.89758808 | P8: =(1-N8)/L8 -> 0.89872154 | Q8: 0.075 | R8: =IFERROR((N8/Q8)-1,0) -> 0.36549228 | T8: 0.06107739 | U8: =IFERROR((N8/T8)-1,0) -> 0.67675666 | W8: 6 | X8: 985 | Y8: =+X8/K8 -> 0.12438439 | Z8: =+X8/M8 -> 1.2145499 | AA8: =1-Y8 -> 0.87561561 | AB8: =+X8/(K8*W8) -> 0.020730732 | AC8: =+(X8/(K8*W8))*10^6 -> 20730.732 | AD8: =IF(K8=0,"",(IF((AC8/1000000)>0.933199,0,IF((AC8/1000000)>0.5,1.5-ABS(NORMSINV(AC8/1000000)),ABS(NORMSINV(AC8/1000000))+1.5)))) -> 3.5388854 | AE8: =+(M8/K8)*10^6 -> 102411.92 | AG8: =IF(AC8="","",IF(AC8>20000,"BRONZE",IF(AC8<=6000,"PLATINUM",IF(AC8>15000,"SILVER","GOLD")))) -> BRONZE
A9: D|air | B9: 1382 | C9: 1350 | D9: =IFERROR(C9/B9,"") -> 0.97684515 | E9: 88 | F9: =IFERROR(E9/C9,"") -> 0.065185185 | G9: 0.005 | H9: =IFERROR(F9-G9,"") -> 0.060185185 | J9: 5952 | K9: 5908 | L9: =+K9/J9 -> 0.99260753 | M9: 130 | N9: =+M9/K9 -> 0.022004062 | O9: =1-N9 -> 0.97799594 | P9: =(1-N9)/L9 -> 0.98527959 | Q9: 0.005 | R9: =IFERROR((N9/Q9)-1,0) -> 3.4008125 | T9: 0.0013636612 | U9: =IFERROR((N9/T9)-1,0) -> 15.136019 | W9: 6 | X9: 130 | Y9: =+X9/K9 -> 0.022004062 | Z9: =+X9/M9 -> 1 | AA9: =1-Y9 -> 0.97799594 | AB9: =+X9/(K9*W9) -> 0.0036673437 | AC9: =+(X9/(K9*W9))*10^6 -> 3667.3437 | AD9: =IF(K9=0,"",IF(X9=0,6,IF((AC9/1000000)>0.933199,0,IF((AC9/1000000)>0.5,1.5-ABS(NORMSINV(AC9/1000000)),ABS(NORMSINV(AC9/1000000))+1.5)))) -> 4.1812538 | AE9: =+(M9/K9)*10^6 -> 22004.062 | AG9: =IF(AC9="","",IF(AC9>20000,"BRONZE",IF(AC9<=6000,"PLATINUM",IF(AC9>15000,"SILVER","GOLD")))) -> PLATINUM
A10: MEL-T | B10: =SUM(B7:B9) -> 4392 | C10: =SUM(C7:C9) -> 4507 | D10: =IFERROR(C10/B10,"") -> 1.026184 | E10: =SUM(E7:E9) -> 431 | F10: =IFERROR(E10/C10,"") -> 0.095629022 | G10: =AVERAGE(G7:G9) -> 0.038333333 | H10: =IFERROR(F10-G10,"") -> 0.057295688 | J10: =SUM(J7:J9) -> 29180 | K10: =SUM(K7:K9) -> 29610 | L10: =+K10/J10 -> 1.0147361 | M10: =SUM(M7:M9) -> 2194 | N10: =+M10/K10 -> 0.074096589 | O10: =1-N10 -> 0.92590341 | P10: =(1-N10)/L10 -> 0.91245733 | Q10: =AVERAGE(Q7:Q9) -> 0.038333333 | R10: =IFERROR((N10/Q10)-1,0) -> 0.9329545 | T10: 0.043450706 | U10: =IFERROR((N10/T10)-1,0) -> 0.7053023 | W10: 6 | X10: =SUM(X7:X9) -> 2494 | Y10: =+X10/K10 -> 0.084228301 | Z10: =+X10/M10 -> 1.1367366 | AA10: =1-Y10 -> 0.9157717 | AB10: =+X10/(K10*W10) -> 0.01403805 | AC10: =+(X10/(K10*W10))*10^6 -> 14038.05 | AD10: =IF(K10=0,"",(IF((AC10/1000000)>0.933199,0,IF((AC10/1000000)>0.5,1.5-ABS(NORMSINV(AC10/1000000)),ABS(NORMSINV(AC10/1000000))+1.5)))) -> 3.6962214 | AE10: =+(M10/K10)*10^6 -> 74096.589 | AG10: =IF(AC10="","",IF(AC10>20000,"BRONZE",IF(AC10<=6000,"PLATINUM",IF(AC10>15000,"SILVER","GOLD")))) -> GOLD | AI10: =PRODUCT(AA7:AA9) -> 0.78152721
A11: * The results of the D|air plant refer to the airbag sac (test sac 100%) ** Leather refer only to the Finished Goods
A13: BU | B13: 45838 | C13: 45869 | D13: 45900 | E13: 45930 | F13: 45961 | G13: 45991 | H13: 46022 | I13: 46053 | J13: 46081 | K13: 46112 | L13: 46142 | M13: 46173 | N13: 46203
A14: Safety | B14: 0.068409164 | C14: 0.049539171 | D14: 0.033482143 | E14: 0.048514251 | F14: 0.072122923 | G14: 0.043126685 | H14: 0.044018059 | I14: 0.054557777 | J14: 0.071646859 | K14: 0.10163468 | L14: 0.092005513 | M14: 0.059351816 | N14: 0.11449016
A15: Leather | B15: 0.06268307 | C15: 0.068376068 | D15: 0.078328982 | E15: 0.051051051 | F15: 0.070320579 | G15: 0.082182774 | H15: 0.12467306 | I15: 0.12712491 | J15: 0.089358245 | K15: 0.076028623 | L15: 0.08632041 | M15: 0.12773723 | N15: 0.10202703
A16: D|air | B16: 0.004587156 | C16: 0.0028208745 | D16: 0.0032051282 | E16: 0.0017006803 | F16: 0.0016411379 | G16: 0.0028801843 | H16: 0.00069979006 | I16: 0 | J16: 0 | K16: 0 | L16: 0 | M16: 0.067524116 | N16: 0.065185185
A17: MEL-T | B17: 0.049923664 | C17: 0.04919994 | D17: 0.037273173 | E17: 0.041293167 | F17: 0.053085887 | G17: 0.041831683 | H17: 0.049019608 | I17: 0.068181818 | J17: 0.063052445 | K17: 0.077436861 | L17: 0.06644805 | M17: 0.081045465 | N17: 0.095629022
A18: * The results of the BU D|air refer to the Airbag Sac
A21: Apparel - OQC Defective Rate Finished goods
A22: (Defective Units / Units Inspected) × 100
B24: MONTH JUN'26 | J24: YTD'26
A25: BU | B25: Qty prod | C25: Sample size | D25: Check Rate | E25: Defective units | F25: OQC Rej % | G25: TARGET | H25: +/- Vs trgt | J25: Qty prod | K25: Sample size | L25: Check Rate | M25: Defective units | N25: OQC Rej % | O25: % Yiled OQR | P25: % FPY | Q25: TARGET | R25: % Var. Vs trgt | T25: FY'25 | U25: % Var. Vs PY | W25: # Opportunities | X25: # Defects | Y25: DPU | Z25: DPR | AA25: Throughput Yield | AB25: DPO | AC25: DPMO | AD25: Process Sigma level | AE25: DPMU (ppm) | AG25: Class | AI25: Rolled-throughput Yield RTY
A26: Safety | B26: 1500 | C26: 433 | D26: =IFERROR(C26/B26,"") -> 0.28866667 | E26: 6 | F26: =IFERROR(E26/C26,"") -> 0.013856813 | G26: 0.015 | H26: =IFERROR(F26-G26,"") -> -0.0011431871 | J26: 15299 | K26: 4145 | L26: =+K26/J26 -> 0.27093274 | M26: 43 | N26: =+M26/K26 -> 0.010373945 | O26: =1-N26 -> 0.98962606 | Q26: 0.015 | R26: =IFERROR((N26/Q26)-1,0) -> -0.3084037 | T26: 0.01439158 | U26: =IFERROR((N26/T26)-1,0) -> -0.27916569 | W26: 7 | X26: 46 | Y26: =+X26/K26 -> 0.011097708 | Z26: =+X26/M26 -> 1.0697674 | AA26: =1-Y26 -> 0.98890229 | AB26: =+X26/(K26*W26) -> 0.0015853869 | AC26: =+(X26/(K26*W26))*10^6 -> 1585.3869 | AD26: =IF(AC26=0,6,(_xlfn.NORM.S.INV(1-(AC26/10^6)))+1.5) -> 4.4506779 | AE26: =+(M26/K26)*10^6 -> 10373.945 | AG26: =IF(AC26="","",IF(AC26>20000,"BRONZE",IF(AC26<=6000,"PLATINUM",IF(AC26>15000,"SILVER","GOLD")))) -> PLATINUM
A27: Leather | B27: 1510 | C27: 535 | D27: =IFERROR(C27/B27,"") -> 0.35430464 | E27: 2 | F27: =IFERROR(E27/C27,"") -> 0.0037383178 | G27: 0.015 | H27: =IFERROR(F27-G27,"") -> -0.011261682 | J27: 7929 | K27: 2703 | L27: =+K27/J27 -> 0.34090049 | M27: 14 | N27: =+M27/K27 -> 0.0051794303 | O27: =1-N27 -> 0.99482057 | Q27: 0.015 | R27: =IFERROR((N27/Q27)-1,0) -> -0.65470465 | T27: 0.010797016 | U27: =IFERROR((N27/T27)-1,0) -> -0.52029059 | W27: 7 | X27: 15 | Y27: =+X27/K27 -> 0.0055493896 | Z27: =+X27/M27 -> 1.0714286 | AA27: =1-Y27 -> 0.99445061 | AB27: =+X27/(K27*W27) -> 0.00079276994 | AC27: =+(X27/(K27*W27))*10^6 -> 792.76994 | AD27: =IF(AC27=0,6,(_xlfn.NORM.S.INV(1-(AC27/10^6)))+1.5) -> 4.6585539 | AE27: =+(M27/K27)*10^6 -> 5179.4303 | AG27: =IF(AC27="","",IF(AC27>20000,"BRONZE",IF(AC27<=6000,"PLATINUM",IF(AC27>15000,"SILVER","GOLD")))) -> PLATINUM
A28: D|air | B28: 1019 | C28: 322 | D28: =IFERROR(C28/B28,"") -> 0.31599607 | E28: 2 | F28: =IFERROR(E28/C28,"") -> 0.0062111801 | G28: 0.005 | H28: =IFERROR(F28-G28,"") -> 0.0012111801 | J28: 6583 | K28: 1560 | L28: =+K28/J28 -> 0.23697402 | M28: 8 | N28: =+M28/K28 -> 0.0051282051 | O28: =1-N28 -> 0.99487179 | Q28: 0.005 | R28: =IFERROR((N28/Q28)-1,0) -> 0.025641026 | T28: 0.0064613397 | U28: =IFERROR((N28/T28)-1,0) -> -0.20632479 | W28: 7 | X28: 8 | Y28: =+X28/K28 -> 0.0051282051 | Z28: =+X28/M28 -> 1 | AA28: =1-Y28 -> 0.99487179 | AB28: =+X28/(K28*W28) -> 0.00073260073 | AC28: =+(X28/(K28*W28))*10^6 -> 732.60073 | AD28: =IF(AC28=0,6,(_xlfn.NORM.S.INV(1-(AC28/10^6)))+1.5) -> 4.6814889 | AE28: =+(M28/K28)*10^6 -> 5128.2051 | AG28: =IF(AC28="","",IF(AC28>20000,"BRONZE",IF(AC28<=6000,"PLATINUM",IF(AC28>15000,"SILVER","GOLD")))) -> PLATINUM
A29: MEL-T | B29: =SUM(B26:B28) -> 4029 | C29: =SUM(C26:C28) -> 1290 | D29: =IFERROR(C29/B29,"") -> 0.3201787 | E29: =SUM(E26:E28) -> 10 | F29: =IFERROR(E29/C29,"") -> 0.007751938 | G29: =AVERAGE(G26:G28) -> 0.011666667 | H29: =IFERROR(F29-G29,"") -> -0.0039147287 | J29: =SUM(J26:J28) -> 29811 | K29: =SUM(K26:K28) -> 8408 | L29: =+K29/J29 -> 0.28204354 | M29: =SUM(M26:M28) -> 65 | N29: =+M29/K29 -> 0.0077307326 | O29: =1-N29 -> 0.99226927 | Q29: =AVERAGE(Q26:Q28) -> 0.011666667 | R29: =IFERROR((N29/Q29)-1,0) -> -0.33736577 | T29: 0.01149727 | U29: =IFERROR((N29/T29)-1,0) -> -0.32760276 | W29: 7 | X29: =SUM(X26:X28) -> 69 | Y29: =+X29/K29 -> 0.00820647 | Z29: =+X29/M29 -> 1.0615385 | AA29: =1-Y29 -> 0.99179353 | AB29: =+X29/(K29*W29) -> 0.0011723529 | AC29: =+(X29/(K29*W29))*10^6 -> 1172.3529 | AD29: =IF(AC29=0,6,(_xlfn.NORM.S.INV(1-(AC29/10^6)))+1.5) -> 4.5426941 | AE29: =+(M29/K29)*10^6 -> 7730.7326 | AG29: =IF(AC29="","",IF(AC29>20000,"BRONZE",IF(AC29<=6000,"PLATINUM",IF(AC29>15000,"SILVER","GOLD")))) -> PLATINUM | AI29: =PRODUCT(AA26:AA28) -> 0.97837134
A30: * The results of the BU refer to the Finished Goods
A32: BU | B32: 45838 | C32: 45869 | D32: 45900 | E32: 45930 | F32: 45961 | G32: 45991 | H32: 46022 | I32: 46053 | J32: 46081 | K32: 46112 | L32: 46142 | M32: 46173 | N32: 46203
A33: Safety | B33: 0.0054347826 | C33: 0 | D33: 0.0086956522 | E33: 0.012617221 | F33: 0.024288107 | G33: 0.026275116 | H33: 0.0021691974 | I33: 0.017567568 | J33: 0.007585335 | K33: 0.010479042 | L33: 0.012642225 | M33: 0.0013850416 | N33: 0.013856813
A34: Leather | B34: 0.0091116173 | C34: 0.0067226891 | D34: 0 | E34: 0.013565891 | F34: 0.0014245014 | G34: 0.016393443 | H34: 0.022727273 | I34: 0 | J34: 0.017632242 | K34: 0.0029069767 | L34: 0.002016129 | M34: 0.0065075922 | N34: 0.0037383178
A35: D|air | B35: 0.01320132 | C35: 0 | D35: 0 | E35: 0 | F35: 0.008291874 | G35: 0 | H35: 0 | I35: 0.0076923077 | J35: 0 | K35: 0 | L35: 0.012820513 | M35: 0.0037313433 | N35: 0.0062111801
A36: MEL-T | B36: 0.0081190798 | C36: 0.0021609941 | D36: 0.004601227 | E36: 0.010835641 | F36: 0.014005602 | G36: 0.020466445 | H36: 0.0072683222 | I36: 0.010204082 | J36: 0.0090277778 | K36: 0.0064724919 | L36: 0.0092044707 | M36: 0.0034458994 | N36: 0.007751938
A54: Further definitions:
A55: Defects and units are fairly straightforward but some folks struggle with the number of opportunities. The number of opportunities is based on how you choose to count defects. Here are some examples:
A56: One opportunity: an item is either wrong or right, good or bad.
A57: Two opportunities: A package could have the wrong product or the wrong # products in it.
A58: Example of three opportunities: a shirt you order could be the wrong: size, style or color.
A60: Six Sigma Table: | D60: 1 | E60: 690000
D61: 2 | E61: 308000
D62: 3 | E62: 66800
D63: 4 | E63: 6210
D64: 5 | E64: 320
D65: 6 | E65: 3.4
A67: Six Sigma Ratings (σ)
A68: 1 Sigma = 691,462 DPMO, 30.85% defect-free
A69: 2 Sigma = 308,538 DPMO, 69.146% defect-free
A70: 3 Sigma = 66,807 DPMO, 93.319% defect-free
A71: 4 Sigma = 6,210 DPMO, 99.379% defect-free
A72: 5 Sigma = 233 DPMO, 99.977% defect-free
A73: 6 Sigma = 3.4 DPMO, 99.99966% defect-free.
A75: Class | B75: DPMO | E75: Typical FPY Benchmarks (General Guidance)
A76: PLATINUM | B76: < 6.000
A77: GOLD | B77: < 15.000 | E77: FPY Level | F77: Meaning
A78: SILVER | B78: < 20.000 | E78: < 85% | F78: Poor – urgent improvement needed
A79: BRONZE | B79: > 20.000 | E79: 85–95% | F79: Acceptable but improvable
E80: > 95% | F80: Excellent
E81: ≥ 99% | F81: World‑class

Sheet Ph_QC
A1: Productivity (p/h) - FQC
A2: (Finished goods output / Total worked hours)
A3: BU | C3: 45688 | D3: 45716 | E3: 45747 | F3: 45777 | G3: 45808 | H3: 45838 | I3: 45869 | J3: 45900 | K3: 45930 | L3: 45961 | M3: 45991 | N3: 46022 | O3: 46053 | P3: 46081 | Q3: 46112 | R3: 46142 | S3: 46173 | T3: 46203 | U3: YTD | V3: TARGET | W3: %Var. Vs trgt | X3: MoM% | Y3: PYTD | Z3: YoY %
A4: BU02 - Safety | B4: QC_Pcs | C4: 4377 | D4: 3694 | E4: 3161 | F4: 3199 | G4: 3454 | H4: 2969 | I4: 4374 | J4: 1312 | K4: 1683 | L4: 5771 | M4: 4927 | N4: 3646 | O4: 2951 | P4: 2686 | Q4: 2775 | R4: 2893 | S4: 2500 | T4: 1561 | U4: =SUM(O4:T4) -> 15366 | X4: =IFERROR(T4/S4-1,100%) -> -0.3756 | Y4: =SUM(C4:H4) -> 20854 | Z4: =+U4/Y4-1 -> -0.26316294
A5: BU02 - Safety | B5: Worked Hrs | C5: 388 | D5: 393 | E5: 291 | F5: 259 | G5: 323.5 | H5: 356 | I5: 273 | J5: 74.5 | K5: 346 | L5: 504.5 | M5: 428.5 | N5: 351 | O5: 290.5 | P5: 333.5 | Q5: 442.5 | R5: 508.5 | S5: 325 | T5: 360 | U5: =SUM(O5:T5) -> 2260 | X5: =IFERROR(T5/S5-1,100%) -> 0.10769231 | Y5: =SUM(C5:H5) -> 2010.5 | Z5: =+U5/Y5-1 -> 0.12409848
A6: BU02 - Safety | B6: Productivity_QC_Ph | C6: 11.280928 | D6: 9.3994911 | E6: 10.862543 | F6: 12.351351 | G6: 10.676971 | H6: 8.3398876 | I6: 16.021978 | J6: 17.610738 | K6: 4.8641618 | L6: 11.439049 | M6: 11.49825 | N6: 10.387464 | O6: 10.158348 | P6: 8.053973 | Q6: 6.2711864 | R6: 5.6892822 | S6: 7.6923077 | T6: 4.3361111 | U6: =+U4/U5 -> 6.799115 | V6: 8.1872465 | W6: =+U6/V6-1 -> -0.16954802 | X6: =IFERROR(T6/S6-1,100%) -> -0.43630556 | Y6: =+Y4/Y5 -> 10.372544 | Z6: =+U6/Y6-1 -> -0.34450845
A8: BU03 - Leather | B8: QC_Pcs | C8: 2304 | D8: 1643 | E8: 1500 | F8: 1283 | G8: 1524 | H8: 1766 | I8: 1679 | J8: 367 | K8: 960 | L8: 2837 | M8: 1490 | N8: 1073 | O8: 1358 | P8: 1221 | Q8: 1127 | R8: 1329 | S8: 1435 | T8: 1511 | U8: =SUM(O8:T8) -> 7981 | X8: =IFERROR(T8/S8-1,100%) -> 0.052961672 | Y8: =SUM(C8:H8) -> 10020 | Z8: =+U8/Y8-1 -> -0.20349301
A9: BU03 - Leather | B9: Worked Hrs | C9: 419.5 | D9: 459.5 | E9: 375 | F9: 346.5 | G9: 408 | H9: 432.5 | I9: 450.5 | J9: 75.5 | K9: 361.5 | L9: 433 | M9: 355.5 | N9: 407 | O9: 367 | P9: 386 | Q9: 354.5 | R9: 384 | S9: 444 | T9: 504.5 | U9: =SUM(O9:T9) -> 2440 | X9: =IFERROR(T9/S9-1,100%) -> 0.13626126 | Y9: =SUM(C9:H9) -> 2441 | Z9: =+U9/Y9-1 -> -0.00040966817
A10: BU03 - Leather | B10: Productivity_QC_Ph | C10: 5.4922527 | D10: 3.5756257 | E10: 4 | F10: 3.7027417 | G10: 3.7352941 | H10: 4.083237 | I10: 3.72697 | J10: 4.8609272 | K10: 2.6556017 | L10: 6.551963 | M10: 4.1912799 | N10: 2.6363636 | O10: 3.7002725 | P10: 3.1632124 | Q10: 3.1791255 | R10: 3.4609375 | S10: 3.231982 | T10: 2.9950446 | U10: =+U8/U9 -> 3.2709016 | V10: 1.97 | W10: =+U10/V10-1 -> 0.66035616 | X10: =IFERROR(T10/S10-1,100%) -> -0.073310243 | Y10: =+Y8/Y9 -> 4.1048751 | Z10: =+U10/Y10-1 -> -0.20316658
A12: BU04 - D|air | B12: QC_Pcs | Y12: =SUM(C12:H12) -> 0
A13: BU04 - D|air | B13: Worked Hrs | Y13: =SUM(C13:H13) -> 0
A14: BU04 - D|air | B14: Productivity_QC_Ph
A16: QC_Pcs totale | C16: 6681 | D16: 5337 | E16: 4661 | F16: 4482 | G16: 4978 | H16: 4735 | I16: 6053 | J16: 1679 | K16: 2643 | L16: 8608 | M16: 6417 | N16: 4719 | O16: 4309 | P16: 3907 | Q16: 3902 | R16: 4222 | S16: 3935 | T16: 3072 | U16: =SUM(O16:T16) -> 23347 | X16: =IFERROR(T16/S16-1,100%) -> -0.21931385 | Y16: =SUM(C16:H16) -> 30874 | Z16: =+U16/Y16-1 -> -0.24379737
A17: Worked Hrs totale | C17: 807.5 | D17: 852.5 | E17: 666 | F17: 605.5 | G17: 731.5 | H17: 788.5 | I17: 723.5 | J17: 150 | K17: 707.5 | L17: 937.5 | M17: 784 | N17: 758 | O17: 657.5 | P17: 719.5 | Q17: 797 | R17: 892.5 | S17: 769 | T17: 864.5 | U17: =SUM(O17:T17) -> 4700 | X17: =IFERROR(T17/S17-1,100%) -> 0.12418726 | Y17: =SUM(C17:H17) -> 4451.5 | Z17: =+U17/Y17-1 -> 0.05582388
A18: Productivity_QC_Ph totale | C18: 8.2736842 | D18: 6.2604106 | E18: 6.9984985 | F18: 7.402147 | G18: 6.8051948 | H18: 6.0050729 | I18: 8.3662751 | J18: 11.193333 | K18: 3.735689 | L18: 9.1818667 | M18: 8.184949 | N18: 6.2255937 | O18: 6.5536122 | P18: 5.4301598 | Q18: 4.8958595 | R18: 4.7305322 | S18: 5.1170351 | T18: 3.5534991 | U18: =+U16/U17 -> 4.9674468 | V18: 6.56 | W18: =+U18/V18-1 -> -0.24276725 | X18: =IFERROR(T18/S18-1,100%) -> -0.30555506 | Y18: =+Y16/Y17 -> 6.9356397 | Z18: =+U18/Y18-1 -> -0.28377957
A19: * Non incluso IPQC-FPLS
A21: Throughtput (p/h) - FQC
A22: (Finished goods output / 1.0 FTE worked hours)
A23: BU_CDC | C23: 45688 | D23: 45716 | E23: 45747 | F23: 45777 | G23: 45808 | H23: 45838 | I23: 45869 | J23: 45900 | K23: 45930 | L23: 45961 | M23: 45991 | N23: 46022 | O23: 46053 | P23: 46081 | Q23: 46112 | R23: 46142 | S23: 46173 | T23: 46203 | U23: YTD | V23: TARGET | W23: %Var. Vs trgt | X23: MoM% | Y23: PYTD | Z23: YoY %
A24: BU02 - Safety | B24: QC_Pcs | C24: 4377 | D24: 3694 | E24: 3161 | F24: 3199 | G24: 3454 | H24: 2969 | I24: 4374 | J24: 1312 | K24: 1683 | L24: 5771 | M24: 4927 | N24: 3646 | O24: 2951 | P24: 2686 | Q24: 2775 | R24: 2893 | S24: 2500 | T24: 1561 | U24: =SUM(O24:T24) -> 15366 | X24: =IFERROR(T24/S24-1,100%) -> -0.3756 | Y24: =SUM(C24:H24) -> 20854 | Z24: =+U24/Y24-1 -> -0.26316294
A25: BU02 - Safety | B25: Run_hrs_YTD | C25: 202 | D25: 185 | E25: 133 | F25: 136 | G25: 170 | H25: 160.5 | I25: 194.5 | J25: 34 | K25: 183 | L25: 210.5 | M25: 185 | N25: 187 | O25: 192.5 | P25: 178 | Q25: 164.5 | R25: 202 | S25: 169 | T25: 205.5 | U25: =SUM(O25:T25) -> 1111.5 | X25: =IFERROR(T25/S25-1,100%) -> 0.21597633 | Y25: =SUM(C25:H25) -> 986.5 | Z25: =+U25/Y25-1 -> 0.12671059
A26: BU02 - Safety | B26: Throughput (ph)_QC | C26: 21.668317 | D26: 19.967568 | E26: 23.766917 | F26: 23.522059 | G26: 20.317647 | H26: 18.498442 | I26: 22.488432 | J26: 38.588235 | K26: 9.1967213 | L26: 27.415677 | M26: 26.632432 | N26: 19.497326 | O26: 15.32987 | P26: 15.089888 | Q26: 16.869301 | R26: 14.321782 | S26: 14.792899 | T26: 7.5961071 | U26: =+U24/U25 -> 13.824561 | V26: 40.936233 | W26: =+U26/V26-1 -> -0.66229033 | X26: =IFERROR(T26/S26-1,100%) -> -0.48650316 | Y26: =+Y24/Y25 -> 21.139382 | Z26: =+U26/Y26-1 -> -0.34602811
A28: BU03 - Leather | B28: QC_Pcs | C28: 2304 | D28: 1643 | E28: 1500 | F28: 1283 | G28: 1524 | H28: 1766 | I28: 1679 | J28: 367 | K28: 960 | L28: 2837 | M28: 1490 | N28: 1073 | O28: 1358 | P28: 1221 | Q28: 1127 | R28: 1329 | S28: 1434 | T28: 1511 | U28: =SUM(O28:T28) -> 7980 | X28: =IFERROR(T28/S28-1,100%) -> 0.053695955 | Y28: =SUM(C28:H28) -> 10020 | Z28: =+U28/Y28-1 -> -0.20359281
A29: BU03 - Leather | B29: Run_hrs_YTD | C29: 202 | D29: 185 | E29: 133 | F29: 136 | G29: 170 | H29: 160.5 | I29: 194.5 | J29: 34 | K29: 183 | L29: 210.5 | M29: 185 | N29: 187 | O29: 192.5 | P29: 178 | Q29: 164.5 | R29: 202 | S29: 169 | T29: 205.5 | U29: =SUM(O29:T29) -> 1111.5 | X29: =IFERROR(T29/S29-1,100%) -> 0.21597633 | Y29: =SUM(C29:H29) -> 986.5 | Z29: =+U29/Y29-1 -> 0.12671059
A30: BU03 - Leather | B30: Throughput (ph)_QC | C30: 11.405941 | D30: 8.8810811 | E30: 11.278195 | F30: 9.4338235 | G30: 8.9647059 | H30: 11.003115 | I30: 8.6323907 | J30: 10.794118 | K30: 5.2459016 | L30: 13.477435 | M30: 8.0540541 | N30: 5.7379679 | O30: 7.0545455 | P30: 6.8595506 | Q30: 6.8510638 | R30: 6.5792079 | S30: 8.4852071 | T30: 7.3527981 | U30: =+U28/U29 -> 7.1794872 | V30: 9.83 | W30: =+U30/V30-1 -> -0.26963508 | X30: =IFERROR(T30/S30-1,100%) -> -0.13345685 | Y30: =+Y28/Y29 -> 10.157121 | Z30: =+U30/Y30-1 -> -0.29315728
A32: BU04 - D|air | B32: QC_Pcs | Y32: =SUM(C32:H32) -> 0
A33: BU04 - D|air | B33: Run_hrs_YTD | C33: 202 | D33: 185 | E33: 133 | F33: 136 | G33: 170 | H33: 160.5 | I33: 194.5 | J33: 34 | K33: 183 | L33: 210.5 | M33: 185 | N33: 187 | O33: 192.5 | P33: 178 | Q33: 164.5 | R33: 202 | S33: 169 | T33: 205.5 | U33: =SUM(O33:T33) -> 1111.5 | Y33: =SUM(C33:H33) -> 986.5
A34: BU04 - D|air | B34: Throughput (ph)_QC | Y34: =+Y32/Y33 -> 0
A36: QC_Pcs totale | C36: 6681 | D36: 5337 | E36: 4661 | F36: 4482 | G36: 4978 | H36: 4735 | I36: 6053 | J36: 1679 | K36: 2643 | L36: 8608 | M36: 6417 | N36: 4719 | O36: 4309 | P36: 3907 | Q36: 3902 | R36: 4222 | S36: 3934 | T36: 3072 | U36: =SUM(O36:T36) -> 23346 | X36: =IFERROR(T36/S36-1,100%) -> -0.2191154 | Y36: =SUM(C36:H36) -> 30874 | Z36: =+U36/Y36-1 -> -0.24382976
A37: Run_hrs_YTD totale | C37: 202 | D37: 185 | E37: 133 | F37: 136 | G37: 170 | H37: 160.5 | I37: 194.5 | J37: 34 | K37: 183 | L37: 210.5 | M37: 185 | N37: 187 | O37: 192.5 | P37: 178 | Q37: 164.5 | R37: 202 | S37: 169 | T37: 205.5 | U37: =SUM(O37:T37) -> 1111.5 | X37: =IFERROR(T37/S37-1,100%) -> 0.21597633 | Y37: =SUM(C37:H37) -> 986.5 | Z37: =+U37/Y37-1 -> 0.12671059
A38: Throughput (ph)_QC totale | C38: 33.074257 | D38: 28.848649 | E38: 35.045113 | F38: 32.955882 | G38: 29.282353 | H38: 29.501558 | I38: 31.120823 | J38: 49.382353 | K38: 14.442623 | L38: 40.893112 | M38: 34.686486 | N38: 25.235294 | O38: 22.384416 | P38: 21.949438 | Q38: 23.720365 | R38: 20.90099 | S38: 23.278107 | T38: 14.948905 | U38: =+U36/U37 -> 21.004049 | V38: 65.58 | W38: =+U38/V38-1 -> -0.67971869 | X38: =IFERROR(T38/S38-1,100%) -> -0.35781267 | Y38: =+Y36/Y37 -> 31.296503 | Z38: =+U38/Y38-1 -> -0.32886915

Sheet Efficiency
A1: Productivity & Efficiency
A2: Operational Efficiency % (O-Eff%)
A3: (Standard minutes produced × Standard cycle time) / Total worked minutes × 100
A4: SAFETY | B4: 45688 | C4: 45716 | D4: 45747 | E4: 45777 | F4: 45808 | G4: 45838 | H4: 45869 | I4: 45900 | J4: 45930 | K4: 45961 | L4: 45991 | M4: 46022 | N4: 46053 | O4: 46081 | P4: 46112 | Q4: 46142 | R4: 46173 | S4: 46203 | T4: YTD | U4: TARGET | V4: % Var. vs trgt | W4: MoM % | X4: PYTD | Y4: YoY% | Z4: WIP FG | AA4: coda 2025 su 2026
A5: Production Volume FG | B5: 4523 | C5: 3850 | D5: 2740 | E5: 3280 | F5: 3583 | G5: 2928 | H5: 4382 | I5: 1140 | J5: 3357 | K5: 3617 | L5: 4784 | M5: 3331 | N5: 3246 | O5: 2503 | P5: 2749 | Q5: 2769 | R5: 2532 | S5: 1500 | T5: =SUM(N5:S5) -> 15299 | W5: =IFERROR(S5/R5-1,100%) -> -0.40758294 | X5: =SUM(B5:G5) -> 20904 | Y5: =+T5/X5-1 -> -0.2681305 | Z5: =+T5+AA5-Delivery!U40 -> 18 | AA5: 1537
A6: Std minutes produced | B6: 202146.49 | C6: 170449.61 | D6: 136977.9 | E6: 112796.4 | F6: 153489.39 | G6: 133601.25 | H6: 171640.58 | I6: 25459.24 | J6: 142370.34 | K6: 153598.73 | L6: 163253.58 | M6: 155414.94 | N6: 131914.28 | O6: 115658.17 | P6: 118011.03 | Q6: 137511.03 | R6: 104725.79 | S6: 100927.74 | T6: =SUM(N6:S6) -> 708748.04 | W6: =IFERROR(S6/R6-1,100%) -> -0.036266616 | X6: =SUM(B6:G6) -> 909461.04 | Y6: =+T6/X6-1 -> -0.22069445
A7: Worked minutes | B7: 304050 | C7: 276330 | D7: 219150 | E7: 190080 | F7: 219780 | G7: 200400 | H7: 239400 | I7: 43050 | J7: 212970 | K7: 248370 | L7: 217110 | M7: 208800 | N7: 190860 | O7: 176870 | P7: 180120 | Q7: 191220 | R7: 151080 | S7: 178980 | T7: =SUM(N7:S7) -> 1069130 | W7: =IFERROR(S7/R7-1,100%) -> 0.18467037 | X7: =SUM(B7:G7) -> 1409790 | Y7: =+T7/X7-1 -> -0.24163883
A8: Efficiency (mth) | B8: =IFERROR(B6/B7,"") -> 0.66484621 | C8: =IFERROR(C6/C7,"") -> 0.61683353 | D8: =IFERROR(D6/D7,"") -> 0.62504175 | E8: =IFERROR(E6/E7,"") -> 0.5934154 | F8: =IFERROR(F6/F7,"") -> 0.69837742 | G8: =IFERROR(G6/G7,"") -> 0.6666729 | H8: =IFERROR(H6/H7,"") -> 0.71696149 | I8: =IFERROR(I6/I7,"") -> 0.59138769 | ... S8: =IFERROR(S6/S7,"") -> 0.56390513 | W8: =IFERROR(S8/R8-1,100%) -> -0.18649659
A9: Efficiency (ytd) | B9: =SUM($B6:B6)/SUM($B7:B7) -> 0.66484621 | C9: =SUM($B6:C6)/SUM($B7:C7) -> 0.64198646 | D9: =SUM($B6:D6)/SUM($B7:D7) -> 0.63734194 | E9: =SUM($B6:E6)/SUM($B7:E7) -> 0.62890472 | F9: =SUM($B6:F6)/SUM($B7:F7) -> 0.64152985 | G9: =SUM($B6:G6)/SUM($B7:G7) -> 0.64510391 | H9: =SUM($B6:H6)/SUM($B7:H7) -> 0.65553491 | I9: =SUM($B6:I6)/SUM($B7:I7) -> 0.65390303 | ... M9: =SUM($B6:M6)/SUM($B7:M7) -> 0.66726308 | N9: =SUM(N6:$N6)/SUM(N7:$N7) -> 0.69115729 | O9: =SUM($N6:O6)/SUM($N7:O7) -> 0.67324517 | P9: =SUM($N6:P6)/SUM($N7:P7) -> 0.66730579 | Q9: =SUM($N6:Q6)/SUM($N7:Q7) -> 0.68071293 | R9: =SUM($N6:R6)/SUM($N7:R7) -> 0.68282907 | S9: =SUM($N6:S6)/SUM($N7:S7) -> 0.66292035 | T9: =+T6/T7 -> 0.66292035 | U9: 0.79 | V9: =T9/U9-1 -> -0.16086031 | W9: =IFERROR(S9/R9-1,100%) -> -0.029156224 | X9: =+X6/X7 -> 0.64510391 | Y9: =+T9/X9-1 -> 0.027617944
A10: Productivity (p/h) | B10: =IFERROR(B5/(B7/60),0) -> 0.89255057 | C10: =IFERROR(C5/(C7/60),0) -> 0.83595701 | D10: =IFERROR(D5/(D7/60),0) -> 0.75017112 | E10: =IFERROR(E5/(E7/60),0) -> 1.0353535 | F10: =IFERROR(F5/(F7/60),0) -> 0.97815998 | G10: =IFERROR(G5/(G7/60),0) -> 0.87664671 | H10: =IFERROR(H5/(H7/60),0) -> 1.0982456 | I10: =IFERROR(I5/(I7/60),0) -> 1.5888502 | ... T10: =IFERROR(T5/(T7/60),0) -> 0.85858595 | U10: 1.05 | V10: =T10/U10-1 -> -0.18229909 | W10: =IFERROR(S10/R10-1,100%) -> -0.49993089 | X10: =+X5/(X7/60) -> 0.88966442 | Y10: =+T10/X10-1 -> -0.034932795
A12: LEATHER | B12: 45688 | C12: 45716 | D12: 45747 | E12: 45777 | F12: 45808 | G12: 45838 | H12: 45869 | I12: 45900 | J12: 45930 | K12: 45961 | L12: 45991 | M12: 46022 | N12: 46053 | O12: 46081 | P12: 46112 | Q12: 46142 | R12: 46173 | S12: 46203 | T12: YTD | U12: TARGET | V12: % Var. vs trgt | W12: MoM % | X12: PYTD | Y12: YoY% | Z12: WIP FG | AA12: coda 2025 su 2026
A13: Production Volume FG | B13: 2331 | C13: 1625 | D13: 1493 | E13: 1285 | F13: 1532 | G13: 1764 | H13: 1715 | I13: 339 | J13: 1901 | K13: 1913 | L13: 1455 | M13: 1098 | N13: 1375 | O13: 1193 | P13: 1131 | Q13: 1273 | R13: 1380 | S13: 1510 | T13: =SUM(N13:S13) -> 7862 | W13: =IFERROR(S13/R13-1,100%) -> 0.094202899 | X13: =SUM(B13:G13) -> 10030 | Y13: =+T13/X13-1 -> -0.21615155 | Z13: =+T13+AA13-Delivery!U41 -> 141 | AA13: 605
A14: Std minutes produced | B14: 769873.22 | C14: 630240.11 | D14: 484938.8 | E14: 440865.74 | F14: 558572.5 | G14: 589885.72 | H14: 667067.34 | I14: 136692.47 | J14: 631411.39 | K14: 690790.96 | L14: 497397.76 | M14: 433900 | N14: 435609.9 | O14: 432189.38 | P14: 393442.09 | Q14: 515577.83 | R14: 479471.31 | S14: 580505.27 | T14: =SUM(N14:S14) -> 2836795.8 | W14: =IFERROR(S14/R14-1,100%) -> 0.21071951 | X14: =SUM(B14:G14) -> 3474376.1 | Y14: =+T14/X14-1 -> -0.1835093
A15: Worked minutes | B15: 955230 | C15: 853590 | D15: 604860 | E15: 583140 | F15: 744690 | G15: 726420 | H15: 910500 | I15: 169920 | J15: 841230 | K15: 950010 | L15: 805470 | M15: 776310 | N15: 758100 | O15: 721180 | P15: 602550 | Q15: 820350 | R15: 709140 | S15: 869880 | T15: =SUM(N15:S15) -> 4481200 | W15: =IFERROR(S15/R15-1,100%) -> 0.22666892 | X15: =SUM(B15:G15) -> 4467930 | Y15: =+T15/X15-1 -> 0.0029700555
A16: Efficiency (mth) | B16: =IFERROR(B14/B15,"") -> 0.80595586 | C16: =IFERROR(C14/C15,"") -> 0.73834055 | D16: =IFERROR(D14/D15,"") -> 0.80173726 | E16: =IFERROR(E14/E15,"") -> 0.75602041 | F16: =IFERROR(F14/F15,"") -> 0.75007386 | G16: =IFERROR(G14/G15,"") -> 0.81204499 | H16: =IFERROR(H14/H15,"") -> 0.73263848 | I16: =IFERROR(I14/I15,"") -> 0.80445192 | ... S16: =IFERROR(S14/S15,"") -> 0.66733948 | W16: =IFERROR(S16/R16-1,100%) -> -0.013002214
A17: Efficiency (ytd) | B17: =SUM($B14:B14)/SUM($B15:B15) -> 0.80595586 | C17: =SUM($B14:C14)/SUM($B15:C15) -> 0.7740479 | D17: =SUM($B14:D14)/SUM($B15:D15) -> 0.78098676 | E17: =SUM($B14:E14)/SUM($B15:E15) -> 0.77612865 | F17: =SUM($B14:F14)/SUM($B15:F15) -> 0.77094285 | G17: =SUM($B14:G14)/SUM($B15:G15) -> 0.77762545 | H17: =SUM($B14:H14)/SUM($B15:H15) -> 0.77000973 | I17: =SUM($B14:I14)/SUM($B15:I15) -> 0.77106453 | ... M17: =SUM($B14:M14)/SUM($B15:M15) -> 0.73213374 | N17: =SUM(N14:$N14)/SUM(N15:$N15) -> 0.57460744 | O17: =SUM($N14:O14)/SUM($N15:O15) -> 0.58663626 | P17: =SUM($N14:P14)/SUM($N15:P15) -> 0.60583303 | Q17: =SUM($N14:Q14)/SUM($N15:Q15) -> 0.61223604 | R17: =SUM($N14:R14)/SUM($N15:R15) -> 0.62478277 | S17: =SUM($N14:S14)/SUM($N15:S15) -> 0.63304378 | T17: =+T14/T15 -> 0.63304378 | U17: 0.77 | V17: =T17/U17-1 -> -0.17786522 | W17: =IFERROR(S17/R17-1,100%) -> 0.01322221 | X17: =+X14/X15 -> 0.77762545 | Y17: =+T17/X17-1 -> -0.18592714
A18: Productivity (p/h) | B18: =IFERROR(B13/(B15/60),0) -> 0.146415 | C18: =IFERROR(C13/(C15/60),0) -> 0.11422346 | D18: =IFERROR(D13/(D15/60),0) -> 0.14810039 | E18: =IFERROR(E13/(E15/60),0) -> 0.13221525 | F18: =IFERROR(F13/(F15/60),0) -> 0.12343391 | G18: =IFERROR(G13/(G15/60),0) -> 0.14570083 | H18: =IFERROR(H13/(H15/60),0) -> 0.11301483 | I18: =IFERROR(I13/(I15/60),0) -> 0.11970339 | ... T18: =IFERROR(T13/(T15/60),0) -> 0.10526645 | U18: 0.12 | V18: =T18/U18-1 -> -0.12277961 | W18: =IFERROR(S18/R18-1,100%) -> -0.10798841 | X18: =+X13/(X15/60) -> 0.13469325 | Y18: =+T18/X18-1 -> -0.21847272
A20: D|AIR | B20: 45688 | C20: 45716 | D20: 45747 | E20: 45777 | F20: 45808 | G20: 45838 | H20: 45869 | I20: 45900 | J20: 45930 | K20: 45961 | L20: 45991 | M20: 46022 | N20: 46053 | O20: 46081 | P20: 46112 | Q20: 46142 | R20: 46173 | S20: 46203 | T20: YTD | U20: TARGET | V20: % Var. vs trgt | W20: MoM % | X20: PYTD | Y20: YoY% | Z20: WIP FG | AA20: coda 2025 su 2026
A21: Production Volume FG | B21: 2966 | C21: 1856 | D21: 1295 | E21: 1197 | F21: 1391 | G21: 870 | H21: 1229 | I21: 721 | J21: 1127 | K21: 2278 | L21: 1795 | M21: 1067 | N21: 1143 | O21: 1235 | P21: 658 | Q21: 1463 | R21: 998 | S21: 1019 | T21: =SUM(N21:S21) -> 6516 | W21: =IFERROR(S21/R21-1,100%) -> 0.021042084 | X21: =SUM(B21:G21) -> 9575 | Y21: =+T21/X21-1 -> -0.31947781 | Z21: =+T21+AA21-Delivery!U42 -> 426 | AA21: 325
A22: Std minutes produced | B22: 74949.19 | C22: 64117.71 | D22: 36342.15 | E22: 36034.99 | F22: 41466.45 | G22: 36754.32 | H22: 25191.3 | I22: 9535.18 | J22: 44162.4 | K22: 55662.29 | L22: 45258.1 | M22: 39423.44 | N22: 22627.4 | O22: 29088.32 | P22: 28795.42 | Q22: 41224.57 | R22: 29638.59 | S22: 37055.01 | T22: =SUM(N22:S22) -> 188429.31 | W22: =IFERROR(S22/R22-1,100%) -> 0.2502285 | X22: =SUM(B22:G22) -> 289664.81 | Y22: =+T22/X22-1 -> -0.34949188
A23: Worked minutes | B23: 90150 | C23: 78780 | D23: 44010 | E23: 43170 | F23: 55020 | G23: 42360 | H23: 32010 | I23: 12930 | J23: 48810 | K23: 66120 | L23: 56370 | M23: 48690 | N23: 30000 | O23: 40410 | P23: 45690 | Q23: 53610 | R23: 38430 | S23: 50310 | T23: =SUM(N23:S23) -> 258450 | W23: =IFERROR(S23/R23-1,100%) -> 0.30913349 | X23: =SUM(B23:G23) -> 353490 | Y23: =+T23/X23-1 -> -0.26886192
A24: Efficiency (mth) | B24: =IFERROR(B22/B23,"") -> 0.83138314 | C24: =IFERROR(C22/C23,"") -> 0.81388309 | D24: =IFERROR(D22/D23,"") -> 0.82577028 | E24: =IFERROR(E22/E23,"") -> 0.83472296 | F24: =IFERROR(F22/F23,"") -> 0.7536614 | G24: =IFERROR(G22/G23,"") -> 0.86766572 | H24: =IFERROR(H22/H23,"") -> 0.78698219 | I24: =IFERROR(I22/I23,"") -> 0.73744625 | ... S24: =IFERROR(S22/S23,"") -> 0.73653369 | W24: =IFERROR(S24/R24-1,100%) -> -0.044995401
A25: Efficiency (ytd) | B25: =SUM($B22:B22)/SUM($B23:B23) -> 0.83138314 | C25: =SUM($B22:C22)/SUM($B23:C23) -> 0.82322204 | D25: =SUM($B22:D22)/SUM($B23:D23) -> 0.82374871 | E25: =SUM($B22:E22)/SUM($B23:E23) -> 0.82559853 | F25: =SUM($B22:F22)/SUM($B23:F23) -> 0.81287722 | G25: =SUM($B22:G22)/SUM($B23:G23) -> 0.81944273 | H25: =SUM($B22:H22)/SUM($B23:H23) -> 0.81674737 | I25: =SUM($B22:I22)/SUM($B23:I23) -> 0.81417386 | ... M25: =SUM($B22:M22)/SUM($B23:M23) -> 0.82289952 | N25: =SUM(N22:$N22)/SUM(N23:$N23) -> 0.75424667 | O25: =SUM($N22:O22)/SUM($N23:O23) -> 0.73449396 | P25: =SUM($N22:P22)/SUM($N23:P23) -> 0.69346374 | Q25: =SUM($N22:Q22)/SUM($N23:Q23) -> 0.71731607 | R25: =SUM($N22:R22)/SUM($N23:R23) -> 0.72727155 | S25: =SUM($N22:S22)/SUM($N23:S23) -> 0.72907452 | T25: =+T22/T23 -> 0.72907452 | U25: 0.8 | V25: =T25/U25-1 -> -0.088656849 | W25: =IFERROR(S25/R25-1,100%) -> 0.0024790922 | X25: =+X22/X23 -> 0.81944273 | Y25: =+T25/X25-1 -> -0.11028008
A26: Productivity (p/h) | B26: =IFERROR(B21/(B23/60),0) -> 1.9740433 | C26: =IFERROR(C21/(C23/60),0) -> 1.4135567 | D26: =IFERROR(D21/(D23/60),0) -> 1.7655078 | E26: =IFERROR(E21/(E23/60),0) -> 1.6636553 | F26: =IFERROR(F21/(F23/60),0) -> 1.5169029 | G26: =IFERROR(G21/(G23/60),0) -> 1.2322946 | H26: =IFERROR(H21/(H23/60),0) -> 2.3036551 | I26: =IFERROR(I21/(I23/60),0) -> 3.3457077 | ... T26: =IFERROR(T21/(T23/60),0) -> 1.5127104 | U26: 2.47 | V26: =T26/U26-1 -> -0.38756664 | W26: =IFERROR(S26/R26-1,100%) -> -0.22006267 | X26: =+X21/(X23/60) -> 1.6252228 | Y26: =+T26/X26-1 -> -0.069228903
A28: MEL-T | B28: 45688 | C28: 45716 | D28: 45747 | E28: 45777 | F28: 45808 | G28: 45838 | H28: 45869 | I28: 45900 | J28: 45930 | K28: 45961 | L28: 45991 | M28: 46022 | N28: 46053 | O28: 46081 | P28: 46112 | Q28: 46142 | R28: 46173 | S28: 46203 | T28: YTD | U28: TARGET | V28: +/- Vs trgt | W28: MoM % | X28: PYTD | Y28: YoY% | Z28: WIP FG | AA28: coda 2025 su 2026
A29: Production Volume FG | B29: =SUM(B5,B13,B21) -> 9820 | C29: =SUM(C5,C13,C21) -> 7331 | D29: =SUM(D5,D13,D21) -> 5528 | E29: =SUM(E5,E13,E21) -> 5762 | F29: =SUM(F5,F13,F21) -> 6506 | G29: =SUM(G5,G13,G21) -> 5562 | H29: =SUM(H5,H13,H21) -> 7326 | I29: =SUM(I5,I13,I21) -> 2200 | ... S29: =SUM(S5,S13,S21) -> 4029 | T29: =SUM(N29:S29) -> 29677 | W29: =IFERROR(S29/R29-1,100%) -> -0.17942974 | X29: =SUM(B29:G29) -> 40509 | Y29: =+T29/X29-1 -> -0.26739737 | Z29: =+T29+AA29-Delivery!U43 -> 585 | AA29: =SUM(AA21,AA13,AA5) -> 2467
A30: Std minutes produced | B30: =SUM(B6,B14,B22) -> 1046968.9 | C30: =SUM(C6,C14,C22) -> 864807.43 | D30: =SUM(D6,D14,D22) -> 658258.85 | E30: =SUM(E6,E14,E22) -> 589697.13 | F30: =SUM(F6,F14,F22) -> 753528.34 | G30: =SUM(G6,G14,G22) -> 760241.29 | H30: =SUM(H6,H14,H22) -> 863899.22 | I30: =SUM(I6,I14,I22) -> 171686.89 | ... S30: =SUM(S6,S14,S22) -> 718488.02 | T30: =SUM(N30:S30) -> 3733973.1 | W30: =IFERROR(S30/R30-1,100%) -> 0.17048916 | X30: =SUM(B30:G30) -> 4673501.9 | Y30: =+T30/X30-1 -> -0.20103315
A31: Worked minutes | B31: =SUM(B7,B15,B23) -> 1349430 | C31: =SUM(C7,C15,C23) -> 1208700 | D31: =SUM(D7,D15,D23) -> 868020 | E31: =SUM(E7,E15,E23) -> 816390 | F31: =SUM(F7,F15,F23) -> 1019490 | G31: =SUM(G7,G15,G23) -> 969180 | H31: =SUM(H7,H15,H23) -> 1181910 | I31: =SUM(I7,I15,I23) -> 225900 | ... S31: =SUM(S7,S15,S23) -> 1099170 | T31: =SUM(N31:S31) -> 5808780 | W31: =IFERROR(S31/R31-1,100%) -> 0.2231347 | X31: =SUM(B31:G31) -> 6231210 | Y31: =+T31/X31-1 -> -0.067792612
A32: Efficiency (mth) | B32: =IFERROR(B30/B31,"") -> 0.7758601 | C32: =IFERROR(C30/C31,"") -> 0.71548559 | D32: =IFERROR(D30/D31,"") -> 0.75834526 | E32: =IFERROR(E30/E31,"") -> 0.72232282 | F32: =IFERROR(F30/F31,"") -> 0.73912284 | G32: =IFERROR(G30/G31,"") -> 0.78441702 | H32: =IFERROR(H30/H31,"") -> 0.73093486 | I32: =IFERROR(I30/I31,"") -> 0.76001279 | ... S32: =IFERROR(S30/S31,"") -> 0.65366415 | W32: =IFERROR(S32/R32-1,100%) -> -0.043041493
A33: Efficiency (ytd) | B33: =SUM($B30:B30)/SUM($B31:B31) -> 0.7758601 | C33: =SUM($B30:C30)/SUM($B31:C31) -> 0.74733353 | D33: =SUM($B30:D30)/SUM($B31:D31) -> 0.75012337 | E33: =SUM($B30:E30)/SUM($B31:E31) -> 0.74477372 | F33: =SUM($B30:F30)/SUM($B31:F31) -> 0.74367889 | G33: =SUM($B30:G30)/SUM($B31:G31) -> 0.75001516 | H33: =SUM($B30:H30)/SUM($B31:H31) -> 0.74697309 | I33: =SUM($B30:I30)/SUM($B31:I31) -> 0.7473587 | ... M33: =SUM($B30:M30)/SUM($B31:M31) -> 0.72295813 | N33: =SUM(N30:$N30)/SUM(N31:$N31) -> 0.60283523 | O33: =SUM($N30:O30)/SUM($N31:O31) -> 0.60867595 | P33: =SUM($N30:P30)/SUM($N31:P31) -> 0.62180364 | Q33: =SUM($N30:Q30)/SUM($N31:Q31) -> 0.63019539 | R33: =SUM($N30:R30)/SUM($N31:R31) -> 0.6402834 | S33: =SUM($N30:S30)/SUM($N31:S31) -> 0.64281538 | T33: =+T30/T31 -> 0.64281538 | U33: 0.77 | V33: =T33/U33-1 -> -0.16517483 | W33: =IFERROR(S33/R33-1,100%) -> 0.0039544676 | X33: =+X30/X31 -> 0.75001516 | Y33: =+T33/X33-1 -> -0.14293015
A34: Productivity (p/h) | B34: =IFERROR(B29/(B31/60),0) -> 0.4366288 | C34: =IFERROR(C29/(C31/60),0) -> 0.36391164 | D34: =IFERROR(D29/(D31/60),0) -> 0.38211101 | E34: =IFERROR(E29/(E31/60),0) -> 0.42347407 | F34: =IFERROR(F29/(F31/60),0) -> 0.38289733 | G34: =IFERROR(G29/(G31/60),0) -> 0.34433232 | H34: =IFERROR(H29/(H31/60),0) -> 0.37190649 | I34: =IFERROR(I29/(I31/60),0) -> 0.58432935 | ... T34: =IFERROR(T29/(T31/60),0) -> 0.30653941 | U34: 0.52 | V34: =T34/U34-1 -> -0.41050113 | W34: =IFERROR(S34/R34-1,100%) -> -0.32912519 | X34: =+X29/(X31/60) -> 0.39005907 | Y34: =+T34/X34-1 -> -0.21412055
A35: Source: "Production report.xlsx"
A36: * Standard minutes produced = (Finished goods + Semi‑finished goods)
A37: ** Minutes worked and produced for FQC&PACK, OUTSOURCING are excluded from the calculation
A38: *** (minutes x1000)

Sheet Costs & Profitability
B1: Costs & Profitability
B2: Scrap Material Value (€) (Material Waste during Manufacturing)
B3: Total euro value of raw materials scrapped during the manufacturing process
B4: BU | C4: 45838 | D4: 45869 | E4: 45900 | F4: 45930 | G4: 45961 | H4: 45991 | I4: 46022 | J4: 46053 | K4: 46081 | L4: 46112 | M4: 46142 | N4: 46173 | O4: 46203 | P4: YTD | Q4: TARGET | R4: +/- Vs trgt | S4: % Var. | T4: FY'25 | U4: % Var. Vs FY'25 | V4: €/unit of RM
B5: Safety | C5: 483 | D5: 404 | E5: 2 | F5: 95 | G5: 1 | H5: 82 | I5: 65 | J5: 0 | K5: 616 | L5: 256 | M5: 7 | N5: 0 | O5: 96 | P5: =SUM(J5:O5) -> 975 | Q5: =Efficiency!T5*V5*0.1% -> 568.35785 | R5: =P5-Q5 -> 406.64215 | S5: =+P5/Q5-1 -> 0.71546852 | T5: 2793 | U5: =IFERROR(P5/T5-1,100%) -> -0.650913 | V5: 37.15
B6: Leather | C6: 0 | D6: 303 | E6: 0 | F6: 121 | G6: 129 | H6: 154 | I6: 93 | J6: 0 | K6: 138 | L6: 143 | M6: 667 | N6: 203 | O6: 79 | P6: =SUM(J6:O6) -> 1230 | Q6: =Efficiency!T13*V6*0.1% -> 669.68516 | R6: =P6-Q6 -> 560.31484 | S6: =+P6/Q6-1 -> 0.83668397 | T6: 1401.3 | U6: =IFERROR(P6/T6-1,100%) -> -0.12224363 | V6: 85.18
B7: D|air | C7: 0.11 | D7: 26 | E7: 0 | F7: 0 | G7: 32 | H7: 0 | I7: 0 | J7: 0 | K7: 0 | L7: 0 | M7: 0 | N7: 0 | O7: 12 | P7: =SUM(J7:O7) -> 12 | Q7: =Efficiency!T21*V7*0.1% -> 413.04924 | R7: =P7-Q7 -> -401.04924 | S7: =+P7/Q7-1 -> -0.97094777 | T7: 321.11 | U7: =IFERROR(P7/T7-1,100%) -> -0.96262963 | V7: 63.39
B8: MEL-T | C8: =SUM(C5:C7) -> 483.11 | D8: =SUM(D5:D7) -> 733 | E8: =SUM(E5:E7) -> 2 | F8: =SUM(F5:F7) -> 216 | G8: =SUM(G5:G7) -> 162 | H8: =SUM(H5:H7) -> 236 | I8: =SUM(I5:I7) -> 158 | J8: =SUM(J5:J7) -> 0 | ... Q8: =SUM(Q5:Q7) -> 1651.0922 | R8: =P8-Q8 -> 565.90775 | S8: =+P8/Q8-1 -> 0.34274751 | T8: 4515.41 | U8: =IFERROR(P8/T8-1,100%) -> -0.50901469 | V8: =SUM(V5:V7) -> 185.72
B12: Maintenance Cost (DT/h)
B13: (Maintenance labor cost + Spare parts cost) / Equipment running hours
B14: BU | C14: 45838 | D14: 45869 | E14: 45900 | F14: 45930 | G14: 45961 | H14: 45991 | I14: 46022 | J14: 46053 | K14: 46081 | L14: 46112 | M14: 46142 | N14: 46173 | O14: 46203 | P14: YTD | Q14: BDG | R14: +/- Vs bdg | S14: % Var. | T14: FY'25 | U14: % Var. Vs FY'25 | W14: BDG
B15: Labor cost | C15: 0 | D15: 0 | E15: 0 | F15: 0 | G15: 0 | H15: 0 | I15: 0 | J15: 0 | K15: 0 | L15: 0 | P15: =SUM(K15:O15) -> 0 | Q15: =+W15/12*6 -> 0 | R15: =P15-Q15 -> 0 | S15: =IFERROR(P15/Q15-1,0) -> 0 | T15: 0 | U15: =IFERROR(P15/T15-1,100%) -> 1 | W15: 0
B16: Other external labor cost | C16: =SUM(C35:C37) -> 7963.545 | D16: =SUM(D35:D37) -> 8200.494 | E16: =SUM(E35:E37) -> 8200.494 | F16: =SUM(F35:F37) -> 8143.545 | G16: =SUM(G35:G37) -> 8380.494 | H16: =SUM(H35:H37) -> 8922.712 | I16: =SUM(I35:I37) -> 8536.332 | J16: =SUM(J35:J37) -> 8465.211 | ... O16: =SUM(O35:O37) -> 0 | P16: =SUM(K16:O16) -> 34492.775 | Q16: =+W16/12*6 -> 52842.075 | R16: =P16-Q16 -> -18349.3 | S16: =IFERROR(P16/Q16-1,0) -> -0.34724791 | T16: 97904.646 | U16: =IFERROR(P16/T16-1,100%) -> -0.64769011 | W16: =SUM(W35:W37)*1 -> 105684.15
B17: Parts cost | C17: =SUM(C27:C34) -> 4485.641 | D17: =SUM(D27:D34) -> 1663.297 | E17: =SUM(E27:E34) -> 1299.743 | F17: =SUM(F27:F34) -> 1415.94 | G17: =SUM(G27:G34) -> 10529.315 | H17: =SUM(H27:H34) -> 6933.266 | I17: =SUM(I27:I34) -> 7019.723 | J17: =SUM(J27:J34) -> 1104.178 | ... O17: =SUM(O27:O34) -> 0 | P17: =SUM(K17:O17) -> 50923.652 | Q17: =+W17/12*6 -> 49821.755 | R17: =P17-Q17 -> 1101.8973 | S17: =IFERROR(P17/Q17-1,0) -> 0.022116789 | T17: 87702.404 | U17: =IFERROR(P17/T17-1,100%) -> -0.41935854 | W17: =SUM(W27:W34)*1 -> 99643.509
B18: Total cost (TND) (BCR) | C18: =SUM(C15:C17) -> 12449.186 | D18: =SUM(D15:D17) -> 9863.791 | E18: =SUM(E15:E17) -> 9500.237 | F18: =SUM(F15:F17) -> 9559.485 | G18: =SUM(G15:G17) -> 18909.809 | H18: =SUM(H15:H17) -> 15855.978 | I18: =SUM(I15:I17) -> 15556.055 | J18: =SUM(J15:J17) -> 9569.389 | ... Q18: =SUM(Q15:Q17) -> 102663.83 | R18: =P18-Q18 -> -17247.403 | S18: =IFERROR(P18/Q18-1,0) -> -0.16799882 | T18: 185607.05 | U18: =IFERROR(P18/T18-1,100%) -> -0.53979966 | W18: =SUM(W15:W17) -> 205327.66 | X18: =+P18/W18 -> 0.41600059
B20: Total direct labour hours worked | C20: 17104.5 | D20: 20753.5 | E20: 3709 | F20: 18966.5 | G20: 21665 | H20: 18669.5 | I20: 17851.5 | J20: 17164 | K20: 16630.5 | L20: 14580.5 | M20: 18571 | N20: 15397.5 | O20: 18636 | P20: =SUM(K20:O20) -> 83815.5 | Q20: =+W20/12*6 -> 149242.5 | R20: =P20-Q20 -> -65427 | S20: =IFERROR(P20/Q20-1,0) -> -0.43839389 | T20: 211765.5 | U20: =IFERROR(P20/T20-1,100%) -> -0.60420607 | W20: =134*2227.5 -> 298485
B21: Overall hours worked | C21: 23499 | D21: 28454.5 | E21: 6795.5 | F21: 26482.5 | G21: 29792.5 | H21: 25918 | I21: 24704 | J21: 23953.5 | K21: 23561.5 | L21: 21122 | M21: 26566 | N21: 22453 | O21: 27143 | P21: =SUM(K21:O21) -> 120845.5 | Q21: =+W21/12*6 -> 198247.5 | R21: =P21-Q21 -> -77402 | S21: =IFERROR(P21/Q21-1,0) -> -0.39043115 | T21: 287544 | U21: =IFERROR(P21/T21-1,100%) -> -0.57973215 | W21: =178*2227.5 -> 396495
B22: Hrs running par 1.0FTE | C22: 169 | D22: 202 | E22: 58.5 | F22: 191.5 | G22: 210.5 | H22: 185 | I22: 202 | J22: 201 | K22: 178 | L22: 164.5 | M22: 202 | N22: 166 | O22: 193.5 | P22: =SUM(K22:O22) -> 904 | Q22: =+W22/12*6 -> 1129.75 | R22: =P22-Q22 -> -225.75 | S22: =IFERROR(P22/Q22-1,0) -> -0.19982297 | T22: 2170 | U22: =IFERROR(P22/T22-1,100%) -> -0.58341014 | W22: 2259.5
B23: Maintenance Cost/h DL | C23: =+C18/C20 -> 0.72783104 | D23: =+D18/D20 -> 0.47528325 | E23: =+E18/E20 -> 2.5614012 | F23: =+F18/F20 -> 0.50401946 | G23: =+G18/G20 -> 0.87282756 | H23: =+H18/H20 -> 0.84929848 | I23: =+I18/I20 -> 0.87141445 | J23: =+J18/J20 -> 0.55752674 | ... Q23: =+Q18/Q20 -> 0.68789942 | R23: =P23-Q23 -> 0.33120118 | S23: =IFERROR(P23/Q23-1,0) -> 0.48146745 | T23: 0.87647445 | U23: =IFERROR(P23/T23-1,100%) -> 0.16272712 | W23: =+W18/W20 -> 0.68789942
B24: Maintenance Cost/h overall | C24: =+C18/C21 -> 0.52977514 | D24: =+D18/D21 -> 0.34665136 | E24: =+E18/E21 -> 1.3980188 | F24: =+F18/F21 -> 0.36097366 | G24: =+G18/G21 -> 0.63471709 | H24: =+H18/H21 -> 0.61177475 | I24: =+I18/I21 -> 0.62969782 | J24: =+J18/J21 -> 0.39949857 | ... Q24: =+Q18/Q21 -> 0.51785687 | R24: =P24-Q24 -> 0.18896653 | S24: =IFERROR(P24/Q24-1,0) -> 0.36490108 | T24: 0.64549095 | U24: =IFERROR(P24/T24-1,100%) -> 0.095016743 | W24: =+W18/W21 -> 0.51785687
B25: Maintenance Cost/h (MCH) | C25: =+C18/C22 -> 73.663822 | D25: =+D18/D22 -> 48.830649 | E25: =+E18/E22 -> 162.39721 | F25: =+F18/F22 -> 49.918982 | G25: =+G18/G22 -> 89.832822 | H25: =+H18/H22 -> 85.707989 | I25: =+I18/I22 -> 77.010173 | J25: =+J18/J22 -> 47.6089 | ... Q25: =+Q18/Q22 -> 90.873051 | R25: =P25-Q25 -> 3.6141467 | S25: =IFERROR(P25/Q25-1,0) -> 0.03977138 | T25: 85.533203 | U25: =IFERROR(P25/T25-1,100%) -> 0.10468444 | W25: =+W18/W22 -> 90.873051
A27: 6152000000 | B27: ENTRETIEN ET REPARATION MATER | C27: 0 | D27: 634.017 | E27: 675.6 | F27: 178.122 | G27: 24 | H27: 1811 | I27: 250 | J27: 555.504 | K27: 461.557 | L27: 6980.711 | M27: 4673.418 | N27: 2829.442 | T27: 48804.986 | W27: 57426.584
A28: 6152000001 | B28: ENTRETIEN ET REPARATION MATER. SAFETY | C28: 0 | D28: 0 | E28: 25 | F28: 250.592 | G28: 0 | H28: 165.5 | I28: 220.58 | J28: 0 | K28: 903.5 | L28: 0 | M28: 131.81 | N28: 0 | T28: 2324.748 | W28: 5704.1615
A29: 6152000004 | B29: ENTRETIEN ET REPARATION MAT.LEATHER | C29: 3749.37 | D29: 413 | E29: 0 | F29: 64.199 | G29: 8456.288 | H29: 80.687 | I29: 0 | J29: 98.341 | K29: 6883.85 | L29: 100 | M29: 11080.529 | N29: 125.431 | T29: 16848.627 | W29: 21149.958
A30: 6152000005 | B30: ENTRETIEN ET REPARATION MAT.LECTRA | C30: 0 | D30: 0 | E30: 0 | F30: 0 | G30: 748.884 | H30: 0 | I30: 0 | J30: 0 | K30: 745.83 | L30: 0 | M30: 0 | N30: 0 | T30: 1589.398 | W30: 2010.2937
A31: 6152000006 | B31: ENTRETIEN ET REPARATION MAT.D-AIR | C31: 0 | D31: 17.137 | E31: 0 | F31: 256 | G31: 0 | H31: 4075.5 | I31: 20.001 | J31: 0 | K31: 838.5 | L31: 13224.776 | M31: 0 | N31: 0 | T31: 5628.308 | W31: 2463.3921
A32: 6151000001 | B32: ENTRETIEN USINE ENFIDHA | C32: 607.271 | D32: 478.143 | E32: 478.143 | F32: 546.027 | G32: 1179.143 | H32: 601.169 | I32: 6408.142 | J32: 329.333 | K32: 329.333 | L32: 329.333 | M32: 472.299 | N32: 329.333 | T32: 10957.917 | W32: 8846.4093
A33: 6151000004 | B33: ENTRETIEN USINE LEATHER | C33: 0 | D33: 0 | E33: 0 | F33: 0 | G33: 0 | H33: 0 | I33: 0 | J33: 0 | K33: 0 | L33: 0 | M33: 0 | N33: 0 | T33: 10.01 | W33: 176.011
A34: 6151000005 | B34: ENTRETIEN USINE D-AIR | C34: 129 | D34: 121 | E34: 121 | F34: 121 | G34: 121 | H34: 199.41 | I34: 121 | J34: 121 | K34: 121 | L34: 121 | M34: 121 | N34: 121 | T34: 1538.41 | W34: 1866.7
A35: 6155000001 | B35: MAINTENANCE | C35: 583 | D35: 583 | E35: 583 | F35: 763 | G35: 763 | H35: 1542.167 | I35: 918.833 | J35: 836.845 | K35: 836.845 | L35: 836.845 | M35: 836.845 | N35: 836.845 | T35: 8651 | W35: 9124.15
A36: 6156000000 | B36: MAINTENANCE LECTRA MATERIEL | C36: 272.057 | D36: 272.057 | E36: 272.057 | F36: 272.057 | G36: 272.057 | H36: 272.057 | I36: 272.062 | J36: 282.929 | K36: 282.929 | L36: 282.929 | M36: 282.929 | N36: 282.929 | T36: 3264.689 | W36: 3553
A37: 6156000004 | B37: MAINTENANCE LECTRA MATERIEL LEATHER | C37: 7108.488 | D37: 7345.437 | E37: 7345.437 | F37: 7108.488 | G37: 7345.437 | H37: 7108.488 | I37: 7345.437 | J37: 7345.437 | K37: 5212.891 | L37: 8767.135 | M37: 8188.506 | N37: 7845.147 | T37: 85988.957 | W37: 93007

Sheet Warehouse & Inventory Managemen
A1: Warehouse & Inventory Management
A2: Reliability of deliveries (POM)
A3: (Error‑free orders / Total orders) × 100
A4: BU | B4: 45838 | C4: 45869 | D4: 45900 | E4: 45930 | F4: 45961 | G4: 45991 | H4: 46022 | I4: 46053 | J4: 46081 | K4: 46112 | L4: 46142 | M4: 46173 | N4: 46203 | O4: YTD | P4: TARGET | Q4: +/- Vs trgt | R4: FY'25 | S4: % Var. Vs FY'25
A5: Commun | B5: 1 | C5: 1 | D5: 1 | E5: 1 | F5: 1 | G5: 1 | H5: 1 | I5: 1 | J5: 1 | K5: 1 | L5: 1 | M5: 1 | N5: 1 | O5: 1 | P5: 0.98 | Q5: =O5-P5 -> 0.02 | R5: 1 | S5: =+O5/R5-1 -> 0
A6: Safety | B6: 1 | C6: 1 | D6: 1 | E6: 1 | F6: 1 | G6: 1 | H6: 1 | I6: 1 | J6: 1 | K6: 1 | L6: 0.92857143 | M6: 1 | N6: 0.91666667 | O6: 0.97402597 | P6: 0.98 | Q6: =O6-P6 -> -0.005974026 | R6: 1 | S6: =+O6/R6-1 -> -0.025974026
A7: Leather | B7: 1 | C7: 1 | D7: 1 | E7: 1 | F7: 1 | G7: 1 | H7: 1 | I7: 1 | J7: 1 | K7: 1 | L7: 1 | M7: 1 | N7: 0.98333333 | O7: 0.99537037 | P7: 0.98 | Q7: =O7-P7 -> 0.01537037 | R7: 1 | S7: =+O7/R7-1 -> -0.0046296296
A8: D|air | B8: 1 | C8: 1 | D8: 1 | E8: 1 | F8: 1 | G8: 1 | H8: 1 | I8: 1 | J8: 1 | K8: 1 | L8: 1 | M8: 1 | N8: 1 | O8: 1 | P8: 0.98 | Q8: =O8-P8 -> 0.02 | R8: 1 | S8: =+O8/R8-1 -> 0
A9: MEL-T | B9: 1 | C9: 1 | D9: 1 | E9: 1 | F9: 1 | G9: 1 | H9: 1 | I9: 1 | J9: 1 | K9: 1 | L9: 0.98795181 | M9: 1 | N9: 0.984375 | O9: 0.99446494 | P9: 0.98 | Q9: =O9-P9 -> 0.014464945 | R9: 1 | S9: =+O9/R9-1 -> -0.0055350554
A10: * The percentage of orders that are error-free.
A11: Source: "POM_Tracking.xlsx"
A14: Inventory Accuracy Rate (in %)
A15: (Correct counted units / Units on record) × 100
A16: BU | B16: 45838 | C16: 45869 | D16: 45900 | E16: 45930 | F16: 45961 | G16: 45991 | H16: 46022 | I16: 46053 | J16: 46081 | K16: 46112 | L16: 46142 | M16: 46173 | N16: 46203 | O16: YTD | P16: TARGET | Q16: +/- Vs trgt | R16: FY'25 | S16: % Var. Vs FY'25
A17: Correct Counted Units | B17: 0 | C17: 3 | D17: 0 | E17: 10 | F17: 0 | G17: 7 | H17: 9 | I17: 0 | J17: 4 | K17: 4 | L17: 2 | M17: 0 | N17: 0 | O17: =SUM(I17:N17) -> 10 | R17: 48
A18: Units on Record | B18: 0 | C18: 10 | D18: 0 | E18: 10 | F18: 0 | G18: 8 | H18: 9 | I18: 0 | J18: 10 | K18: 7 | L18: 6 | M18: 0 | N18: 0 | O18: =SUM(I18:N18) -> 23 | R18: 63 | S18: =O18/R18-1 -> -0.63492063
A19: Inventory Accuracy Rate | B19: =IFERROR(B17/B18,"") | C19: =IFERROR(C17/C18,"") -> 0.3 | D19: =IFERROR(D17/D18,"") | E19: =IFERROR(E17/E18,"") -> 1 | F19: =IFERROR(F17/F18,"") | G19: =IFERROR(G17/G18,"") -> 0.875 | H19: =IFERROR(H17/H18,"") -> 1 | I19: =IFERROR(I17/I18,"") | ... N19: =IFERROR(N17/N18,"") | O19: =IFERROR(O17/O18,0) -> 0.43478261 | P19: 0.97 | Q19: =O19-P19 -> -0.53521739 | R19: 0.76190476 | S19: =O19/R19-1 -> -0.42934783
A20: * The incorrect counted units are considered as varaition negative value and other specific conditions at the time of inventory and registration. | P20: and > PY
A21: ** Inventory accuracy is a metric that measures the difference between your records of warehouse stock and your real-life inventory.
A22: *** Average inventory accuracy for companies ranges from 75% to 97%. That includes companies that use SKUs and barcode scanning to manage inventory.
A23: Source: "Inventory_Tracking.xlsx"

Sheet Logistic
B1: N° container
B2: BU | C2: 45658 | D2: 45716 | E2: 45747 | F2: 45777 | G2: 45808 | H2: 45838 | I2: 45869 | J2: 45900 | K2: 45930 | L2: 45961 | M2: 45991 | N2: 46022 | O2: 46053 | P2: 46081 | Q2: 46112 | R2: 46142 | S2: 46173 | T2: 46203 | U2: YTD | V2: Media/mese | W2: TARGET | X2: +/- Vs trgt | Y2: % Var. | Z2: FY'25/mese | AA2: % Var. Vs FY'25
B3: Safety | C3: 1.1397059 | D3: 0.43382353 | E3: 1.0588235 | F3: 0.51470588 | G3: 0.77205882 | H3: 0.77205882 | I3: 1.3823529 | J3: 0 | K3: 1.1544118 | L3: 1 | M3: 1.1764706 | N3: 0.63970588 | O3: 1.4338235 | P3: 0.67415966 | Q3: 1.2867647 | R3: 1.0808824 | S3: 1.1323529 | T3: 1.6102941 | U3: =SUM(O3:T3) -> 7.2182773 | V3: =+U3/6 -> 1.2030462 | W3: =+Z3*0.7 -> 0.58590686 | X3: =V3-W3 -> 0.61713936 | Y3: =+V3/W3-1 -> 1.0533062 | Z3: 0.8370098 | AA3: =IFERROR(V3/Z3-1,100%) -> 0.43731437
B4: Leather | C4: 2.0588235 | D4: 1.4411765 | E4: 1.7058824 | F4: 0.86029412 | G4: 1.1985294 | H4: 1.1985294 | I4: 2.1985294 | J4: 0.33088235 | K4: 1.2069328 | L4: 1.9852941 | M4: 1.6544118 | N4: 0.88235294 | O4: 2.2352941 | P4: 1.4021008 | Q4: 1.5955882 | R4: 1.6404412 | S4: 1.2279412 | T4: 1.644958 | U4: =SUM(O4:T4) -> 9.7463235 | V4: =+U4/6 -> 1.6243873 | W4: =+V4*0.7 -> 1.1370711 | X4: =V4-W4 -> 0.48731618 | Y4: =+V4/W4-1 -> 0.42857143 | Z4: 1.3934699 | AA4: =IFERROR(V4/Z4-1,100%) -> 0.16571393
B5: D|air | C5: 1.5367647 | D5: 0.60294118 | E5: 1.9558824 | F5: 0.35294118 | G5: 0.44117647 | H5: 0.44117647 | I5: 0.86029412 | J5: 0.20588235 | K5: 1.0577731 | L5: 1.3382353 | M5: 0.76470588 | N5: 0.67647059 | O5: 0.72058824 | P5: 0.35430672 | Q5: 0.44117647 | R5: 0.7 | S5: 0.64705882 | T5: 0.83823529 | U5: =SUM(O5:T5) -> 3.7013655 | V5: =+U5/6 -> 0.61689426 | W5: =+V5*0.7 -> 0.43182598 | X5: =V5-W5 -> 0.18506828 | Y5: =+V5/W5-1 -> 0.42857143 | Z5: 0.85285364 | AA5: =IFERROR(V5/Z5-1,100%) -> -0.27667043
B6: Helmet
B7: MEL-T | C7: =SUM(C3:C6) -> 4.7352941 | D7: =SUM(D3:D6) -> 2.4779412 | E7: =SUM(E3:E6) -> 4.7205882 | F7: =SUM(F3:F6) -> 1.7279412 | G7: =SUM(G3:G6) -> 2.4117647 | H7: =SUM(H3:H6) -> 2.4117647 | I7: =SUM(I3:I6) -> 4.4411765 | J7: =SUM(J3:J6) -> 0.53676471 | ... P7: =SUM(P3:P6) -> 2.4305672 | Q7: 3.3235294 | R7: 3.4213235 | S7: =SUM(S3:S6) -> 3.0073529 | T7: =SUM(T3:T6) -> 4.0934874 | U7: =SUM(U3:U6) -> 20.665966 | V7: =SUM(V3:V6) -> 3.4443277 | W7: =SUM(W3:W6) -> 2.1548039 | X7: =V7-W7 -> 1.2895238 | Y7: =+V7/W7-1 -> 0.59844137 | Z7: =SUM(Z3:Z5) -> 3.0833333 | AA7: =IFERROR(V7/Z7-1,100%) -> 0.11707926
B11: Logistic Cost
C12: 45658 | D12: 45716 | E12: 45747 | F12: 45777 | G12: 45808 | H12: 45838 | I12: 45869 | J12: 45900 | K12: 45930 | L12: 45961 | M12: 45991 | N12: 46022 | O12: 46053 | P12: 46081 | Q12: 46112 | R12: 46142 | S12: 46173 | T12: 46203 | U12: YTD | V12: BDG | W12: +/- Vs bdg | X12: % Var. | Y12: FY'24 | Z12: % Var. Vs FY'25 | AC12: BDG
B13: Fees cost (TND) | C13: =SUM(C25:C30) -> 25000.395 | D13: =SUM(D25:D30) -> 20176.679 | E13: =SUM(E25:E30) -> 20468.867 | F13: =SUM(F25:F30) -> 8822.593 | G13: =SUM(G25:G30) -> 25880.73 | H13: =SUM(H25:H30) -> 10174.024 | I13: =SUM(I25:I30) -> 18027.173 | J13: =SUM(J25:J30) -> 15355.088 | ... P13: =SUM(P25:P30) -> 19561.466 | Q13: 17512.197 | R13: 23417.484 | S13: =SUM(S25:S30) -> 33780.842 | T13: =SUM(T25:T30) -> 30065.597 | U13: =SUM(O13:T13) -> 144293.88 | V13: =+AC13/12*6 -> 135097.37 | W13: =U13-V13 -> 9196.513 | X13: =IFERROR(U13/V13-1,0) -> 0.06807322 | Y13: =SUM(Y25:Y30) -> 226089.57 | Z13: =IFERROR(U13/Y13-1,100%) -> -0.36178443 | AC13: =SUM(AC25:AC30) -> 270194.74
B14: Transport Cost (TND) | C14: =SUM(C31:C36) -> 24455.52 | D14: =SUM(D31:D36) -> 23651.68 | E14: =SUM(E31:E36) -> 37225.419 | F14: =SUM(F31:F36) -> 13323.959 | G14: =SUM(G31:G36) -> 25616.639 | H14: =SUM(H31:H36) -> 19079.948 | I14: =SUM(I31:I36) -> 17626.558 | J14: =SUM(J31:J36) -> 11836.759 | ... P14: =SUM(P31:P36) -> 22640.6 | Q14: 17850.828 | R14: 20783.316 | S14: =SUM(S31:S36) -> 31192.404 | T14: =SUM(T31:T36) -> 28798.197 | U14: =SUM(O14:T14) -> 149036.58 | V14: =+AC14/12*6 -> 155265.74 | W14: =U14-V14 -> -6229.1609 | X14: =IFERROR(U14/V14-1,0) -> -0.040119352 | Y14: =SUM(Y31:Y36) -> 348323.99 | Z14: =IFERROR(U14/Y14-1,100%) -> -0.57213231 | AC14: =SUM(AC31:AC36) -> 310531.48
B15: Total cost (TND) | C15: =SUM(C13:C14) -> 49455.915 | D15: =SUM(D13:D14) -> 43828.359 | E15: =SUM(E13:E14) -> 57694.286 | F15: =SUM(F13:F14) -> 22146.552 | G15: =SUM(G13:G14) -> 51497.369 | H15: =SUM(H13:H14) -> 29253.972 | I15: =SUM(I13:I14) -> 35653.731 | J15: =SUM(J13:J14) -> 27191.847 | ... P15: =SUM(P13:P14) -> 42202.066 | Q15: 35363.025 | R15: 44200.8 | S15: =SUM(S13:S14) -> 64973.246 | T15: =SUM(T13:T14) -> 58863.794 | U15: =SUM(U13:U14) -> 293330.46 | V15: =SUM(V13:V14) -> 290363.11 | W15: =U15-V15 -> 2967.3522 | X15: =IFERROR(U15/V15-1,0) -> 0.010219453 | Y15: =SUM(Y13:Y14) -> 574413.56 | Z15: =IFERROR(U15/Y15-1,100%) -> -0.48933924 | AC15: =SUM(AC13:AC14) -> 580726.22
B17: Capi Spediti
B18: Safety | C18: 5638 | D18: 3715 | E18: 3194 | F18: 3425 | G18: 3102 | H18: 3170 | I18: 3939 | J18: 280 | K18: 3415 | L18: 3986 | M18: 5639 | N18: 2160 | O18: 4264 | P18: 2767 | Q18: 2252 | R18: 3232 | S18: 2300 | T18: 2300 | U18: =SUM(O18:T18) -> 17115 | V18: =+AC18/12*6 -> 32084.5 | W18: =U18-V18 -> -14969.5 | X18: =IFERROR(U18/V18-1,0) -> -0.46656485 | Y18: 229260 | Z18: =IFERROR(U18/Y18-1,100%) -> -0.92534677 | AC18: 64169
B19: Leather | C19: 3500 | D19: 1499 | E19: 1449 | F19: 1381 | G19: 1487 | H19: 1697 | I19: 1481 | J19: 0 | K19: 1459 | L19: 2643 | M19: 1798 | N19: 573 | O19: 1812 | P19: 1149 | Q19: 1162 | R19: 961 | S19: 1536 | T19: 1536 | U19: =SUM(O19:T19) -> 8156 | V19: =+AC19/12*6 -> 9301 | W19: =U19-V19 -> -1145 | X19: =IFERROR(U19/V19-1,0) -> -0.12310504 | Y19: 16554 | Z19: =IFERROR(U19/Y19-1,100%) -> -0.50730941 | AC19: 18602
B20: D|air | C20: 4358 | D20: 1723 | E20: 1283 | F20: 664 | G20: 1971 | H20: 904 | I20: 966 | J20: 620 | K20: 1420 | L20: 2182 | M20: 1950 | N20: 768 | O20: 1390 | P20: 816 | Q20: 877 | R20: 1076 | S20: 868 | T20: 868 | U20: =SUM(O20:T20) -> 5895 | V20: =+AC20/12*6 -> 10924.5 | W20: =U20-V20 -> -5029.5 | X20: =IFERROR(U20/V20-1,0) -> -0.4603872 | Y20: 28954 | Z20: =IFERROR(U20/Y20-1,100%) -> -0.79640119 | AC20: 21849
B21: Tot. Capi Spediti (PZ) | C21: =SUM(C18:C20) -> 13496 | D21: =SUM(D18:D20) -> 6937 | E21: =SUM(E18:E20) -> 5926 | F21: =SUM(F18:F20) -> 5470 | G21: =SUM(G18:G20) -> 6560 | H21: =SUM(H18:H20) -> 5771 | I21: =SUM(I18:I20) -> 6386 | J21: =SUM(J18:J20) -> 900 | ... P21: =SUM(P18:P20) -> 4732 | Q21: 4291 | R21: 5269 | S21: =SUM(S18:S20) -> 4704 | T21: =SUM(T18:T20) -> 4704 | U21: =SUM(U18:U20) -> 31166 | V21: =SUM(V18:V20) -> 52310 | W21: =U21-V21 -> -21144 | X21: =IFERROR(U21/V21-1,0) -> -0.4042057 | Y21: =SUM(Y18:Y20) -> 274768 | Z21: =IFERROR(U21/Y21-1,100%) -> -0.8865734 | AC21: =SUM(AC18:AC20) -> 104620
B23: Cost Unit (TND) | C23: =+C15/C21 -> 3.6644869 | D23: =+D15/D21 -> 6.3180567 | E23: =+E15/E21 -> 9.7357891 | F23: =+F15/F21 -> 4.0487298 | G23: =+G15/G21 -> 7.8502087 | H23: =+H15/H21 -> 5.0691339 | I23: =+I15/I21 -> 5.5831085 | J23: =+J15/J21 -> 30.213163 | ... P23: =+P15/P21 -> 8.9184417 | Q23: 8.2412083 | R23: 8.3888404 | S23: =+S15/S21 -> 13.81234 | T23: =+T15/T21 -> 12.513562 | U23: =+U15/U21 -> 9.4118739 | V23: =+V15/V21 -> 5.5508146 | W23: =U23-V23 -> 3.8610594 | X23: =IFERROR(U23/V23-1,0) -> 0.69558428 | Y23: =+Y15/Y21 -> 2.0905402 | Z23: =IFERROR(U23/Y23-1,100%) -> 3.5021252 | AC23: =+AC15/AC21 -> 5.5508146
A25: 6011000000 | B25: FRAIS SUR ACHAT SAFETY | C25: 3606.514 | D25: 2889.568 | E25: 3605.109 | F25: 1365.988 | G25: 4147.965 | H25: 3845.203 | I25: 4111.129 | J25: 1679.537 | K25: 6667.609 | L25: 4026.052 | M25: 4780.78 | N25: 3782.083 | O25: 6374.082 | P25: 3531.296 | Q25: 4615.36 | R25: 7704.76 | S25: 11359.164 | T25: 12783.107 | Y25: 25685.161 | AC25: 33007.878
A26: 6011000004 | B26: FRAIS SUR ACHAT LEATHER | C26: 3233.063 | D26: 5096.572 | E26: 2491.191 | F26: 3001.691 | G26: 5655.547 | H26: 5079.177 | I26: 4733.96 | J26: 4540.267 | K26: 3538.827 | L26: 4990.71 | M26: 5221.596 | N26: 3986.121 | O26: 5749.198 | P26: 2311.406 | Q26: 6232.962 | R26: 5498.158 | S26: 3906.646 | T26: 5572.839 | Y26: 80316.508 | AC26: 34875.192
A27: 6011000005 | B27: FRAIS SUR ACHAT D-AIR | C27: 4694.097 | D27: 1599.512 | E27: 947.75 | F27: 1241.02 | G27: 1018.185 | H27: 2399.465 | I27: 1237.152 | J27: 2353.701 | K27: 3559.579 | L27: 2584.71 | M27: 1871.9 | N27: 1076.064 | O27: 1273.372 | P27: 1562.132 | Q27: 1898.686 | R27: 2478.522 | S27: 2582.004 | T27: 2413.828 | Y27: 28699.787 | AC27: 40180.713
A28: 6012000000 | B28: FRAIS SUR VENTE SAFETY | C28: 1806.511 | D28: 1044.647 | E28: 2548.249 | F28: 18 | G28: 1520.49 | H28: 1142.806 | I28: 1076.794 | J28: 748.062 | K28: 519.968 | L28: 1138.236 | M28: 2428.284 | N28: 321.994 | O28: 674.078 | P28: 1184.016 | Q28: 695.055 | R28: 1177.788 | S28: 1748.384 | T28: 1110.064 | Y28: 6386.53 | AC28: 15401.87
A29: 6012000004 | B29: FRAIS SUR VENTE LEATHER | C29: 5366.066 | D29: 3948.617 | E29: 3333.707 | F29: 1191.164 | G29: 8746.871 | H29: -4029.287 | I29: 2682.706 | J29: 2659.688 | K29: 565.66 | L29: 3922.88 | M29: 4701.762 | N29: 1001.665 | O29: 3782.358 | P29: 6864.43 | Q29: 1711.416 | R29: 4724.394 | S29: 7999.952 | T29: 4131.304 | Y29: 23825.202 | AC29: 32616.749
A30: 6012000005 | B30: FRAIS SUR VENTE D-AIR | C30: 6294.144 | D30: 5597.763 | E30: 7542.861 | F30: 2004.73 | G30: 4791.672 | H30: 1736.66 | I30: 4185.432 | J30: 3373.833 | K30: 2344.928 | L30: 8496.468 | M30: 3914.434 | N30: 2998.981 | O30: 2103.21 | P30: 4108.186 | Q30: 2358.718 | R30: 1833.862 | S30: 6184.692 | T30: 4054.455 | Y30: 61176.384 | AC30: 114112.34
A31: 6241000001 | B31: TRANSPORT SUR ACHATS SAFETY | C31: 2766.431 | D31: 3572.32 | E31: 6401.328 | F31: 4271.238 | G31: 2868.263 | H31: 6167.114 | I31: 3805.737 | J31: 1095.12 | K31: 7870.134 | L31: 4766.8 | M31: 4890.594 | N31: 2303.433 | O31: 7698.28 | P31: 4016.216 | Q31: 4957.989 | R31: 5801.488 | S31: 11107.562 | T31: 12730.475 | Y31: 33862.915 | AC31: 40142.378
A32: 6241000004 | B32: TRANSPORT SUR ACHAT LEATHER | C32: 2733.264 | D32: 5557.68 | E32: 7017.74 | F32: 4477.824 | G32: 7038.83 | H32: 4249.674 | I32: 4043.222 | J32: 2976.462 | K32: 4287.824 | L32: 5134 | M32: 5757.356 | N32: 2489.295 | O32: 6756.82 | P32: 2395.164 | Q32: 5767.389 | R32: 4701.792 | S32: 3232.788 | T32: 4310.863 | Y32: 107861.6 | AC32: 39552.766
A33: 6241000005 | B33: TRANSPORT SUR ACHAT D-AIR | C33: 4070.725 | D33: 1772.88 | E33: 1075.312 | F33: 958.298 | G33: 690.346 | H33: 2928.381 | I33: 470.4 | J33: 978.138 | K33: 4114.696 | L33: 2488.8 | M33: 1952.45 | N33: 653.553 | O33: 1858.1 | P33: 1673.82 | Q33: 1318.901 | R33: 3004.036 | S33: 2151.418 | T33: 2561.151 | Y33: 34227.645 | AC33: 35980.749
A34: 6242000001 | B34: TRANSPORT SUR VENTES SAFETY | C34: 1425.573 | D34: 1895.72 | E34: 4695.397 | F34: 0 | G34: 2604.84 | H34: 2121.868 | I34: 1904.011 | J34: 1386.949 | K34: 930.648 | L34: 1923.856 | M34: 3962.53 | N34: 573.648 | O34: 1910.324 | P34: 1615.85 | Q34: 1103.244 | R34: 1165.724 | S34: 1910.188 | T34: 1173.23 | Y34: 14582.672 | AC34: 25062.792
A35: 6242000004 | B35: TRANSPORT SUR VENTE LEATHER | C35: 8228.763 | D35: 7084.88 | E35: 6336.277 | F35: 1928.864 | G35: 5788.44 | H35: 2580.651 | I35: 3934.526 | J35: 3170.203 | K35: 2791.944 | L35: 6963.37 | M35: 7762.54 | N35: 1835.673 | O35: 5732.06 | P35: 10165.15 | Q35: 2787.144 | R35: 5384.24 | S35: 8935.914 | T35: 4907.31 | Y35: 52920.295 | AC35: 55786.733
A36: 6242000005 | B36: TRANSPORT SUR VENTES D-AIR | C36: 5230.764 | D36: 3768.2 | E36: 11699.365 | F36: 1687.735 | G36: 6625.92 | H36: 1032.26 | I36: 3468.662 | J36: 2229.887 | K36: 2093.958 | L36: 6310.774 | M36: 4968.93 | N36: 3327.158 | O36: 3815.65 | P36: 2774.4 | Q36: 1916.161 | R36: 726.036 | S36: 3854.534 | T36: 3115.168 | Y36: 104868.87 | AC36: 114006.06

Sheet Capex
A1: CAPEX in TND
A3: Project/Category | B3: Done | C3: Approved | D3: Actual | F3: gen | G3: feb | H3: mar | I3: apr | J3: mag | K3: giu | L3: lug | M3: ago | N3: set | O3: ott | P3: dic | Q3: Totale complessivo
A4: Developments & Upgrade, Tools durable | B4: 49586.11 | D4: 49586.11 | F4: 15361.856 | G4: 2487 | H4: 335 | I4: 18371.58 | K4: 13030.674 | Q4: 49586.11
A5: IT equipments and software licence | B5: 6398 | D5: 6398 | G5: 2188 | H5: 335 | I5: 3875 | Q5: 6398
A6: Industrial equipments | B6: 42889.11 | D6: 42889.11 | F6: 15361.856 | I6: 14496.58 | K6: 13030.674 | Q6: 42889.11
A7: Shops and Office Furniture and equipments | B7: 299 | D7: 299 | G7: 299 | Q7: 299
A8: Risks assessment_Occupational health and safety | B8: 6944.0487 | C8: 22263.608 | D8: 29207.657 | I8: 2631.4999 | K8: 4312.5488 | L8: 22263.608 | Q8: 29207.657
A9: Generic plants | B9: 5933.5488 | C9: 22263.608 | D9: 28197.157 | I9: 1621 | K9: 4312.5488 | L9: 22263.608 | Q9: 28197.157
A10: Shops and Office Furniture and equipments | B10: 1010.4999 | D10: 1010.4999 | I10: 1010.4999 | Q10: 1010.4999
A11: DAIR SKI | B11: 340 | D11: 340 | F11: 340 | Q11: 340
A12: Machinery | B12: 340 | D12: 340 | F12: 340 | Q12: 340
A13: SMART GO | B13: 204510 | C13: 117938.4 | D13: 322448.4 | F13: 100640 | G13: 3230 | J13: 100640 | L13: 117938.4 | Q13: 322448.4
A14: Generic plants | C14: 19338.4 | D14: 19338.4 | L14: 19338.4 | Q14: 19338.4
A15: Industrial equipments | B15: 3230 | D15: 3230 | G15: 3230 | Q15: 3230
A16: Machinery | B16: 201280 | C16: 98600 | D16: 299880 | F16: 100640 | J16: 100640 | L16: 98600 | Q16: 299880
A17: MEL-T Space&Cost_Optimization_Plan 2026 | B17: 36186.45 | C17: 4650.02 | D17: 40836.47 | J17: 1459.357 | K17: 34727.093 | L17: 4650.02 | Q17: 40836.47
A18: Generic plants | B18: 35766.45 | D18: 35766.45 | J18: 1459.357 | K18: 34307.093 | Q18: 35766.45
A19: Industrial equipments | B19: 420 | D19: 420 | K19: 420 | Q19: 420
A20: Shops and Office Furniture and equipments | C20: 4650.02 | D20: 4650.02 | L20: 4650.02 | Q20: 4650.02
A21: Totale complessivo | B21: 297566.61 | C21: 144852.03 | D21: 442418.64 | F21: 116341.86 | G21: 5717 | H21: 335 | I21: 21003.08 | J21: 102099.36 | K21: 52070.316 | L21: 144852.03 | Q21: 442418.64
A24: Category/Capex | B24: Done | C24: Approved | D24: Actual
A25: Machinery | B25: 201620 | C25: 98600 | D25: 300220
A26: JACK M9 MACCHINA A CAMPO CON TESTA ROTANTE 360° Dotata di sistema anti groviglio filo crochet e dispostivo taglio laser JACK 9M+-SS-F11BF13-X ROTANTE LASER 140X95CM | B26: 201280 | C26: 98600 | D26: 299880
A27: RIFILATRICE GP15 | B27: 340 | D27: 340
A28: Generic plants | B28: 41699.999 | C28: 41602.008 | D28: 83302.007
A29: Adeguamento impianto area compressa | B29: 9435.562 | D29: 9435.562
A30: Armoire pour RIA DN33 | B30: 1621 | D30: 1621
A31: Communication & internet network installation and setup | B31: 5638.5 | D31: 5638.5
A32: Ergonomic mats, Ergomat Basic Bubble (Tappetti antifatica) | C32: 22263.608 | D32: 22263.608
A33: Ergonomic mats, Ergomat Basic Bubble (Tappetti antifatica) 600*900 | B33: 4312.5488 | D33: 4312.5488
A34: ESTRAZIONE FUMI TAGLIO LASER | B34: 5001.2 | D34: 5001.2
A35: Impianto Extraction fumo x 12 machines JACk | C35: 19338.4 | D35: 19338.4
A36: Lavori di impianto illuminizaizone & alimentazione elettrica | B36: 9731.831 | D36: 9731.831
A37: Lavori di smontaggio e montaggio scaffalatura magazzino | B37: 4500 | D37: 4500
A38: SYSTÈME DE DEGAGEMENT AIR MACHINE COUPE LASER | B38: 1459.357 | D38: 1459.357
A39: Industrial equipments | B39: 46539.11 | D39: 46539.11
A40: 12 SUPPORTO X TAVOLI CQ | B40: 420 | D40: 420
A41: Attrezzo manuale per fascette in mettalo MK9SST UNS 110-95000 | MK9SST-PA66GF30-GY | B41: 3230 | D41: 3230
A42: Batterie traction à plaques positives tubulaires 24 x 5 PzS 625 | B42: 15001 | D42: 15001
A43: Leather inspection POWERED TABLE MOTORISEE AVEC SIST.ECLAIRAGE INCLU cm 250x100x80-140 REGLABLE EN HAUTEUR ET INCLINATION | B43: 14496.58 | D43: 14496.58
A44: MINI RAYTEMP - THERMOMETRE INFRARIUGE ETI Plage de mesure -50° a 330°C | B44: 360.856 | D44: 360.856
A45: Piede di alimentazione / PIED ENTRAINEUR DKP 0867 221183 DX | B45: 2064.276 | D45: 2064.276
A46: Piede di alimentazione / PIED ENTRAINEUR DKP 0867 221193 SX | B46: 194.2848 | D46: 194.2848
A47: Piedino premistoffa con distanza dal bordo 2mm / PIED PRESSEUR DKP 0867 221064 DX | B47: 5492.0873 | D47: 5492.0873
... A59: Switch D-Link DES-8 ports | B59: 120 | D59: 120
A60: Shops and Office Furniture and equipments | B60: 1309.4999 | C60: 4650.02 | D60: 5959.5199
A61: BLOC A 3 TIROIRS | C61: 1238.4 | D61: 1238.4
A62: ENSEMBLE HELLO 4 POSTES SANS SEPARATIONS 242*122 | C62: 1135.2 | D62: 1135.2
A63: HAUT PARLEUR | B63: 299 | D63: 299
A64: Poubelle 120L | B64: 960 | D64: 960
A65: Poubelle 8L | B65: 50.4999 | D65: 50.4999
A66: SEPARATION HELLO FRONTALE 120X35 | C66: 256.28 | D66: 256.28
A67: SEPARATION HELLO LATERALE 122X35 | C67: 128.14 | D67: 128.14
A68: SIEGE LYON | C68: 1892 | D68: 1892
A69: Totale complessivo | B69: 297566.61 | C69: 144852.03 | D69: 442418.64

Sheet Ratio
A1: Production volume, Capacity utilisation and Efficiency ratios
A2: Production volume ratio
A3: The production volume ratio measures how the actual production output for a period, measured in standard direct labour hours, compares with the budgeted hours for a production cost centre. It is calculated as:
A4: BU | B4: SAFETY | C4: LEATHER | D4: D|AIR | E4: HELMET | F4: MEL-T | J4: SAFETY | K4: LEATHER | L4: D|AIR | M4: HELMET
A5: Std direct labour hours of actual production | B5: =J5/60 -> 11002.929 | C5: =K5/60 -> 71380.553 | D5: =L5/60 -> 7314.2108 | E5: =M5/60 -> 29798.762 | F5: =SUM(B5:E5) -> 119496.45 | G5: Including QC & Rework & Buy | J5: 660175.73 | K5: 4282833.2 | L5: 438852.65 | M5: 1787925.7
A6: budgeted direct labour hours | B6: =J6/60 -> 19177.476 | C6: =K6/60 -> 88273.746 | D6: =L6/60 -> 13465.973 | E6: =M6/60 -> 37920.756 | F6: =SUM(B6:E6) -> 158837.95 | G6: Including QC | J6: 1150648.6 | K6: 5296424.7 | L6: 807958.4 | M6: 2275245.3
A7: Production volume ratio | B7: =+B5/B6 -> 0.57374228 | C7: =+C5/C6 -> 0.80862722 | D7: =+D5/D6 -> 0.54316243 | E7: =+E5/E6 -> 0.78581666 | F7: =+F5/F6 -> 0.75231677 | H7: =+F7-100% -> -0.24768323
A8: A ratio of > 100% indicates above budget production volume and vice versa.
A10: Capacity utilisation ratio
A11: The capacity utilisation ratio measures whether the total direct labour hours worked in a production cost centre in a period was greater or less than what was budgeted. It is calculated as:
A12: BU | B12: SAFETY | C12: LEATHER | D12: D|AIR | E12: HELMET | F12: MEL-T
A13: Actual direct labour hours worked | B13: =J13/60 -> 4712.5 | C13: =K13/60 -> 112299 | D13: =L13/60 -> 9583.5 | E13: =M13/60 -> 35382.5 | F13: =SUM(B13:E13) -> 161977.5 | G13: Escluding Buy | J13: 282750 | K13: 6737940 | L13: 575010 | M13: 2122950
A14: budgeted direct labour hours | B14: =+B6 -> 19177.476 | C14: =+C6 -> 88273.746 | D14: =+D6 -> 13465.973 | E14: =+E6 -> 37920.756 | F14: =SUM(B14:E14) -> 158837.95
A15: Capacity utilisation ratio | B15: =+B13/B14 -> 0.24573098 | C15: =+C13/C14 -> 1.2721676 | D15: =+D13/D14 -> 0.71168268 | E15: =+E13/E14 -> 0.93306421 | F15: =+F13/F14 -> 1.0197657
A16: A ratio of > 100% indicates that more direct labour hours were worked than budget and vice versa.
A18: Efficiency ratio
A19: The efficiency ratio measures whether the production output for a period in a production cost centre took more or less direct labour time than expected. It is calculated as:
A20: BU | B20: SAFETY | C20: LEATHER | D20: D|AIR | E20: HELMET | F20: MEL-T
A21: Std direct labour hours of actual production | B21: =J21/60 -> 2962.5805 | C21: =+C5 -> 71380.553 | D21: =+D5 -> 7314.2108 | E21: =+E5 -> 29798.762 | F21: =SUM(B21:E21) -> 111456.11 | G21: Escluding Buy | J21: 177754.83
A22: actual direct labour hours worked | B22: =+B13 -> 4712.5 | C22: =+C13 -> 112299 | D22: =+D13 -> 9583.5 | E22: =+E13 -> 35382.5 | F22: =SUM(B22:E22) -> 161977.5 | G22: Escluding Buy
A23: Efficiency ratio | B23: =+B21/B22 -> 0.6286643 | C23: =+C21/C22 -> 0.63562946 | D23: =+D21/D22 -> 0.76320873 | E23: =+E21/E22 -> 0.84218926 | F23: =+F21/F22 -> 0.68809622 | H23: =+F23-79% -> -0.10190378
A24: A ratio of > 100% indicates greater labour efficiency than budgeted and vice versa.
A26: Analysis
A27: The actual output in the production cost centre ytd, measured in standard direct labour hours, was 75.2% lower than budget
A28: The under-budget production activity occurred despite the fact that utilisation of capacity was only 102.0% over of the budgeted utilisation. This was because direct labour efficiency was 10.2% worst than expected – ie fewer hours than expected were required to produce the actual output.
A29: The relationship between the three ratios can be demonstrated as follows:
A30: BU | B30: SAFETY | C30: LEATHER | D30: D|AIR | E30: HELMET | F30: MEL-T
A31: Capacity utilisation ratio | B31: =+B15 -> 0.24573098 | C31: =+C15 -> 1.2721676 | D31: =+D15 -> 0.71168268 | E31: =+E15 -> 0.93306421 | F31: =+F15 -> 1.0197657
A32: Efficiency ratio | B32: =+B23 -> 0.6286643 | C32: =+C23 -> 0.63562946 | D32: =+D23 -> 0.76320873 | E32: =+E23 -> 0.84218926 | F32: =+F23 -> 0.68809622
A33: Production volume ratio | B33: =+B31*B32*100 -> 15.448229 | C33: =+C31*C32*100 -> 80.862722 | D33: =+D31*D32*100 -> 54.316243 | E33: =+E31*E32*100 -> 78.581666 | F33: =+F31*F32*100 -> 70.169695
B34: =+B33-100 -> -84.551771 | C34: =+C33-100 -> -19.137278 | D34: =+D33-100 -> -45.683757 | E34: =+E33-100 -> -21.418334 | F34: =+F33-100 -> -29.830305
A37: Higher | C37: Lower
A38: over-budget | C38: under-budget
A39: better | C39: worst

Sheet Raio_calc-exp
A1: Product A - 12,400 units | E1: 12400 | F1: 0.1 | G1: =+E1*F1 -> 1240 | L1: Production volume ratio
A2: Product B - 10,000 units | E2: 10000 | F2: 0.04 | G2: =+E2*F2 -> 400 | L2: Std direct labour hours of actual production | M2: =+G11 -> 2614
A3: Product C - 18,500 units | E3: 18500 | F3: 0.05 | G3: =+E3*F3 -> 925 | L3: budgeted direct labour hours | M3: =+G4 -> 2565
A4: A | B4: 10 units | C4: 0.1 hours or 6 minutes | E4: =SUM(E1:E3) -> 40900 | G4: =SUM(G1:G3) -> 2565 | L4: Production volume ratio | M4: =+M2/M3 -> 1.0191033 | O4: =+M4-100% -> 0.019103314
A5: B | B5: 25 units | C5: 0.04 hours or 2.4 minutes
A6: C | B6: 20 units | C6: 0.05 hours or 3 minutes | L6: Capacity utilisation ratio
L7: Actual direct labour hours worked | M7: =+G12 -> 2430
A8: Product A - 13,300 units | E8: 13300 | F8: 0.1 | G8: =+E8*F8 -> 1330 | L8: budgeted direct labour hours | M8: =+G4 -> 2565
A9: Product B - 9,600 units | E9: 9600 | F9: 0.04 | G9: =+E9*F9 -> 384 | L9: Capacity utilisation ratio | M9: =+M7/M8 -> 0.94736842
A10: Product C - 18,000 units | E10: 18000 | F10: 0.05 | G10: =+E10*F10 -> 900
E11: =SUM(E8:E10) -> 40900 | G11: =SUM(G8:G10) -> 2614 | L11: Efficiency ratio
A12: Worked hrs | G12: 2430 | L12: Std direct labour hours of actual production | M12: =+G11 -> 2614
L13: actual direct labour hours worked | M13: =+G12 -> 2430
L14: Efficiency ratio | M14: =+M12/M13 -> 1.0757202 | O14: =+M14-100% -> 0.075720165
L16: Analysis
L17: It can be seen, from the above ratios, that the actual output in the production cost centre in the period, measured in standard direct labour hours, was 1.9% higher than budget (it may be noted that the total number of product units manufactured was the same as budget, but the units of one product are not comparable, in terms of production effort, with another).
L18: The over-budget production activity occurred despite the fact that utilisation of capacity was only 94.7% of the budgeted utilisation. This was because direct labour efficiency was 7.6% better than expected – ie fewer hours than expected were required to produce the actual output.
L19: The relationship between the three ratios can be demonstrated as follows:
L20: BU | M20: MEL-T
L21: Capacity utilisation ratio | M21: =+M9 -> 0.94736842
L22: Efficiency ratio | M22: =+M14 -> 1.0757202
L23: Production volume | M23: =(M21*M22)/100 -> 0.010191033
